Workbook

Sheet Changelog
A1: Version | B1: Date | C1: Notes | D1: Links
C2: Remember you need to download or copy the document before using it! Toolbar -> File -> Make a copy/Download This way you'll be able to change cell values in your own copy. Please DO NOT use cell comments to mark your progress by writing something like Y/N/Done/Yes/No, those are for feedback. | D2: =hyperlink("https://docs.google.com/spreadsheets/d/1W4P83Y9umpGs8DX9VtzXngE-Knhv8sndDhj1QpBIYUA/edit?usp=sharing" , "Link to main google sheet (If you're using web view or need a link to the main document use this)") -> Link to main google sheet (If you're using web view or need a link to the main document use this)
C3: Comments are open to everyone feel free to make suggestions or suggest fixes. Check the feedback and todo page first. | D3: =HYPERLINK("https://docs.google.com/spreadsheets/d/e/2PACX-1vSE_QojDmDDLYDmNQuy4Lkpl2PrJ_NB7DoCbMYJ_E8xFgKoBgMjNmWf1oiHz2Of9eQYrIpFdzQVgbw1/pubhtml", "Link to web view (Page loads much faster but CAN'T be copied or edited! Useful if you just want to use it as a refrence)") -> Link to web view (Page loads much faster but CAN'T be copied or edited! Useful if you just want to use it as a refrence)
A4: 1.1 | B4: 45606 | C4: Added perks gained from quests. Minor formatting changes and corrections
A5: 1.0 (finally) | B5: 45603 | C5: Added Anniversary Edition (CC) Quests. Added the percentages to track quests progession. Added Aniversary Edition (CC) Spells, Enchanting Effects, Alchemy ingrediants and Locations Alchemy Tab has been reorganized and list ingrediants effect duration and value multipliers if they have one. Also lists if the ingrediant is growable and how many are harvested this way Redid the formulas a bit so thay should be fine if you delete any Aniversary Edition content. I probably made some mistakes let me know if you see any.
B6: 44446 | C6: Added some quest items that can be pickpocketed back after completion.
B7: 44444 | C7: Unique horses added to Followers tab Fjola's Wedding Band added to Vanilla uniques Filters for sorting added
B8: 44438 | C8: Minor fixes to books tab. Added notes to a couple books with two versions Added notes to quest books that can be pickpocketed back Changed name of the book "The "Madmen" of the Reach to contain quotes Smithing perks notes fixed Fixed a lot of misprints on the Enchantments tab
B9: 44433 | C9: Added perk trees for Werewolf and Vampire Lord Bone hawk ring and amulet are removed from unique gear - craftable Enchanted ring added again to vanilla Uniques since its optional to turn it in for a quest. Layout of Perks tab changed to be more convenient. Conditional formatting fixed across the whole spreadsheet. Y/N changed to checkboxes on every tab except Quest because it needs to be redone anyway. Books type column fixed, skill books and spell tomes style changed for better sorting About 25 empty descriptions filled in in Books tab. Multiple link errors fixed and all of them are verified plus consistent now on all tabs except quests
B10: 44430 | C10: Removed Enchanted ring from vanilla Uniques - quest item Removed Chrysamere from vanilla Uniques - CC content Removed Tandil's Staff from vanilla Uniques - quest item Zephyr and Talor Dreth's robes are moved to Dawnguard Uniques Mutually exclusive items are now marked Added following list of vanilla uniques: https://pastebin.com/PZKAsnFa Added following Dawnguard uniques: Akaviri Sword Staff of Ruunvald Vampire Royal Armor Bone Hawk Ring Bone Hawk Amulet Added following Dragonborn uniques: Ancient Nordic Pickaxe Unique Gear tab added to Dashboard
B11: 44429 | C11: Added 5 paragons to Collectables tab Added following list of misc collectables : https://pastebin.com/WPE38dbh Collectables tab added to Dashboard
B12: 44426 | C12: Fixed some minor formatting issues Fixed spell location column Added missing tome ids for DLC spells
B13: 44423 | C13: Civil war locations are separated from the main list All fast travel markers verified Location added: The Chill Skuldafn Minor style and error fixes Formulas for locations tab replaced. Locations and Merchants tabs added to dashboard. Added "List" column to the Books tab with link to an explanation
B14: 44421 | C14: Removed duplicate book: Diary of Faire Agarwen Removed unobtainable books: Gallus's Journal The Secrets of Ragnvald Tolfdir's Book Unsent Afflicted Letter Added 3 Elder Scrolls as quest books Following list of books moved to quest books: https://pastebin.com/RwnZMCNK Fixed links to DG spell tomes Fixed style on books tab Removed Jarrin root from alchemy ingridients due to it being unique quest item. Added following spells: Summon Unbound Dremora Arniel Convection Summon Arniel's Shade Added prototype of the Dashboard tab with optional tracking. Requires testing and fixing other tabs to be fully complete
B15: 44410 | C15: Fixed incorrect spell levels Added missing spell Vision of the Tenth eye Added missing location East Empire company Warehouse Added 7 missing unique items. Theres probably more I didn't catch Added missing book Children of the All Maker Removed duplicate book The "Madmen" of the Reach Added a hidden quest Archery Practice given by Angi in outside Falkreath
A16: 0.5 | B16: 44283 | C16: Added missing Dragonborn and Dawngaurd books Marked some book which must be turned in for quests
B17: 44272 | C17: Added numbering to spell levels to make sorting easier Marked spells that all races start with as already collected Added missing location quest for Lair's retreat Fixed a few typos and some cleanup on quest tab Moved a couple quests to the correct location
B18: 44226 | C18: Fixed some typos, errors in book count formulas, and 1 missing book, slight formatting changes
A19: 0.4 | B19: 44095 | C19: Finished adding all missing DLC spells and spell tomes
B20: 43982 | C20: Finished adding links to Quest tab
B21: 43971 | C21: Corrected two locations which are not on the map Added Hunter's rest and Raven Rock Mine to locations
B22: 43959 | C22: Added missing Nightingale armor pieces to Unique Gear
B23: 43953 | C23: Added missing unique item Staff of Jerik Gaudurson Added some items to gather to the lists in quest tab Fixed conditional formatting on quests tab
B24: 43949 | C24: Added links to: spells tab, followers tab, shouts tab, alchemy ingrediants tab, merchants tab Removed two duplicate Unique items
A25: 0.3 | B25: 43947 | C25: Added spell tomes and links to Books sheet Fixed error in read books formula More edits for consistancy Added formula and conditional formatting for total thieves guild jobs.
B26: 43945 | C26: Added two missing Inns to the list of locations Fixed some slight errors in formulas
A27: 0.2 | B27: 43934 | C27: Made a few modifications for consistancy Added Merchants tab
A28: 0.1 | B28: 43369 | C28: First Release | D28: =HYPERLINK("https://docs.google.com/spreadsheets/d/1yHg39nzekiEgwuG07YFAhSequQBaKBT-6ArOAbQaOT4/edit?usp=sharing","link to original version (mostly here for crediting the original work)") -> link to original version (mostly here for crediting the original work)

Sheet TodoFeedback
A1: Completion Percentage | B1: Task Name
A2: Key (rough estmates): 0-10% = Not started/outlined only 11-90%= In progress 91-99%= Almost done; Needs final checks 100%= Complete
B3: Comments are open to everyone please suggest changes! Please put comments in the appropriate spot. On the specific item in the to do list if it relates to the page as a whole or the spot in the page itself that has a problem. I can only have one active comment thread per cell If one already exists just add to the thread.
B4: DO NOT close or open a comment that is not your own. I need those to fix issues and I will close them as needed.
B5: Comment on this cell with any NEW suggestions for features or fixes
B6: Comment on this cell for general discussion, feedback, questions on checklist
A7: 1 | B7: Add Dawnguard and Dragonborn Spells and Spell tomes
A8: 1 | B8: Add Dawnguard and Dragonborn Books
A9: 1 | B9: Add Dawnguard and Dragonborn ingredients and effects
A10: 1 | B10: Add a column for which leveled list each book is in to aid in finding them
A11: 1 | B11: Verify all fast-travel locations and check for duplicates
A12: 1 | B12: Verify that all recruitable followers are in the list and that they are properly marked
A13: 1 | B13: Find quest-related books which must be turned in and remove them from Books list
A14: 1 | B14: Add more data to the recruitable followers list (gender, race, etc.)
A15: 1 | B15: Fix spell locations column. I didn't make it I have no idea what all those letters mean.
A16: 1 | B16: Add more collectables to collectables tab. Only unique items that are not equippable should go here.
A17: 1 | B17: Verify all unique gear is in the list and remove any quest-specific items that must be turned in to complete the quest
A18: 1 | B18: Add werewolf and vampire perks to Perks tab
... A36: 0 | B36: Add a list of notes (probably not happening)

Sheet Dashboard
A1: Tab name | B1: Track | C1: Progress bar | G1: Completed % | H1: Left % | I1: Multiplier
A2: Total progression | B2: Y | C2: =IFERROR(__xludf.DUMMYFUNCTION("IF(B2=""Y"",SPARKLINE(G2:H2,{""charttype"",""bar"";""max"",1;""min"",0;""color1"",""#b7e1cd"";""color2"",""#f4c7c3""}),""Not tracked"")"),"") | G2: =round(SUMPRODUCT(G3:G14,I3:I14)/COUNTIF(I3:I14,"=1"),4) -> 0.001 | H2: =100%-G2 -> 0.999 | I2: =if(B2="Y",1,0) -> 1
A3: Quests | B3: Y | C3: =IFERROR(__xludf.DUMMYFUNCTION("IF(B3=""Y"",SPARKLINE(G3:H3,{""charttype"",""bar"";""max"",1;""min"",0;""color1"",""#b7e1cd"";""color2"",""#f4c7c3""}),""Not tracked"")"),"") | G3: =Quests!I1 -> 0 | H3: =100%-G3 -> 1 | I3: =if(B3="Y",1,0) -> 1
A4: Enchanting Effects | B4: Y | C4: =IFERROR(__xludf.DUMMYFUNCTION("IF(B4=""Y"",SPARKLINE(G4:H4,{""charttype"",""bar"";""max"",1;""min"",0;""color1"",""#b7e1cd"";""color2"",""#f4c7c3""}),""Not tracked"")"),"") | G4: ='Enchanting Effects'!B2 -> 0 | H4: =100%-G4 -> 1 | I4: =if(B4="Y",1,0) -> 1
A5: Spells | B5: Y | C5: =IFERROR(__xludf.DUMMYFUNCTION("IF(B5=""Y"",SPARKLINE(G5:H5,{""charttype"",""bar"";""max"",1;""min"",0;""color1"",""#b7e1cd"";""color2"",""#f4c7c3""}),""Not tracked"")"),"") | G5: =Spells!B2 -> 0.011976048 | H5: =100%-G5 -> 0.98802395 | I5: =if(B5="Y",1,0) -> 1
A6: Dragon Shouts | B6: Y | C6: =IFERROR(__xludf.DUMMYFUNCTION("IF(B6=""Y"",SPARKLINE(G6:H6,{""charttype"",""bar"";""max"",1;""min"",0;""color1"",""#b7e1cd"";""color2"",""#f4c7c3""}),""Not tracked"")"),"") | G6: ='Dragon Shouts'!A2 -> 0 | H6: =100%-G6 -> 1 | I6: =if(B6="Y",1,0) -> 1
A7: Locations | B7: Y | C7: =IFERROR(__xludf.DUMMYFUNCTION("IF(B7=""Y"",SPARKLINE(G7:H7,{""charttype"",""bar"";""max"",1;""min"",0;""color1"",""#b7e1cd"";""color2"",""#f4c7c3""}),""Not tracked"")"),"") | G7: =Locations!G4 -> 0 | H7: =100%-G7 -> 1 | I7: =if(B7="Y",1,0) -> 1
A8: Merchants Invested | B8: Y | C8: =IFERROR(__xludf.DUMMYFUNCTION("IF(B8=""Y"",SPARKLINE(G8:H8,{""charttype"",""bar"";""max"",1;""min"",0;""color1"",""#b7e1cd"";""color2"",""#f4c7c3""}),""Not tracked"")"),"") | G8: =Merchants!C3 -> 0 | H8: =100%-G8 -> 1 | I8: =if(B8="Y",1,0) -> 1
A9: Unique Gear | B9: Y | C9: =IFERROR(__xludf.DUMMYFUNCTION("IF(B9=""Y"",SPARKLINE(G9:H9,{""charttype"",""bar"";""max"",1;""min"",0;""color1"",""#b7e1cd"";""color2"",""#f4c7c3""}),""Not tracked"")"),"") | G9: =('Unique Gear'!D6 + 'Unique Gear'!D186 + 'Unique Gear'!D216)/3 -> 0 | H9: =100%-G9 -> 1 | I9: =if(B9="Y",1,0) -> 1
A10: Collectible Items | B10: Y | C10: =IFERROR(__xludf.DUMMYFUNCTION("IF(B10=""Y"",SPARKLINE(G10:H10,{""charttype"",""bar"";""max"",1;""min"",0;""color1"",""#b7e1cd"";""color2"",""#f4c7c3""}),""Not tracked"")"),"") | G10: ='Collectible Items'!A31 -> 0 | H10: =100%-G10 -> 1 | I10: =if(B10="Y",1,0) -> 1
A11: Books | B11: Y | C11: =IFERROR(__xludf.DUMMYFUNCTION("IF(B11=""Y"",SPARKLINE(G11:H11,{""charttype"",""bar"";""max"",1;""min"",0;""color1"",""#b7e1cd"";""color2"",""#f4c7c3""}),""Not tracked"")"),"") | G11: =(Books!G3 + Books!K3 + Books!M3 + Books!K601)/400 -> 0 | H11: =100%-G11 -> 1 | I11: =if(B11="Y",1,0) -> 1
A12: Recruitable Followers | B12: Y | C12: =IFERROR(__xludf.DUMMYFUNCTION("IF(B12=""Y"",SPARKLINE(G12:H12,{""charttype"",""bar"";""max"",1;""min"",0;""color1"",""#b7e1cd"";""color2"",""#f4c7c3""}),""Not tracked"")"),"") | G12: ='Recruitable Followers'!B2 -> 0 | H12: =100%-G12 -> 1 | I12: =if(B12="Y",1,0) -> 1
A13: Learned Alchemy Effects | B13: Y | C13: =IFERROR(__xludf.DUMMYFUNCTION("IF(B13=""Y"",SPARKLINE(G13:H13,{""charttype"",""bar"";""max"",1;""min"",0;""color1"",""#b7e1cd"";""color2"",""#f4c7c3""}),""Not tracked"")"),"") | G13: ='Learned Alchemy Effects'!A2 -> 0 | H13: =100%-G13 -> 1 | I13: =if(B13="Y",1,0) -> 1
A14: Perks | B14: Y | C14: =IFERROR(__xludf.DUMMYFUNCTION("IF(B14=""Y"",SPARKLINE(G14:H14,{""charttype"",""bar"";""max"",1;""min"",0;""color1"",""#b7e1cd"";""color2"",""#f4c7c3""}),""Not tracked"")"),"") | G14: =Perks!M4 -> 0 | H14: =100%-G14 -> 1 | I14: =if(B14="Y",1,0) -> 1

Sheet Credits
A1: Name | B1: Author | C1: Contributions
A2: Current Document | B2: Xboxiscrunchy | C2: Main author. Mostly formatting work honestly.
B3: Mezotaken | C3: Reformatting and many additions
A4: Skyrim 100% Completion Checklist v0.6 | B4: TheDJjams | C4: Quests tab formulas and creation club content
A5: Skyrim AE 100% Completion Checklist (v0.5) - AleHitti Version | B5: Alejandro Hitti | C5: Most of the creation club additions except the quests tab, Redoing Alchemy Tab
A6: IP - Skyrim AE 100% Completion Checklist (v0.5) - AshCamo Personal Edit | B6: Ashley Motter | C6: Most of the creation club additions except the quests tab
B7: Chasingcalliope | C7: Reformatted the books tab.
A8: Skyrim 100% Checklist (v0.01) | B8: bastionf***s | C8: Everything below was compiled here by bastionfucks
A9: =HYPERLINK("https://www.nexusmods.com/skyrim/mods/23188/?tab=images","Skyrim Books Checklist") -> Skyrim Books Checklist | B9: roachy1 | C9: The Books tab is based off of roachy1's work and the UESP wiki.
A10: =HYPERLINK("https://www.reddit.com/r/skyrim/comments/50d750/skyrim_character_planning_spreadsheet/","Skyrim Character Planning Spreadsheet") -> Skyrim Character Planning Spreadsheet | B10: porter2613 | C10: The Perks tab is based off of porter2613's work.
A11: =HYPERLINK("https://www.reddit.com/r/skyrim/comments/2r8nvw/all_skyrim_spells_broken_down_by_level_and_school/","All Skyrim Spells broken down by Level and School") -> All Skyrim Spells broken down by Level and School | B11: alanchavez | C11: The spells tab is a copy of alanchavez's work
A12: =HYPERLINK("https://www.nexusmods.com/skyrim/mods/51284/?tab=1&navtag=http%3A%2F%2Fwww.nexusmods.com%2Fskyrim%2Fajax%2Fmoddescription%2F%3Fid%3D51284%26preview%3D&pUp=1","Skyrim Quest Checklists and Quest Mod Checklists") -> Skyrim Quest Checklists and Quest Mod Checklists | B12: Sakr3d | C12: The Quests, Collectible Items, and Dragon Shout tabs are based off of Sakr3d's work.
A13: =HYPERLINK("https://www.reddit.com/r/skyrim/comments/mmtdf/filterable_list_of_alchemy_ingredients/","Filterable list of alchemy ingredients") -> Filterable list of alchemy ingredients | B13: u/Guysmiley777 | C13: The Alchemy tabis based of off Guysmiley777's wor.
A14: =HYPERLINK("https://en.uesp.net/wiki/Main_Page","The UESP Wiki") -> The UESP Wiki | B14: All Authors | C14: The UESP wiki was the best resource and I am forever in your debt.
A15: Bastionfucks built the orininal spreadsheet based on the work of the spreadsheets that other people made. I have added to his work by refining the spreadsheet and adding edits for consistency and some missing info
A16: =HYPERLINK("https://creativecommons.org/licenses/by/4.0/","This work is licensed under a Creative Commons Attribution 4.0 International License.") -> This work is licensed under a Creative Commons Attribution 4.0 International License.

Sheet Quests
A1: Y | B1: Anniversary Edition? | C1: S K Y R I M Q U E S T C H E C K L I S T | I1: =if(A1="Y", (average(I4,I27,D46,I46,D54,I75,I98,I132,I153,I178,I183,I214,I242,I257,I274,I300,I329,I360,I386,I400,I410,I441,I471,I519)),average(I4,I27,D46,I46,D54,I75,I98,I132,I153,I178,I183,I214,I242,I257,I274,I300,I329,I360,I386,I400,I410,I441,I471)) -> 0
A2: Side quests highlighted in orange. Level dependent quests highlighted in green. | H2: last updated: 2023.07.14
B3: Quest | D3: Description | I3: Giver
A4: Main Quest | I4: =(countif(A5:A23,"Y")/19) -> 0
A5: N | B5: =hyperlink("https://en.uesp.net/wiki/Skyrim:Unbound", "Unbound") -> Unbound | D5: Escape Imperial custody and a dragon raid. | I5: N/A
A6: N | B6: =hyperlink("https://en.uesp.net/wiki/Skyrim:Before_the_Storm", "Before the Storm") -> Before the Storm | D6: Inform the Jarl of Whiterun about the dragon attack on Helgen. | I6: Hadvar or Ralof
A7: N | B7: =hyperlink("https://en.uesp.net/wiki/Skyrim:Bleak_Falls_Barrow_(quest)", "Bleak Falls Barrow") -> Bleak Falls Barrow | D7: Retrieve the Dragonstone. | I7: Jarl Balgruuf
A8: N | B8: =hyperlink("https://en.uesp.net/wiki/Skyrim:Dragon_Rising", "Dragon Rising") -> Dragon Rising | D8: Investigate a Dragon sighting near Whiterun. | I8: Jarl Balgruuf
A9: N | B9: =hyperlink("https://en.uesp.net/wiki/Skyrim:The_Way_of_the_Voice", "The Way of the Voice") -> The Way of the Voice | D9: Meet the Greybeards. | I9: Jarl Balgruuf
A10: N | B10: =hyperlink("https://en.uesp.net/wiki/Skyrim:The_Horn_of_Jurgen_Windcaller", "The Horn of Jurgen Windcaller") -> The Horn of Jurgen Windcaller | D10: Retrieve a Greybeard artifact from Ustengrav. | I10: Arngeir
A11: N | B11: =hyperlink("https://en.uesp.net/wiki/Skyrim:A_Blade_in_the_Dark", "A Blade in the Dark") -> A Blade in the Dark | D11: Prove you are Dragonborn to Delphine by slaying the dragon Sahloknir. | I11: A Mysterious Note
A12: N | B12: =hyperlink("https://en.uesp.net/wiki/Skyrim:Diplomatic_Immunity", "Diplomatic Immunity") -> Diplomatic Immunity | D12: Infiltrate a party at the Thalmor Embassy. | I12: Delphine
A13: N | B13: =hyperlink("https://en.uesp.net/wiki/Skyrim:A_Cornered_Rat", "A Cornered Rat") -> A Cornered Rat | D13: Locate Esbern. | I13: Delphine
A14: N | B14: =hyperlink("https://en.uesp.net/wiki/Skyrim:Alduin's_Wall", "Alduin's Wall") -> Alduin's Wall | D14: Locate the prophecy within Sky Haven Temple. | I14: Esbern
A15: N | B15: =hyperlink("https://en.uesp.net/wiki/Skyrim:The_Throat_of_the_World", "The Throat of the World") -> The Throat of the World | D15: Receive a lesson from Paarthurnax. | I15: Arngeir
A16: N | B16: =hyperlink("https://en.uesp.net/wiki/Skyrim:Elder_Knowledge", "Elder Knowledge") -> Elder Knowledge | D16: Locate an Elder Scroll. | I16: Paarthurnax
A17: N | B17: =hyperlink("https://en.uesp.net/wiki/Skyrim:Alduin's_Bane", "Alduin's Bane") -> Alduin's Bane | D17: Exploit the Time Wound to learn Dragonrend. | I17: Paarthurnax
A18: N | B18: =hyperlink("https://en.uesp.net/wiki/Skyrim:The_Fallen", "The Fallen") -> The Fallen | D18: Capture and interrogate one of Alduin's allies. | I18: Paarthurnax Arngeir Esbern
A19: N | B19: =hyperlink("https://en.uesp.net/wiki/Skyrim:Paarthurnax_(quest)", "Paarthurnax (optional)") -> Paarthurnax (optional) | D19: Deal with a potential threat.
A20: N | B20: =hyperlink("https://en.uesp.net/wiki/Skyrim:Season_Unending", "Season Unending (optional)") -> Season Unending (optional) | D20: Enforce a ceasefire to secure Dragonsreach.
A21: N | B21: =hyperlink("https://en.uesp.net/wiki/Skyrim:The_World-Eater's_Eyrie", "The World-Eater's Eyrie") -> The World-Eater's Eyrie | D21: Battle through Skuldafn Temple to reach Alduin's portal to Sovngarde.
A22: N | B22: =hyperlink("https://en.uesp.net/wiki/Skyrim:Sovngarde_(quest)", "Sovngarde") -> Sovngarde | D22: Seek out Alduin within Sovngarde.
A23: N | B23: =hyperlink("https://en.uesp.net/wiki/Skyrim:Dragonslayer", "Dragonslayer") -> Dragonslayer | D23: Put an end to the World Eater.
A25: Faction Quests
A27: College of Winterhold | I27: =((countif(A29:A44,"Y")+countif(F29:F44,"Y"))/25) -> 0
A28: Main Quests | F28: Radiant Quests
A29: N | B29: =hyperlink("https://en.uesp.net/wiki/Skyrim:College_Objective_Quest", "College Objective Quest") -> College Objective Quest | C29: Visit the College of Winterhold. | F29: N | G29: =hyperlink("https://en.uesp.net/wiki/Skyrim:Enchanting_Pick-Up", "Enchanting Pick-Up") -> Enchanting Pick-Up | H29: Sergius wants you to pick-up an item from a client for enchanting. | I29: Sergius Turrianus
A30: N | B30: =hyperlink("https://en.uesp.net/wiki/Skyrim:First_Lessons", "First Lessons") -> First Lessons | C30: Join the College of Winterhold. | F30: N | G30: =hyperlink("https://en.uesp.net/wiki/Skyrim:Restocking_Soul_Gems", "Restocking Soul Gems") -> Restocking Soul Gems | H30: Help Sergius Turrianus to fill his stock with soul gems. | I30: Sergius Turrianus
A31: N | B31: =hyperlink("https://en.uesp.net/wiki/Skyrim:Under_Saarthal", "Under Saarthal") -> Under Saarthal | C31: Uncover the mysteries beneath this ancient ruin. | D31: Tolfdir | F31: N | G31: =hyperlink("https://en.uesp.net/wiki/Skyrim:Tolfdir_The_Absent-Minded", "Tolfdir The Absent-Minded") -> Tolfdir The Absent-Minded | H31: Help Tolfdir find his missing alembic. | I31: Tolfdir
A32: N | B32: =hyperlink("https://en.uesp.net/wiki/Skyrim:Hitting_the_Books", "Hitting the Books") -> Hitting the Books | C32: Find the books needed to identify the artifact found in Saarthal. | D32: Savos Aren | F32: N | G32: =hyperlink("https://en.uesp.net/wiki/Skyrim:Aftershock", "Aftershock") -> Aftershock | H32: Put an end to the rupture caused by the Eye of Magnus. | I32: Tolfdir
A33: N | B33: =hyperlink("https://en.uesp.net/wiki/Skyrim:Good_Intentions", "Good Intentions") -> Good Intentions | C33: Find and consult the Augur of Dunlain. | D33: Tolfdir | F33: N | G33: =hyperlink("https://en.uesp.net/wiki/Skyrim:Fetch_me_that_Book!", "Fetch me that Book!") -> Fetch me that Book! | H33: Fetch a book for Urag gro-Shub. | I33: Urag gro-Shub
A34: N | B34: =hyperlink("https://en.uesp.net/wiki/Skyrim:Revealing_the_Unseen", "Revealing the Unseen") -> Revealing the Unseen | C34: Discover the location of Magnus' staff. | D34: Mirabelle Ervine | F34: N | G34: =hyperlink("https://en.uesp.net/wiki/Skyrim:Shalidor's_Insights", "Shalidor's Insights") -> Shalidor's Insights | H34: Discover the writings of Shalidor and benefit from his wisdom. | I34: Urag gro-Shub
A35: N | B35: =hyperlink("https://en.uesp.net/wiki/Skyrim:Containment", "Containment") -> Containment | C35: Deal with the aftermath of the Eye's power surge. | F35: Master Skill Quests
A36: N | B36: =hyperlink("https://en.uesp.net/wiki/Skyrim:The_Staff_of_Magnus", "The Staff of Magnus") -> The Staff of Magnus | C36: Retrieve the Staff of Magnus. | D36: Mirabelle Ervine | F36: N | G36: =hyperlink("https://en.uesp.net/wiki/Skyrim:Alteration_Ritual_Spell", "Alteration Ritual Spell") -> Alteration Ritual Spell | H36: Find the Fang and use it to get Heartscales from a dragon. | I36: Tolfdir
A37: N | B37: =hyperlink("https://en.uesp.net/wiki/Skyrim:The_Eye_of_Magnus", "The Eye of Magnus") -> The Eye of Magnus | C37: Reclaim the College and contain the Eye. | F37: N | G37: =hyperlink("https://en.uesp.net/wiki/Skyrim:Conjuration_Ritual_Spell", "Conjuration Ritual Spell") -> Conjuration Ritual Spell | H37: Find a Sigil Stone by summoning a Daedra. | I37: Phinis Gestor
A38: Optional Quests | F38: N | G38: =hyperlink("https://en.uesp.net/wiki/Skyrim:Destruction_Ritual_Spell", "Destruction Ritual Spell") -> Destruction Ritual Spell | H38: Learn the most powerful Destruction spells in Skyrim. | I38: Faralda
A39: N | B39: =hyperlink("https://en.uesp.net/wiki/Skyrim:Arniel's_Endeavor", "Arniel's Endeavor") -> Arniel's Endeavor | C39: Uncover an ancient Dwemer secret. | D39: Arniel Gane | F39: N | G39: =hyperlink("https://en.uesp.net/wiki/Skyrim:Illusion_Ritual_Spell", "Illusion Ritual Spell") -> Illusion Ritual Spell | H39: Find some books about Illusion Magic to learn Master Spells. | I39: Drevis Neloren
A40: N | B40: =hyperlink("https://en.uesp.net/wiki/Skyrim:Brelyna's_Practice", "Brelyna's Practice") -> Brelyna's Practice | C40: Help Brelyna Maryon test spells. | D40: Brelyna Maryon | F40: N | G40: =hyperlink("https://en.uesp.net/wiki/Skyrim:Restoration_Ritual_Spell", "Restoration Ritual Spell") -> Restoration Ritual Spell | H40: Find the Augur of Dunlain and learn more about Restoration Magic. | I40: Colette Marence
A41: N | B41: =hyperlink("https://en.uesp.net/wiki/Skyrim:J'zargo's_Experiment", "J'zargo's Experiment") -> J'zargo's Experiment | C41: Help J'zargo test out a fiery new spell. | D41: J'zargo
A42: N | B42: =hyperlink("https://en.uesp.net/wiki/Skyrim:Onmund's_Request", "Onmund's Request") -> Onmund's Request | C42: Help Onmund negotiate the return of a family amulet. | D42: Onmund
A43: N | B43: =hyperlink("https://en.uesp.net/wiki/Skyrim:Out_of_Balance", "Out of Balance") -> Out of Balance | C43: Purify the focus points for magical energy around the College. | D43: Drevis Neloren
A44: N | B44: =hyperlink("https://en.uesp.net/wiki/Skyrim:Rejoining_the_College", "Rejoining the College") -> Rejoining the College | C44: Make amends for breaking the College of Winterhold rules. | D44: Kill a member of the college
A46: Bards College (Solitude) | D46: =(countif(A48:A53,"Y")/5) -> 0 | F46: Companions (Whiterun) | I46: =(countif(F48:F73,"Y")/19) -> 0
A47: Side Quests | F47: Quest Line
A48: N | B48: =hyperlink("https://en.uesp.net/wiki/Skyrim:Tending_the_Flames", "Tending the Flames") -> Tending the Flames | C48: Unveil the truth about a King; become a member of Bards College. | D48: Viarmo | F48: N | G48: Take Up Arms | H48: Prove you are worthy to join the Companions.
A49: Miscellaneous Quests | F49: Complete one radiant quest.
A50: N | B50: =hyperlink("https://en.uesp.net/wiki/Skyrim:Investigate_the_Bards_College", "Investigate the Bards College") -> Investigate the Bards College | C50: Investigate the Bards College. | D50: Any Bard | F50: N | G50: =hyperlink("https://en.uesp.net/wiki/Skyrim:Proving_Honor", "Proving Honor") -> Proving Honor | H50: Claim a Fragment of Wuuthrad from Dustman's Cairn. | I50: Skjor
A51: N | B51: =hyperlink("https://en.uesp.net/wiki/Skyrim:Finn's_Lute", "Finn's Lute") -> Finn's Lute | C51: Return an invaluable lute to Inge Six Fingers. | D51: Inge Six Fingers | F51: Complete one radiant quest.
A52: N | B52: =hyperlink("https://en.uesp.net/wiki/Skyrim:Pantea's_Flute", "Pantea's Flute") -> Pantea's Flute | C52: Find a missing flute for Pantea. | D52: Pantea Ateia | F52: N | G52: =hyperlink("https://en.uesp.net/wiki/Skyrim:The_Silver_Hand", "The Silver Hand") -> The Silver Hand | H52: Join the Circle and clear Gallows Rock of werewolf hunters. | I52: Skjor
A53: N | B53: =hyperlink("https://en.uesp.net/wiki/Skyrim:Rjorn's_Drum", "Rjorn's Drum") -> Rjorn's Drum | C53: Retrieve a drum for Giraud Gemane. | D53: Giraud Gemane | F53: Complete two radiant quests. At least one from Aela.
A54: Blades | D54: =(countif(A56:A58,"Y")/3) -> 0 | F54: N | G54: =hyperlink("https://en.uesp.net/wiki/Skyrim:Blood's_Honor", "Blood's Honor") -> Blood's Honor | H54: Claim the head of a Glenmoril Witch for Kodlak Whitemane. | I54: Kodlak Whitemane
A55: Miscellaneous Quests | F55: N | G55: =hyperlink("https://en.uesp.net/wiki/Skyrim:Purity_of_Revenge", "Purity of Revenge") -> Purity of Revenge | H55: Retrieve the Fragments of Wuuthrad. | I55: Vilkas
A56: N | B56: =hyperlink("https://en.uesp.net/wiki/Skyrim:Rebuilding_the_Blades", "Rebuilding the Blades") -> Rebuilding the Blades | C56: Recruit new members for the Blades. | D56: Delphine | F56: N | G56: =hyperlink("https://en.uesp.net/wiki/Skyrim:Glory_of_the_Dead", "Glory of the Dead") -> Glory of the Dead | H56: Cure Kodlak's spirit and prove yourself as a true Companion. | I56: Vilkas
A57: N | B57: =hyperlink("https://en.uesp.net/wiki/Skyrim:Dragon_Hunting", "Dragon Hunting") -> Dragon Hunting | C57: Kill a dragon at its lair. | D57: Esbern | F57: Radiant Quests
A58: N | B58: =hyperlink("https://en.uesp.net/wiki/Skyrim:Dragon_Research", "Dragon Research") -> Dragon Research | C58: Help Esbern complete his research on dragons. | D58: Esbern | F58: Aela the Huntress Radiant Quests
F59: N | G59: =hyperlink("https://en.uesp.net/wiki/Skyrim:Animal_Extermination", "Animal Extermination") -> Animal Extermination | H59: Fulfill a Companion contract to kill an invading beast. | I59: Aela
F60: N | G60: =hyperlink("https://en.uesp.net/wiki/Skyrim:Animal_Extermination", "Animal Extermination") -> Animal Extermination | H60: Fulfill a Companion contract to clear out a beast den. | I60: Aela
F61: N | G61: =hyperlink("https://en.uesp.net/wiki/Skyrim:Striking_the_Heart", "Striking the Heart") -> Striking the Heart | H61: Assassinate a Silver Hand leader. | I61: Aela
F62: N | G62: =hyperlink("https://en.uesp.net/wiki/Skyrim:Stealing_Plans", "Stealing Plans") -> Stealing Plans | H62: Search a Silver Hand hideout for information on their headquarters. | I62: Aela
F63: N | G63: =hyperlink("https://en.uesp.net/wiki/Skyrim:Retrieval", "Retrieval") -> Retrieval | H63: Retrieve a fragment of Wuuthrad. Unavailable after Glory of the Dead. | I63: Aela
F64: N | G64: =hyperlink("https://en.uesp.net/wiki/Skyrim:Totems_of_Hircine", "Totems of Hircine") -> Totems of Hircine | H64: Find a Totem of Hircine. Only available if you are a werewolf. | I64: Aela
F65: Farkas Radiant Quests
F66: N | G66: =hyperlink("https://en.uesp.net/wiki/Skyrim:Hired_Muscle", "Hired Muscle") -> Hired Muscle | H66: Fulfill a Companion contract bring a citizen back in line. | I66: Farkas
F67: N | G67: =hyperlink("https://en.uesp.net/wiki/Skyrim:Trouble_in_Skyrim", "Trouble in Skyrim") -> Trouble in Skyrim | H67: Fulfill a Companion contract to clear out a troublesome area. | I67: Farkas
F68: Skjor / Vilkas Radiant Quests
F69: N | G69: =hyperlink("https://en.uesp.net/wiki/Skyrim:Family_Heirloom", "Family Heirloom") -> Family Heirloom | H69: Fulfill a Companion contract to retrieve a stolen family heirloom. | I69: Skjor or Vilkas
F70: N | G70: =hyperlink("https://en.uesp.net/wiki/Skyrim:Escaped_Criminal", "Escaped Criminal") -> Escaped Criminal | H70: Fulfill a Companion contract to hunt down an escaped criminal. | I70: Skjor or Vilkas
F71: N | G71: =hyperlink("https://en.uesp.net/wiki/Skyrim:Rescue_Mission", "Rescue Mission") -> Rescue Mission | H71: Fulfill a Companion contract to rescue a kidnapped citizen. | I71: Skjor or Vilkas
F72: N | G72: =hyperlink("https://en.uesp.net/wiki/Skyrim:Purity", "Purity") -> Purity | H72: Help a member of the Circle give up their beast hood. | I72: Farkas or Vilkas
F73: N | G73: =hyperlink("https://en.uesp.net/wiki/Skyrim:Dragon_Seekers", "Dragon Seekers") -> Dragon Seekers | H73: Go to a dragon lair with Farkas or Vilkas and kill the dragon. | I73: Farkas or Vilkas
A75: The Dark Brotherhood | I75: =if(A92="N",((countif(A77:A96,"Y")+countif(F77:F96,"Y"))/30),1) -> 0
A76: Main Quests | F76: Contract Quests
A77: N | B77: =hyperlink("https://en.uesp.net/wiki/Skyrim:Delayed_Burial", "Delayed Burial (optional)") -> Delayed Burial (optional) | C77: Convince farmer to help a stranded jester outside of Whiterun. | D77: Cicero | F77: N | G77: =hyperlink("https://en.uesp.net/wiki/Skyrim:Kill_Narfi", "Kill Narfi") -> Kill Narfi | H77: Kill a hapless beggar in Ivarstead. | I77: Nazir
A78: N | B78: =hyperlink("https://en.uesp.net/wiki/Skyrim:Innocence_Lost", "Innocence Lost") -> Innocence Lost | C78: Help an orphaned child avoid being returned to a caretaker. | D78: Aventus Aretino | F78: N | G78: =hyperlink("https://en.uesp.net/wiki/Skyrim:Kill_Beitild", "Kill Beitild") -> Kill Beitild | H78: Resolve a feud in Dawnstar. | I78: Nazir
A79: N | B79: =hyperlink("https://en.uesp.net/wiki/Skyrim:With_Friends_Like_These...", "With Friends Like These...") -> With Friends Like These... | C79: Show you are willing to kill on command. | F79: N | G79: =hyperlink("https://en.uesp.net/wiki/Skyrim:Kill_Ennodius_Papius", "Kill Ennodius Papius") -> Kill Ennodius Papius | H79: Kill Ennodius Papius. | I79: Nazir
A80: N | B80: =hyperlink("https://en.uesp.net/wiki/Skyrim:Sanctuary", "Sanctuary") -> Sanctuary | C80: Pick up your first contracts as a Brotherhood member. | D80: Astrid | F80: N | G80: =hyperlink("https://en.uesp.net/wiki/Skyrim:Kill_Hern", "Kill Hern") -> Kill Hern | H80: Kill Hern, a reclusive vampire. | I80: Nazir
A81: N | B81: =hyperlink("https://en.uesp.net/wiki/Skyrim:Mourning_Never_Comes", "Mourning Never Comes") -> Mourning Never Comes | C81: Help Muiri get her revenge. | D81: Astrid | F81: N | G81: =hyperlink("https://en.uesp.net/wiki/Skyrim:Kill_Lurbuk", "Kill Lurbuk") -> Kill Lurbuk | H81: Silence a terrible bard, permanently. | I81: Nazir
A82: N | B82: =hyperlink("https://en.uesp.net/wiki/Skyrim:Whispers_in_the_Dark", "Whispers in the Dark") -> Whispers in the Dark | C82: Spy on the Night Mother's keeper. | D82: Astrid | F82: N | G82: =hyperlink("https://en.uesp.net/wiki/Skyrim:Kill_Deekus", "Kill Deekus") -> Kill Deekus | H82: Slay an Argonian looting a shipwreck. | I82: Nazir
A83: N | B83: =hyperlink("https://en.uesp.net/wiki/Skyrim:The_Silence_Has_Been_Broken", "The Silence Has Been Broken") -> The Silence Has Been Broken | C83: Meet Amaund Motierre inside Volunruud. | D83: Astrid | F83: N | G83: =hyperlink("https://en.uesp.net/wiki/Skyrim:Kill_Ma'randru-jo", "Kill Ma'randru-jo") -> Kill Ma'randru-jo | H83: Fulfill a Dark Brotherhood contract assassinate Ma'randru-jo. | I83: Nazir
A84: N | B84: =hyperlink("https://en.uesp.net/wiki/Skyrim:Bound_Until_Death", "Bound Until Death") -> Bound Until Death | C84: Assassinate Vittoria Vici at her own wedding. | D84: Astrid | F84: N | G84: =hyperlink("https://en.uesp.net/wiki/Skyrim:Kill_Anoriath", "Kill Anoriath") -> Kill Anoriath | H84: Fulfill a Dark Brotherhood contract assassinate Anoriath. | I84: Nazir
A85: N | B85: =hyperlink("https://en.uesp.net/wiki/Skyrim:Breaching_Security", "Breaching Security") -> Breaching Security | C85: Kill and frame the son of a high-ranking Imperial guard. | D85: Astrid | F85: N | G85: =hyperlink("https://en.uesp.net/wiki/Skyrim:Kill_Agnis", "Kill Agnis") -> Kill Agnis | H85: Fulfill a Dark Brotherhood contract assassinate Agnis. | I85: Nazir
A86: N | B86: =hyperlink("https://en.uesp.net/wiki/Skyrim:The_Cure_for_Madness", "The Cure for Madness") -> The Cure for Madness | C86: Confront the traitor among the Dark Brotherhood. | D86: Gabriella | F86: N | G86: =hyperlink("https://en.uesp.net/wiki/Skyrim:Kill_Maluril", "Kill Maluril") -> Kill Maluril | H86: Kill Maluril in Mzinchaleft. | I86: Nazir
A87: N | B87: =hyperlink("https://en.uesp.net/wiki/Skyrim:Recipe_for_Disaster", "Recipe for Disaster") -> Recipe for Disaster | C87: Assume the identity of the famous Gourmet. | D87: Astrid | F87: N | G87: =hyperlink("https://en.uesp.net/wiki/Skyrim:Kill_Helvard", "Kill Helvard") -> Kill Helvard | H87: Fulfill a Dark Brotherhood contract assassinate Helvard. | I87: Nazir
A88: N | B88: =hyperlink("https://en.uesp.net/wiki/Skyrim:To_Kill_an_Empire", "To Kill an Empire") -> To Kill an Empire | C88: Attempt to assassinate the Emperor. | D88: Astrid | F88: N | G88: =hyperlink("https://en.uesp.net/wiki/Skyrim:Kill_Safia", "Kill Safia") -> Kill Safia | H88: Kill a pirate captain on her own ship. | I88: Nazir
A89: N | B89: =hyperlink("https://en.uesp.net/wiki/Skyrim:Death_Incarnate", "Death Incarnate") -> Death Incarnate | C89: Assist Brotherhood members in the fight against assault. | F89: Miscellaneous Quests
A90: N | B90: =hyperlink("https://en.uesp.net/wiki/Skyrim:Hail_Sithis!", "Hail Sithis!") -> Hail Sithis! | C90: Fulfill the biggest contract in Brotherhood history. | D90: Night Mother | F90: N | G90: =hyperlink("https://en.uesp.net/wiki/Skyrim:Locate_the_Assassin_of_Old", "Locate the Assassin of Old") -> Locate the Assassin of Old | H90: Find Dark Brotherhood Assassin. (Quest activates if you successfully completed Breaching Security and received a bonus from Gabriella.) | I90: Olava the Feeble
A91: Other Quests
A92: N | B92: Destroy the Dark Brotherhood! | C92: Finish the Dark Brotherhood and rid Skyrim of their kind. | D92: After killing Astrid
A93: N | B93: Where You Hang Your Enemy's Head… | C93: Restore the Dark Brotherhood's sanctuary. | D93: Nazir | F93: N | G93: =hyperlink("https://en.uesp.net/wiki/Skyrim:Take_the_Hidden_Treasure", "Take the Hidden Treasure") -> Take the Hidden Treasure | H93: Torture the Brotherhood's prisoners for treasure. (This quest activates after purchasing the torture room for the Dawnstar Sanctuary.) | I93: Torture Victims
A94: Radiant Quests
A95: N | B95: Honor Thy Family | C95: Regain the trust of your fellow Assassins. | D95: Nazir
A96: N | B96: The Dark Brotherhood Forever | C96: Yet another child has prayed to their mother. | D96: Night Mother
A98: Thieves Guild (Riften) | I98: =((countif(A100:A125,"Y")+countif(F127:F130,"Y")+F109)/149) -> 0
A99: Main Quests | F99: Special Job Quests
A100: N | B100: =hyperlink("https://en.uesp.net/wiki/Skyrim:A_Chance_Arrangement", "A Chance Arrangement") -> A Chance Arrangement | C100: Help teach a merchant to mind his own business. | D100: Brynjolf | F100: Delvin's and Vex's quests become available once you join the guild, and can be repeated indefinitely. In addition to the monetary reward for completing these quests, they also count towards restoring the guild's status in Skyrim. In order to start the final Thieves Guild quest, Under New Management, you must complete five of these jobs in each of the other four main cities in Skyrim (Markarth, Solitude, Whiterun, and Windhelm), at which point Delvin will give you a special "reputation" job in that city. Completing these jobs also contributes to improving the guild.
A101: N | B101: =hyperlink("https://en.uesp.net/wiki/Skyrim:Taking_Care_of_Business", "Taking Care of Business") -> Taking Care of Business | C101: Help Brynjolf collect some debts for the Thieves Guild. | D101: Brynjolf
A102: N | B102: =hyperlink("https://en.uesp.net/wiki/Skyrim:Loud_and_Clear", "Loud and Clear") -> Loud and Clear | C102: Send a message to a former Thieves Guild client. | D102: Brynjolf
A103: N | B103: =hyperlink("https://en.uesp.net/wiki/Skyrim:Dampened_Spirits", "Dampened Spirits") -> Dampened Spirits | C103: Put Maven Black-Briar's competition out of business. | D103: Brynjolf or Maven
A104: N | B104: =hyperlink("https://en.uesp.net/wiki/Skyrim:Scoundrel's_Folly", "Scoundrel's Folly") -> Scoundrel's Folly | C104: Squeeze a reluctant informer for information. | D104: Mercer Frey | F104: Shadowmarks: Guild Safe Danger Escape Protected Shadowmarks: Fence Cache Loot Empty
A105: N | B105: =hyperlink("https://en.uesp.net/wiki/Skyrim:Speaking_With_Silence", "Speaking With Silence") -> Speaking With Silence | C105: Track down the Dunmer behind the Guild's misfortunes. | D105: Mercer Frey
...

Sheet Enchanting Effects
A1: Enchantment Name | B1: Obtained? | C1: Weapon | D1: Head | E1: Neck | F1: Chest | G1: Hands | H1: Finger | I1: Feet | J1: Shield | K1: School | L1: Base Magnitude | M1: Base Cost | N1: Disenchant
A2: - | B2: =(countif(B3:B60,"*Y*")/COUNTA(B3:B60)) -> 0 | C2: - | D2: - | E2: - | F2: - | G2: - | H2: - | I2: - | J2: - | K2: - | L2: - | M2: - | N2: -
A3: =HYPERLINK("https://en.uesp.net/wiki/Skyrim:Fortify_Alchemy","Fortify Alchemy") -> Fortify Alchemy | B3: N | C3: - | D3: X | E3: X | F3: - | G3: X | H3: X | I3: - | J3: - | K3: - | L3: Plus 8% potion strength | M3: 167 | N3: Bracers/Gauntlets and Helmets "of Alchemy" Muiri's Ring Ring of Pure Mixtures Dwarven Helment of Eminent Alteration
A4: =HYPERLINK("https://en.uesp.net/wiki/Skyrim:Fortify_Alteration","Fortify Alteration") -> Fortify Alteration | B4: N | C4: - | D4: X | E4: X | F4: X | G4: - | H4: X | I4: - | J4: - | K4: - | L4: Minus 8% casting cost | M4: 206 | N4: Armor, Bracers, and Helmets "of Alteration"
A5: =HYPERLINK("https://en.uesp.net/wiki/Skyrim:Enchanting_Effects","Fortify Alteration & Magicka Regen") -> Fortify Alteration & Magicka Regen | B5: N | C5: - | D5: - | E5: - | F5: X | G5: - | H5: - | I5: - | J5: - | K5: - | L5: Negative 5% casting cost Plus 10% Magicka Regen | M5: 176 | N5: Robes "of Alteration"
A6: =HYPERLINK("https://en.uesp.net/wiki/Skyrim:Fortify_Archery","Fortify Archery") -> Fortify Archery | B6: N | C6: - | D6: X | E6: X | F6: - | G6: X | H6: X | I6: - | J6: - | K6: - | L6: Plus 13% damage | M6: 352 | N6: Bracers/Gauntlets, Circlets, Helmets, and Rings "of Archery"
A7: =HYPERLINK("https://en.uesp.net/wiki/Skyrim:Fortify_Barter","Fortify Barter") -> Fortify Barter | B7: N | C7: - | D7: - | E7: X | F7: - | G7: - | H7: - | I7: - | J7: - | K7: - | L7: Prices Improved by 8% | M7: 206 | N7: Necklaces "of Haggling"
A8: =HYPERLINK("https://en.uesp.net/wiki/Skyrim:Fortify_Block","Fortify Block") -> Fortify Block | B8: N | C8: - | D8: - | E8: X | F8: - | G8: X | H8: X | I8: - | J8: X | K8: - | L8: Plus 13% damage blocked | M8: 235 | N8: Shields "of Blocking"
A9: =HYPERLINK("https://en.uesp.net/wiki/Skyrim:Fortify_Carry_Weight","Fortify Carry Weight") -> Fortify Carry Weight | B9: N | C9: - | D9: - | E9: X | F9: - | G9: X | H9: - | I9: X | J9: - | K9: - | L9: Plus 15 | M9: 393 | N9: Charmed Necklace Boots "of Brawn" Boots "of Hauling" Boots "of Lifting" Boots "of the Mammoth" Boots "of the Ox" Boots "of Strength"
A10: =HYPERLINK("https://en.uesp.net/wiki/Skyrim:Fortify_Conjuration","Fortify Conjuration") -> Fortify Conjuration | B10: N | C10: - | D10: X | E10: X | F10: X | G10: - | H10: X | I10: - | J10: - | K10: - | L10: Minus 8% casting cost | M10: 248 | N10: Armor, Bracers, and Helmet "of Conjuring" Circlets, and Imperial Helmets "of Conjuration"
A11: =HYPERLINK("https://en.uesp.net/wiki/Skyrim:Enchanting_Effects","Fortify Conjuration & Magicka Regen") -> Fortify Conjuration & Magicka Regen | B11: N | C11: - | D11: - | E11: - | F11: X | G11: - | H11: - | I11: - | J11: - | K11: - | L11: Negative 5% casting cost Plus 10% Magicka Regen | M11: 199 | N11: Robes and Vampire Armor "of Conjuration"
A12: =HYPERLINK("https://en.uesp.net/wiki/Skyrim:Fortify_Destruction","Fortify Destruction") -> Fortify Destruction | B12: N | C12: - | D12: X | E12: X | F12: X | G12: - | H12: X | I12: - | J12: - | K12: - | L12: Minus 8% casting cost | M12: 256 | N12: Armor, Bracers, Circlets, Helmets, Necklaces, and Rings "of Destruction" Thalmor Robes, Hooded Thalmor Robes
A13: =HYPERLINK("https://en.uesp.net/wiki/Skyrim:Enchanting_Effects","Fortify Destruction & Magicka Regen") -> Fortify Destruction & Magicka Regen | B13: N | C13: - | D13: - | E13: - | F13: X | G13: - | H13: - | I13: - | J13: - | K13: - | L13: Negative 5% casting cost Plus 10% Magicka Regen | M13: 205 | N13: Robes and Vampire Armor "of Destruction"
A14: =HYPERLINK("https://en.uesp.net/wiki/Skyrim:Regenerate_Health","Fortify Healing Rate") -> Fortify Healing Rate | B14: N | C14: - | D14: - | E14: X | F14: X | G14: - | H14: X | I14: - | J14: - | K14: - | L14: Plus 10% | M14: 251 | N14: Armor, Necklaces, and Rings "of Mending" Armor, Necklaces, and Rings "of Revival" Armor, Necklaces, and Rings "of Regeneration" Armor, Necklaces, and Rings "of Remedy"
A15: =HYPERLINK("https://en.uesp.net/wiki/Skyrim:Fortify_Health","Fortify Health") -> Fortify Health | B15: N | C15: - | D15: - | E15: X | F15: X | G15: - | H15: X | I15: - | J15: X | K15: - | L15: Plus 20 | M15: 202 | N15: Armor "of Health" Enchanted Ring
A16: =HYPERLINK("https://en.uesp.net/wiki/Skyrim:Fortify_Heavy_Armor","Fortify Heavy Armor") -> Fortify Heavy Armor | B16: N | C16: - | D16: - | E16: X | F16: X | G16: X | H16: X | I16: - | J16: - | K16: - | L16: Plus 8 Skill | M16: 157 | N16: Armor and Necklaces "of the Knight"
A17: =HYPERLINK("https://en.uesp.net/wiki/Skyrim:Fortify_Illusion","Fortify Illusion") -> Fortify Illusion | B17: N | C17: - | D17: X | E17: X | F17: X | G17: - | H17: X | I17: - | J17: - | K17: - | L17: Minus 8% casting cost | M17: 226 | N17: Armor, and Helmets "of Illusion"
A18: =HYPERLINK("https://en.uesp.net/wiki/Skyrim:Enchanting_Effects","Fortify Illusion & Magicka Regen") -> Fortify Illusion & Magicka Regen | B18: N | C18: - | D18: - | E18: - | F18: X | G18: - | H18: - | I18: - | J18: - | K18: - | L18: Negative 5% casting cost Plus 10% Magicka Regen | M18: 182 | N18: Robes "of Illusion"
A19: =HYPERLINK("https://en.uesp.net/wiki/Skyrim:Fortify_Light_Armor","Fortify Light Armor") -> Fortify Light Armor | B19: N | C19: - | D19: - | E19: X | F19: X | G19: X | H19: X | I19: - | J19: - | K19: - | L19: Plus 8 Skill | M19: 137 | N19: Armor and Necklaces "of the Squire"
A20: =HYPERLINK("https://en.uesp.net/wiki/Skyrim:Fortify_Lockpicking","Fortify Lockpicking") -> Fortify Lockpicking | B20: N | C20: - | D20: X | E20: X | F20: - | G20: X | H20: X | I20: - | J20: - | K20: - | L20: Plus 13% | M20: 168 | N20: Bracers/Gauntlets and Necklaces "of Lockpicking"
A21: =HYPERLINK("https://en.uesp.net/wiki/Skyrim:Fortify_Magicka","Fortify Magicka") -> Fortify Magicka | B21: N | C21: - | D21: X | E21: X | F21: - | G21: X | H21: X | I21: - | J21: - | K21: - | L21: Plus 20 | M21: 188 | N21: Circlets, Helmets, and Rings "of Magicka" Adept Hood Amulet of Julianos Apprentice Hood Black Mage Hood Executioner's Hood Mage's Circlet Novice Hood Savos Aren's Amulet
A22: =HYPERLINK("https://en.uesp.net/wiki/Skyrim:Regenerate_Magicka","Fortify Magicka Regen") -> Fortify Magicka Regen | B22: N | C22: - | D22: X | E22: - | F22: X | G22: - | H22: X | I22: - | J22: - | K22: - | L22: Plus 20% | M22: 53 | N22: Helmets, Rings, and Robes "of Recovery" Armor, Helmets, Rings, and Robes "of Replenishing" Helmets, Rings, and Robes "of Resurgence" Adept Robes Apprentice Robes Black Mage Robes Blue Mage Robes Expert Robes Hooded Black Mage Robes Hooded Necromancer Robes Master Robes Mythic Dawn Robes Necromancer Robes Novice Robes
A23: =HYPERLINK("https://en.uesp.net/wiki/Skyrim:Fortify_One-handed","Fortify One-Handed") -> Fortify One-Handed | B23: N | C23: - | D23: - | E23: X | F23: - | G23: X | H23: X | I23: X | J23: - | K23: - | L23: Plus 13% damage | M23: 369 | N23: Bracers/Gauntlets, Necklaces, and Rings "of Wielding"
A24: =HYPERLINK("https://en.uesp.net/wiki/Skyrim:Fortify_Pickpocket","Fortify Pickpocket") -> Fortify Pickpocket | B24: N | C24: - | D24: - | E24: X | F24: - | G24: X | H24: X | I24: X | J24: - | K24: - | L24: Plus 13% mulitplier to success chance | M24: 184 | N24: Bracers/Gauntlets and Rings "of Deft Hands"
A25: =HYPERLINK("https://en.uesp.net/wiki/Skyrim:Fortify_Restoration","Fortify Restoration") -> Fortify Restoration | B25: N | C25: - | D25: X | E25: X | F25: X | G25: - | H25: X | I25: - | J25: - | K25: - | L25: Minus 8% casting cost | M25: 231 | N25: Armor, Circlets, Helmets, and Rings "of Restoration"
A26: =HYPERLINK("https://en.uesp.net/wiki/Skyrim:Enchanting_Effects","Fortify Restoration & Magicka Regen") -> Fortify Restoration & Magicka Regen | B26: N | C26: - | D26: - | E26: - | F26: X | G26: - | H26: - | I26: - | J26: - | K26: - | L26: Negative 5% casting cost Plus 10% Magicka Regen | M26: 193 | N26: Robes "of Restoration"
A27: =HYPERLINK("https://en.uesp.net/wiki/Skyrim:Fortify_Smithing","Fortify Smithing") -> Fortify Smithing | B27: N | C27: - | D27: - | E27: X | F27: X | G27: X | H27: X | I27: - | J27: - | K27: - | L27: Plus 8% tempering strength | M27: 236 | N27: Bracers/Gauntlet, Necklaces, and rings "of Smithing" Silver-Blood Family Ring The Forgemaster's Fingers
A28: =HYPERLINK("https://en.uesp.net/wiki/Skyrim:Fortify_Sneak","Fortify Sneak") -> Fortify Sneak | B28: N | C28: - | D28: - | E28: X | F28: - | G28: X | H28: X | I28: X | J28: - | K28: - | L28: Plus 13% | M28: 672 | N28: Boots, Necklaces, and Rings "of Sneaking"
A29: =HYPERLINK("https://en.uesp.net/wiki/Skyrim:Fortify_Stamina","Fortify Stamina") -> Fortify Stamina | B29: N | C29: - | D29: - | E29: X | F29: X | G29: - | H29: X | I29: X | J29: - | K29: - | L29: Plus 20 | M29: 161 | N29: Armor, Boots, Necklaces, and Rings "of Stamina"
A30: =HYPERLINK("https://en.uesp.net/wiki/Skyrim:Regenerate_Stamina","Fortify Stamina Regen") -> Fortify Stamina Regen | B30: N | C30: - | D30: - | E30: X | F30: X | G30: - | H30: X | I30: X | J30: - | K30: - | L30: Plus 10% | M30: 125 | N30: Armor, Necklaces and Rings "of Invigoration"Armor Necklaces and Rings "of Recuperation" Armor, Necklaces and Rings "of Rejuvenation" Armor, Necklaces and Rings "of Renewal"
A31: =HYPERLINK("https://en.uesp.net/wiki/Skyrim:Fortify_Two-handed","Fortify Two-Handed") -> Fortify Two-Handed | B31: N | C31: - | D31: - | E31: X | F31: - | G31: X | H31: X | I31: X | J31: - | K31: - | L31: Plus 13% damage | M31: 369 | N31: Bracers/Gauntlets, Necklaces, and Rings "of Sure Grip" Ironhand Gauntlets Ring of Minor Striking
A32: =HYPERLINK("https://en.uesp.net/wiki/Skyrim:Fortify_Unarmed_Damage","Fortify Unarmed") -> Fortify Unarmed | B32: N | C32: - | D32: - | E32: - | F32: - | G32: X | H32: X | I32: - | J32: - | K32: - | L32: Plus 5 damage | M32: 88 | N32: Gloves of the Pugilist
A33: =HYPERLINK("https://en.uesp.net/wiki/Skyrim:Muffle_(effect)","Muffle") -> Muffle | B33: N | C33: - | D33: - | E33: - | F33: - | G33: - | H33: - | I33: X | J33: - | K33: - | L33: N/A | M33: 105 | N33: Boots "of Muffling"
A34: =HYPERLINK("https://en.uesp.net/wiki/Skyrim:Resist_Disease","Resist Disease") -> Resist Disease | B34: N | C34: - | D34: - | E34: X | F34: X | G34: - | H34: X | I34: - | J34: X | K34: - | L34: Plus 25% | M34: 55 | N34: Necklace of Disease Immunity Necklace of Disease Resistance
A35: =HYPERLINK("https://en.uesp.net/wiki/Skyrim:Resist_Fire","Resist Fire") -> Resist Fire | B35: N | C35: - | D35: - | E35: X | F35: - | G35: - | H35: X | I35: X | J35: X | K35: - | L35: Plus 15% | M35: 176 | N35: Boots, Necklaces, and Shields "of Dwindling Flames" Boots, Necklaces, and Shields "of Fire Abatement" Boots, Necklaces, and Shields "of Fire Suppression" Boots, Necklaces, and Shields "of Flame Suppression" Boots, Necklaces, and Shields "of the Firewalker" Boots, Necklaces, and Shields "of Resist Fire" Boots, Necklaces, and Shields "of Waning Fire" Ancient Helm of the Unburned Steel Shield of Fire Resist
A36: =HYPERLINK("https://en.uesp.net/wiki/Skyrim:Resist_Frost","Resist Frost") -> Resist Frost | B36: N | C36: - | D36: - | E36: X | F36: - | G36: - | H36: X | I36: X | J36: X | K36: - | L36: Plus 15% | M36: 186 | N36: Armor, Boots, Necklaces, and Shields "of Dwindling Frost" Armor, Boots, Necklaces, and Shields "of Frost Abatement" Armor, Boots, Necklaces, and Shields "of Frost Suppression" Armor, Boots, Necklaces, and Shields "of Resist Frost" Armor, Boots, Necklaces, and Shields "of Waning Frost" Armor, Boots, Necklaces, and Shields "of Warmth" Helm of Yngol Herebane's Fortress Necklace of Frost Resist
A37: =HYPERLINK("https://en.uesp.net/wiki/Skyrim:Resist_Magic","Resist Magic (Two Versions)") -> Resist Magic (Two Versions) | B37: N | C37: - | D37: - | E37: X | F37: - | G37: - | H37: X | I37: - | J37: X | K37: - | L37: Plus 8% | M37: 187 | N37: Necklaces, Rings, and Shields "of Dwindling Magic" Necklaces, Rings, and Shields "of Resist Magic" Necklaces, Rings, and Shields "of Waning Magic" Necklaces, Rings, and Shields "of Magic Abatement" Necklaces, Rings, and Shields "of Magic Suppression" Necklaces, Rings, and Shields "of Nullification" A second version of the effect is available from the Shield of Solitude
A38: =HYPERLINK("https://en.uesp.net/wiki/Skyrim:Resist_Poison","Resist Poison") -> Resist Poison | B38: N | C38: - | D38: - | E38: X | F38: X | G38: - | H38: X | I38: - | J38: X | K38: - | L38: Plus 15% | M38: 39 | N38: Necklace of Poison Immunity Necklace of Poison Resistance
A39: =HYPERLINK("https://en.uesp.net/wiki/Skyrim:Resist_Shock","Resist Shock") -> Resist Shock | B39: N | C39: - | D39: - | E39: X | F39: - | G39: - | H39: X | I39: X | J39: X | K39: - | L39: Plus 15% | M39: 196 | N39: Boots, Necklaces, and Shields "of Dwindling Shock" Boots, Necklaces, and Shields "of Grounding" Boots, Necklaces, and Shields "of Resist Shock" Boots, Necklaces, and Shields "of Shock Abatement" Boots, Necklaces, and Shields "of Shock Suppression" Boots, Necklaces, and Shields "of Waning Shock"
A40: =HYPERLINK("https://en.uesp.net/wiki/Skyrim:Waterbreathing_(effect)","Waterbreathing") -> Waterbreathing | B40: N | C40: - | D40: X | E40: X | F40: - | G40: - | H40: X | I40: - | J40: - | K40: - | L40: N/A | M40: 100 | N40: Circlets, Helmets, and Necklaces "of Waterbreathing"
A41: =HYPERLINK("https://en.uesp.net/wiki/Skyrim:Absorb_Health","Absorb Health") -> Absorb Health | B41: N | C41: X | D41: - | E41: - | F41: - | G41: - | H41: - | I41: - | J41: - | K41: Destruction | L41: 8 | M41: 31 | N41: Weapons "of Absorption" Weapons "of Consuming" Weapons "of Devouring" Weapons "of Leeching" Weapons "of the Vampire" Blade of Woe Drainblood Battleaxe Gauldur Blackblade
A42: =HYPERLINK("https://en.uesp.net/wiki/Skyrim:Absorb_Magicka","Absorb Magicka") -> Absorb Magicka | B42: N | C42: X | D42: - | E42: - | F42: - | G42: - | H42: - | I42: - | J42: - | K42: Destruction | L42: 10 | M42: 21 | N42: Weapons "of the Sorcerer" Weapons "of Evoking" Weapons "of Harrowing" Weapons "of Siphoning" Weapons "of Winnowing" Gauldur Blackbow Drainspell Bow
A43: =HYPERLINK("https://en.uesp.net/wiki/Skyrim:Absorb_Stamina","Absorb Stamina") -> Absorb Stamina | B43: N | C43: X | D43: - | E43: - | F43: - | G43: - | H43: - | I43: - | J43: - | K43: Destruction | L43: 10 | M43: 22 | N43: Weapons "of Subsuming" Weapons "of Garnering" Weapons "of Gleaning" Weapons "of Harvesting" Weapons "of Reaping" Drainheart Sword
A44: =HYPERLINK("https://en.uesp.net/wiki/Skyrim:Banish","Banish") -> Banish | B44: N | C44: X | D44: - | E44: - | F44: - | G44: - | H44: - | I44: - | J44: - | K44: Conjuration | L44: Level 10 | M44: 113 | N44: Weapons "of Annihilating" Weapons "of Banishing" Weapons "of Expelling"
A45: =HYPERLINK("https://en.uesp.net/wiki/Dragonborn:Chaos_Damage","Chaos Damage (Dragonborn Only)") -> Chaos Damage (Dragonborn Only) | B45: N | C45: X | D45: - | E45: - | F45: - | G45: - | H45: - | I45: - | J45: - | K45: Destruction | L45: 10 | M45: 19 | N45: Weapons "of Chaos" Weapons "of Extreme Chaos" Weapons "of High Chaos" Weapons "of Ultimate Chaos" Champion's Cudgel
A46: =HYPERLINK("https://en.uesp.net/wiki/Skyrim:Damage_Stamina","Damage Stamina") -> Damage Stamina | B46: N | C46: X | D46: - | E46: - | F46: - | G46: - | H46: - | I46: - | J46: - | K46: Destruction | L46: 15 | M46: 29 | N46: Weapons "of Debilitation" Weapons "of Exhaustion" Weapons "of Fatigue" Weapons "of Lethargy" Weapons "of Torpor" Weapons "of Weariness" Froki's Bow
A47: =HYPERLINK("https://en.uesp.net/wiki/Skyrim:Fear_(effect)","Fear") -> Fear | B47: N | C47: X | D47: - | E47: - | F47: - | G47: - | H47: - | I47: - | J47: - | K47: Illusion | L47: Level 10, for 30 seconds | M47: 16 | N47: Weapons "of Cowardice" Weapons "of Despair" Weapons "of Dismay" Weapons "of Dread" Weapons "of Fear" Weapons "of Terror"
A48: =HYPERLINK("https://en.uesp.net/wiki/Skyrim:Fiery_Soul_Trap","Fiery Soul Trap") -> Fiery Soul Trap | B48: N | C48: X | D48: - | E48: - | F48: - | G48: - | H48: - | I48: - | J48: - | K48: Conjuration | L48: 5 seconds 10 fire damage | M48: 11 | N48: Steel Battleaxe of Fiery Souls
A49: =HYPERLINK("https://en.uesp.net/wiki/Skyrim:Fire_Damage","Fire Damage") -> Fire Damage | B49: N | C49: X | D49: - | E49: - | F49: - | G49: - | H49: - | I49: - | J49: - | K49: Destruction | L49: 10 | M49: 11 | N49: Weapons "of Burning" Weapons "of Scorching" Weapons "of Embers" Weapons "of Fire" Weapons "of Flames" Weapons "of the Blaze" Weapons "of the Inferno"
A50: =HYPERLINK("https://en.uesp.net/wiki/Skyrim:Frost_Damage","Frost Damage") -> Frost Damage | B50: N | C50: X | D50: - | E50: - | F50: - | G50: - | H50: - | I50: - | J50: - | K50: Destruction | L50: 10 50% slow for 2 seconds | M50: 13 | N50: Weapons "of Chills" Weapons "of Blizzards" Weapons "of Cold" Weapons "of Freezing" Weapons "of Frost" Weapons "of Ice" Weapons "of Winter" Aegisbane Eduj Firiniel's End Grimsever Okin
A51: =HYPERLINK("https://en.uesp.net/wiki/Skyrim:Huntsman%27s_Prowess","Huntsman's Prowess") -> Huntsman's Prowess | B51: N | C51: X | D51: - | E51: - | F51: - | G51: - | H51: - | I51: - | J51: - | K51: Destruction | L51: Plus 3 damage vs. Animals | M51: 3 | N51: Poacher's Axe
A52: =HYPERLINK("https://en.uesp.net/wiki/Skyrim:Damage_Magicka","Magicka Damage") -> Magicka Damage | B52: N | C52: X | D52: - | E52: - | F52: - | G52: - | H52: - | I52: - | J52: - | K52: Destruction | L52: 15 | M52: 15 | N52: Weapons "of Depleting" Weapons "of Diminishing' Weapons "of Draining" Weapons "of Enervating" Weapons "of Nullifying" Weapons "of Sapping"
A53: =HYPERLINK("https://en.uesp.net/wiki/Skyrim:Paralyze_(effect)","Paralyze") -> Paralyze | B53: N | C53: X | D53: - | E53: - | F53: - | G53: - | H53: - | I53: - | J53: - | K53: Alteration | L53: 26% chance for 2 secondds | M53: 34 | N53: Weapons "of Immobilizing" Weapons ""of Petrifying" Weapons "of Stunning"
A54: =HYPERLINK("https://en.uesp.net/wiki/Skyrim:Enchanting_Effects#cite_ref-FixedMagnitude_3-0","Shock Damage") -> Shock Damage | B54: N | C54: X | D54: - | E54: - | F54: - | G54: - | H54: - | I54: - | J54: - | K54: Destruction | L54: 10 | M54: 14 | N54: Weapons "of Sparks" Weapons "of Arcing" Weapons "of Shocks" Weapons "of Thunderbolts" Weapons "of Lightning" Weapons "of Storms"
A55: =HYPERLINK("https://en.uesp.net/wiki/Skyrim:Silent_Moons_Enchant","Silent Moons Enchant") -> Silent Moons Enchant | B55: N | C55: X | D55: - | E55: - | F55: - | G55: - | H55: - | I55: - | J55: - | K55: Destruction | L55: Plus 10 damage between 9pm and 5am | M55: 5 | N55: Lunar Iron Mace Lunar Iron Sword Lunar Iron War Axe Lunar Steel Mace Lunar Steel Sword Lunar Steel War Axe
A56: =HYPERLINK("https://en.uesp.net/wiki/Skyrim:Smithing_Expertise","Smithing Expertise") -> Smithing Expertise | B56: N | C56: X | D56: - | E56: - | F56: - | G56: - | H56: - | I56: - | J56: - | K56: Destruction | L56: 5 shock damage +5 Smithing | M56: 11 | N56: Notched Pickaxe
A57: =HYPERLINK("https://en.uesp.net/wiki/Skyrim:Soul_Trap_(effect)","Soul Trap") -> Soul Trap | B57: N | C57: X | D57: - | E57: - | F57: - | G57: - | H57: - | I57: - | J57: - | K57: Conjuration | L57: 4 seconds | M57: 9 | N57: Weapons "of Animus" Weapons "of Binding" Weapons "of Damnation" Weapons "of Malediction" Weapons "of Soul Snares" Weapons "of Souls"
A58: =HYPERLINK("https://en.uesp.net/wiki/Skyrim:Turn_Undead_(effect)","Turn Undead") -> Turn Undead | B58: N | C58: X | D58: - | E58: - | F58: - | G58: - | H58: - | I58: - | J58: - | K58: Restoration | L58: Level 10, for 30 seconds | M58: 29 | N58: Blessed weapons Hallowed weapons Holy weapons Reverent weapons Sanctified weapons Virtuous weapons
A59: =HYPERLINK("https://en.uesp.net/w/index.php?title=Skyrim:Dark_Moon&action=edit&redlink=1 ", "Dark Moon (AE)") -> Dark Moon (AE) | B59: N | C59: - | D59: X | E59: X | F59: - | G59: X | H59: X | I59: - | J59: - | K59: - | L59: Plus 40 Magicka Minus 30% Health Regen | M59: 404 | N59: Elite and Ascendant "Necromancer Hoods" (From Creation "Necromatic Grimoire")
A60: =HYPERLINK("https://en.uesp.net/w/index.php?title=Skyrim:Empower_Necromancy&action=edit&redlink=1 ", "Empower Necromancy (AE)") -> Empower Necromancy (AE) | B60: N | C60: - | D60: - | E60: - | F60: X | G60: - | H60: - | I60: - | J60: - | K60: - | L60: Conjuration spell duration plus 5% Lesser undead summon limit plus 1 | M60: 199 | N60: Elite and Ascendant "Necromancer Robes" (From Creation "Necromatic Grimoire")

Sheet Spells
A1: Name | B1: Obtained? | C1: School | D1: Level | E1: Value | F1: Description | G1: Location | H1: Tome ID
A2: - | B2: =(countif(B3:B116,"Y")/(Rows(B3:B170)-1)) -> 0.011976048 | C2: - | D2: - | E2: - | F2: - | G2: - | H2: -
A3: =HYPERLINK("https://en.uesp.net/wiki/Skyrim:Candlelight", "Candlelight") -> Candlelight | B3: N | C3: Alteration | D3: (1) - Novice | E3: 44 | F3: Create hovering light that lasts 60 seconds | G3: Purchase from CUK, FFH, FDR, MWH, NFH, SBP, TCW, WPK, WMK | H3: 0009E2A7
A4: =HYPERLINK("https://en.uesp.net/wiki/Skyrim:Equilibrium", "Equilibrium") -> Equilibrium | B4: N | C4: Alteration | D4: (1) - Novice | E4: 250 | F4: Convert 20/s Health into 20/s Magicka | G4: Found in Labyrinthian Chasm | H4: 000F4997
A5: =HYPERLINK("https://en.uesp.net/wiki/Skyrim:Oakflesh", "Oakflesh") -> Oakflesh | B5: N | C5: Alteration | D5: (1) - Novice | E5: 44 | F5: Improves caster's armor by 40 points for 60 seconds | G5: Purchase from CUK, FFH, FDR, MWH, NFH, RT, SBP, TCW, WPK, WMK | H5: 0009E2A8
A6: =HYPERLINK("https://en.uesp.net/wiki/Skyrim:Magelight", "Magelight") -> Magelight | B6: N | C6: Alteration | D6: (2) - Apprentice | E6: 87 | F6: Stick a 60-second ball of light where it strikes when cast | G6: Purchase from CUK, FFH, FDR, MWH, SBP, TCW, WPK, WMK | H6: 000A26E2
A7: =HYPERLINK("https://en.uesp.net/wiki/Skyrim:Stoneflesh", "Stoneflesh") -> Stoneflesh | B7: N | C7: Alteration | D7: (2) - Apprentice | E7: 95 | F7: Improves caster's armor by 60 points for 60 seconds | G7: Purchase from CUK, FFH, FDR, MWH, SBP, TCW, WPK, WMK | H7: 000A26E3
A8: =HYPERLINK("https://en.uesp.net/wiki/Skyrim:Ash_Shell", "Ash Shell (DB)") -> Ash Shell (DB) | B8: N | C8: Alteration | D8: (3) - Adept | E8: 425 | F8: (DB) Cast on a nearby surface, it explodes when enemies are nearby, immobilizing them in hardened ash for 30 seconds | G8: Purchase from TTM after "From the Ashes" quest | H8: XX0177AC
A9: =HYPERLINK("https://en.uesp.net/wiki/Skyrim:Detect_Life", "Detect Life") -> Detect Life | B9: N | C9: Alteration | D9: (3) - Adept | E9: 332 | F9: See nearby living through walls | G9: Purchase from TCW, WMK (level 40 Alteration) | H9: 000A26E7
A10: =HYPERLINK("https://en.uesp.net/wiki/Skyrim:Ironflesh", "Ironflesh") -> Ironflesh | B10: N | C10: Alteration | D10: (3) - Adept | E10: 341 | F10: Improves caster's armor by 80 points for 60 seconds | G10: Purchase from TCW, WMK (level 40 Alteration) | H10: 000A26E4
A11: =HYPERLINK("https://en.uesp.net/wiki/Skyrim:Telekinesis", "Telekinesis") -> Telekinesis | B11: N | C11: Alteration | D11: (3) - Adept | E11: 326 | F11: Target item and hover it nearer or cast it away | G11: Purchase from TCW, WMK (level 40 Alteration) | H11: 000A26E5
A12: =HYPERLINK("https://en.uesp.net/wiki/Skyrim:Transmute_Mineral_Ore", "Transmute Mineral Ore") -> Transmute Mineral Ore | B12: N | C12: Alteration | D12: (3) - Adept | E12: 200 | F12: Transmute one piece of unrefined Iron Ore to Silver Ore or Silver Ore to Gold Ore | G12: Found in Ansilvund Burial Chambers, Halted Stream Camp | H12: 00109112
A13: =HYPERLINK("https://en.uesp.net/wiki/Skyrim:Alteration_Spells#Waterbreathing", "Waterbreathing") -> Waterbreathing | B13: N | C13: Alteration | D13: (3) - Adept | E13: 340 | F13: Breathe under water for 60 seconds | G13: Purchase from TCW, WMK (level 40 Alteration) | H13: 000A26E6
A14: =HYPERLINK("https://en.uesp.net/wiki/Skyrim:Ash_Rune", "Ash Rune (DB)") -> Ash Rune (DB) | B14: N | C14: Alteration | D14: (4) - Expert | E14: 635 | F14: (DB) Targets that fail to resist are immobilized in hardened ash for 30 seconds | G14: Purchase from TTM after "From the Ashes" quest | H14: XX0177B5
A15: =HYPERLINK("https://en.uesp.net/wiki/Skyrim:Detect_Dead", "Detect Dead") -> Detect Dead | B15: N | C15: Alteration | D15: (4) - Expert | E15: 600 | F15: See nearby dead through walls | G15: Purchase from TCW (level 65 Alteration) | H15: 000A26EA
A16: =HYPERLINK("https://en.uesp.net/wiki/Skyrim:Ebonyflesh", "Ebonyflesh") -> Ebonyflesh | B16: N | C16: Alteration | D16: (4) - Expert | E16: 650 | F16: Improves caster's armor by 100 points for 60 seconds | G16: Purchase from TCW (level 65 Alteration) | H16: 000A26E9
A17: =HYPERLINK("https://en.uesp.net/wiki/Skyrim:Paralyze_(spell)", "Paralyze") -> Paralyze | B17: N | C17: Alteration | D17: (4) - Expert | E17: 685 | F17: Targets that fail to resist are paralyzed for 10 sec | G17: Purchase from TCW (level 65 Alteration) | H17: 000A26E8
A18: =HYPERLINK("https://en.uesp.net/wiki/Skyrim:Dragonhide", "Dragonhide") -> Dragonhide | B18: N | C18: Alteration | D18: (5) - Master | E18: 1389 | F18: Caster ignores 80% of physical damage for 30 seconds | G18: Reward for "Alteration Ritual Spell" quest (level 90 Alteration) | H18: 000D2B4E
A19: =HYPERLINK("https://en.uesp.net/wiki/Skyrim:Mass_Paralysis", "Mass Paralysis") -> Mass Paralysis | B19: N | C19: Alteration | D19: (5) - Master | E19: 1280 | F19: All targets in the area that fail to resist are paralyzed for 15 sec | G19: Purchase from TCW after "Alteration Ritual Spell" (Level 90 Alteration) | H19: 000DD646
A20: =HYPERLINK("https://en.uesp.net/wiki/Skyrim:Bound_Dagger", "Bound Dagger (DB)") -> Bound Dagger (DB) | B20: N | C20: Conjuration | D20: (1) - Novice | E20: 38 | F20: (DB) Creates a magic dagger for 120 seconds. Sheathe it to dispel | G20: Purchase from TTM after "From the Ashes" quest | H20: XX01CE07
A21: =HYPERLINK("https://en.uesp.net/wiki/Skyrim:Bound_Sword", "Bound Sword") -> Bound Sword | B21: N | C21: Conjuration | D21: (1) - Novice | E21: 49 | F21: Creates magic sword for 120 seconds | G21: Purchase from CUK, FFH, FDR, MWH, NFH, SBP, PCW, WPK, WMK, TTM | H21: 0009E2A9
A22: =HYPERLINK("https://en.uesp.net/wiki/Skyrim:Conjure_Familiar", "Conjure Familiar") -> Conjure Familiar | B22: N | C22: Conjuration | D22: (1) - Novice | E22: 49 | F22: Summons a familiar for 60 seconds where the caster is pointing | G22: Purchase from CUK, FFH, FDR, MWH, NFH, SBP, PCW, WPK, WMK, TTM | H22: 0009E2AB
A23: =HYPERLINK("https://en.uesp.net/wiki/Skyrim:Raise_Zombie", "Raise Zombie") -> Raise Zombie | B23: N | C23: Conjuration | D23: (1) - Novice | E23: 49 | F23: Reanimate a weak dead body to fight for 60 seconds | G23: Purchase from CUK, FFH, FDR, MWH, NFH, RT, SBP, PCW, WPK, WMK, TTM | H23: 0009E2AA
A24: =HYPERLINK("https://en.uesp.net/wiki/Skyrim:Summon_Unbound_Dremora","Summon Unbound Dremora") -> Summon Unbound Dremora | B24: N | C24: Conjuration | D24: (1) - Novice | E24: N/A | F24: Summons an unbound Dremora for 999 seconds. | G24: Learned during the quest "Conjuration Ritual Spell" (level 90 Conjuration) | H24: N/A
A25: =HYPERLINK("https://en.uesp.net/wiki/Skyrim:Bound_Battleaxe", "Bound Battleaxe") -> Bound Battleaxe | B25: N | C25: Conjuration | D25: (2) - Apprentice | E25: 99 | F25: Creates a magic battleaxe for 120 seconds | G25: Purchase from CUK, FFH, FDR, MWH, NFH, SBP, PCW, WPK, WMK, TTM | H25: 000A26ED
A26: =HYPERLINK("https://en.uesp.net/wiki/Skyrim:Conjure_Boneman", "Conjure Boneman (DG)") -> Conjure Boneman (DG) | B26: N | C26: Conjuration | D26: (2) - Apprentice | E26: 75 | F26: (DG) Summons a Boneman Archer from the Soul Cairn for 60 seconds wherever the caster is pointing | G26: Found in Soul Cairn, in the center of the encircling pathways southwest of Jiub's Opus, Page 9 | H26: XX0045B0
A27: =HYPERLINK("https://en.uesp.net/wiki/Skyrim:Conjure_Flame_Atronach", "Conjure Flame Atronach") -> Conjure Flame Atronach | B27: N | C27: Conjuration | D27: (2) - Apprentice | E27: 99 | F27: Summons a flame atronach for 60 seconds where the caster is pointing | G27: Purchase from CUK, FFH, FDR, MWH, NFH, SBP, PCW, WPK, WMK, TTM | H27: 000A26EC
A28: =HYPERLINK("https://en.uesp.net/wiki/Skyrim:Reanimate_Corpse", "Reanimate Corpse") -> Reanimate Corpse | B28: N | C28: Conjuration | D28: (2) - Apprentice | E28: 99 | F28: Reanimate a more powerful dead body to fight for 60 seconds | G28: Purchase from CUK, FFH, FDR, MWH, NFH, SBP, PCW, WPK, WMK, TTM | H28: 000A26EB
A29: =HYPERLINK("https://en.uesp.net/wiki/Skyrim:Conjuration_Spells#Soul_Trap", "Soul Trap") -> Soul Trap | B29: N | C29: Conjuration | D29: (2) - Apprentice | E29: 100 | F29: Fills a soul gem if target dies within 60 seconds of casting | G29: Purchase from CUK, FFH, FDR, MWH, NFH, SBP, PCW, WPK, WMK, TTM | H29: 0009CD54
A30: =HYPERLINK("https://en.uesp.net/wiki/Skyrim:Summon_Arniel%27s_Shade","Summon Arniel's Shade") -> Summon Arniel's Shade | B30: N | C30: Conjuration | D30: (2) - Apprentice | E30: N/A | F30: Summons the Shade of Arniel Gane for 60 seconds wherever the caster is pointing. | G30: Reward for "Arniel's Endeavor" quest | H30: N/A
A31: =HYPERLINK("https://en.uesp.net/wiki/Skyrim:Summon_Arvak", "Summon Arvak (DG)") -> Summon Arvak (DG) | B31: N | C31: Conjuration | D31: (2) - Apprentice | E31: N/A | F31: (DG) Summons Arvak in the Soul Cairn or Tamriel wilderness to act as your steed | G31: Reward for "Soul Cairn Horse" quest | H31: N/A
A32: =HYPERLINK("https://en.uesp.net/wiki/Skyrim:Banish_Daedra", "Banish Daedra") -> Banish Daedra | B32: N | C32: Conjuration | D32: (3) - Adept | E32: 346 | F32: Returns weaker daedra to Oblivion | G32: Purchase from CUK, FFH, PCW (level 40 Conjuration) | H32: 000A26EE
A33: =HYPERLINK("https://en.uesp.net/wiki/Skyrim:Bound_Bow", "Bound Bow") -> Bound Bow | B33: N | C33: Conjuration | D33: (3) - Adept | E33: 335 | F33: Creates a magic bow for 120 seconds | G33: Purchase from CUK, FFH, PCW (level 40 Conjuration) | H33: 000A26F1
A34: =HYPERLINK("https://en.uesp.net/wiki/Skyrim:Conjure_Ash_Spawn", "Conjure Ash Spawn (DB)") -> Conjure Ash Spawn (DB) | B34: N | C34: Conjuration | D34: (3) - Adept | E34: 338 | F34: (DB) Summons an Ash Spawn for 60 seconds wherever the caster is pointing | G34: Purchase from TTM after "Telvanni Research" quest | H34: XX01E2B1
A35: =HYPERLINK("https://en.uesp.net/wiki/Skyrim:Conjure_Frost_Atronach", "Conjure Frost Atronach") -> Conjure Frost Atronach | B35: N | C35: Conjuration | D35: (3) - Adept | E35: 347 | F35: Summons a frost atronach for 60 seconds where the caster is pointing | G35: Purchase from CUK, FFH, PCW (level 40 Conjuration) | H35: 000A26EF
A36: =HYPERLINK("https://en.uesp.net/wiki/Skyrim:Conjure_Mistman", "Conjure Mistman (DG)") -> Conjure Mistman (DG) | B36: N | C36: Conjuration | D36: (3) - Adept | E36: 75 | F36: (DG) Summons a Mistman from the Soul Cairn for 60 seconds wherever the caster is pointing | G36: Found in Soul Cairn next to Jiub's Opus, Page 7 | H36: XX0045B1
A37: =HYPERLINK("https://en.uesp.net/wiki/Skyrim:Conjure_Seeker", "Conjure Seeker (DB)") -> Conjure Seeker (DB) | B37: N | C37: Conjuration | D37: (3) - Adept | E37: 307 | F37: (DB) Summons a Seeker for 60 seconds wherever the caster is pointing | G37: Found in Apocrypha in multiple places (level 40 Conjuration) | H37: XX033C67
A38: =HYPERLINK("https://en.uesp.net/wiki/Skyrim:Flaming_Familiar", "Flaming Familiar") -> Flaming Familiar | B38: N | C38: Conjuration | D38: (3) - Adept | E38: 250 | F38: Summons flaming familiar that attacks then explodes causing flame damage | G38: Reward for "A Scroll For Anska" quest | H38: 000B45F7
A39: =HYPERLINK("https://en.uesp.net/wiki/Skyrim:Revenant", "Revenant") -> Revenant | B39: N | C39: Conjuration | D39: (3) - Adept | E39: 340 | F39: Reanimate a powerful dead body to fight for 60 seconds | G39: Purchase from CUK, FFH, PCW (level 40 Conjuration) | H39: 000A26F2
A40: =HYPERLINK("https://en.uesp.net/wiki/Skyrim:Command_Daedra", "Command Daedra") -> Command Daedra | B40: N | C40: Conjuration | D40: (4) - Expert | E40: 660 | F40: Powerful summoned & raised creatures are put under your control | G40: Purchase from PCW (level 65 Conjuration) | H40: 000A26F6
A41: =HYPERLINK("https://en.uesp.net/wiki/Skyrim:Conjure_Ash_Guardian", "Conjure Ash Guardian (DB)") -> Conjure Ash Guardian (DB) | B41: N | C41: Conjuration | D41: (4) - Expert | E41: 1120 | F41: Creates an Ash Guardian that guards that location until destroyed. Consumes a heart stone from your inventory, without which it will be hostile. | G41: Purchase from TTM after "From the Ashes" quest | H41: 0301AABA
A42: =HYPERLINK("https://en.uesp.net/wiki/Skyrim:Conjure_Dremora_Lord", "Conjure Dremora Lord") -> Conjure Dremora Lord | B42: N | C42: Conjuration | D42: (4) - Expert | E42: 730 | F42: Summons a Dremora Lord to fight for you for 120 seconds | G42: Purchase from PCW (level 65 Conjuration) | H42: 0010FD60
A43: =HYPERLINK("https://en.uesp.net/wiki/Skyrim:Conjure_Storm_Atronach", "Conjure Storm Atronach") -> Conjure Storm Atronach | B43: N | C43: Conjuration | D43: (4) - Expert | E43: 690 | F43: Summons a storm atronach for 60 seconds where the caster is pointing | G43: Purchase from PCW (level 65 Conjuration) | H43: 000A26f0
A44: =HYPERLINK("https://en.uesp.net/wiki/Skyrim:Conjure_Wrathman", "Conjure Wrathman (DG)") -> Conjure Wrathman (DG) | B44: N | C44: Conjuration | D44: (4) - Expert | E44: 75 | F44: (DG) Summons a Wrathman from the Soul Cairn for 60 seconds wherever the caster is pointing | G44: Soul Cairn, in a building due south of Jiub's Opus, Page 5 | H44: XX0045B2
A45: =HYPERLINK("https://en.uesp.net/wiki/Skyrim:Dread_Zombie", "Dread Zombie") -> Dread Zombie | B45: N | C45: Conjuration | D45: (4) - Expert | E45: 630 | F45: Reanimate a very powerful dead body to fight for you for 60 sec | G45: Purchase from PCW (level 65 Conjuration) | H45: 000A26F7
A46: =HYPERLINK("https://en.uesp.net/wiki/Skyrim:Expel_Daedra", "Expel Daedra") -> Expel Daedra | B46: N | C46: Conjuration | D46: (4) - Expert | E46: 620 | F46: Powerful summoned daedra creatures are sent back to Oblivion | G46: Purchase from PCW (level 65 Conjuration) | H46: 000A26F8
A47: =HYPERLINK("https://en.uesp.net/wiki/Skyrim:Dead_Thrall", "Dead Thrall") -> Dead Thrall | B47: N | C47: Conjuration | D47: (5) - Master | E47: 3296 | F47: Reanimate a dead person permanently to fight for you | G47: Purchase from PCW after "Conjuration Ritual Spell" quest (level 90 Conjuration) | H47: 000A26F9
A48: =HYPERLINK("https://en.uesp.net/wiki/Skyrim:Thrall#Flame_Thrall", "Flame Thrall") -> Flame Thrall | B48: N | C48: Conjuration | D48: (5) - Master | E48: 1260 | F48: Summons a Flame Atronach permanently | G48: Reward for "Conjuration Ritual Spell" quest (level 90 Conjuration) | H48: 000A26FA
A49: =HYPERLINK("https://en.uesp.net/wiki/Skyrim:Thrall#Frost_Thrall", "Frost Thrall") -> Frost Thrall | B49: N | C49: Conjuration | D49: (5) - Master | E49: 3374 | F49: Summons a Frost Atronach permanently | G49: Purchase from PCW after "Conjuration Ritual Spell" quest (level 90 Conjuration) | H49: 000A26FB
A50: =HYPERLINK("https://en.uesp.net/wiki/Skyrim:Thrall#Storm_Thrall", "Storm Thrall") -> Storm Thrall | B50: N | C50: Conjuration | D50: (5) - Master | E50: 3504 | F50: Summons a Storm Atronach permanently | G50: Purchase from PCW after "Conjuration Ritual Spell" quest (level 90 Conjuration) | H50: 000A26FC
A51: =HYPERLINK("https://en.uesp.net/wiki/Skyrim:Arniel%27s_Convection","Arniel's Convection") -> Arniel's Convection | B51: N | C51: Destruction | D51: (1) - Novice | E51: N/A | F51: Burns the target 1 points per second. Targets on fire take extra damage. | G51: Learned during the quest "Arniel's Endeavor" | H51: N/A
A52: =HYPERLINK("https://en.uesp.net/wiki/Skyrim:Flames", "Flames") -> Flames | B52: Y | C52: Destruction | D52: (1) - Novice | E52: 50 | F52: Shoot flames from one or both hands for 8/s fire damage; targets on fire take extra damage | G52: All players start with this spell | H52: 0009CD51
A53: =HYPERLINK("https://en.uesp.net/wiki/Skyrim:Frostbite", "Frostbite") -> Frostbite | B53: N | C53: Destruction | D53: (1) - Novice | E53: 47 | F53: A blast of cold that does 8/s per second to health and stamina | G53: Purchase from CUK, FFH, FDR, MWH, NFH, RT, SBP, FCW, WPK, WMK, TTM | H53: 0009CD52
A54: =HYPERLINK("https://en.uesp.net/wiki/Skyrim:Sparks", "Sparks") -> Sparks | B54: N | C54: Destruction | D54: (1) - Novice | E54: 46 | F54: Create a bolt of lightning that does 10/s shock damage to health and 5/s to magicka | G54: Purchase from CUK, FFH, FDR, MWH, NFH, SBP, FCW, WPK, WMK, TTM | H54: 0009CD53
A55: =HYPERLINK("https://en.uesp.net/wiki/Skyrim:Fire_Rune", "Fire Rune") -> Fire Rune | B55: N | C55: Destruction | D55: (2) - Apprentice | E55: 90 | F55: Cast on a nearby surface, it explodes for 50 points of fire damage when enemies come near | G55: Purchase from CUK, FFH, FDR, MWH, SBP, FCW, WPK, WMK, TTM | H55: 000A2700
A56: =HYPERLINK("https://en.uesp.net/wiki/Skyrim:Firebolt", "Firebolt") -> Firebolt | B56: N | C56: Destruction | D56: (2) - Apprentice | E56: 96 | F56: A blast of fire that does 25 points of damage; targets on fire take extra damage | G56: Purchase from CUK, FFH, FDR, MWH, SBP, FCW, WPK, WMK, TTM | H56: 000A26FD
A57: =HYPERLINK("https://en.uesp.net/wiki/Skyrim:Frost_Rune", "Frost Rune") -> Frost Rune | B57: N | C57: Destruction | D57: (2) - Apprentice | E57: 92 | F57: Cast on a nearby surface, it explodes for 50 points of frost damage when enemies come near | G57: Purchase from CUK, FFH, FDR, MWH, SBP, FCW, WPK, WMK, TTM | H57: 000A2701
A58: =HYPERLINK("https://en.uesp.net/wiki/Skyrim:Ice_Spike", "Ice Spike") -> Ice Spike | B58: N | C58: Destruction | D58: (2) - Apprentice | E58: 96 | F58: Throw a spike of ice that does 25 points of frost damage to health and stamina | G58: Purchase from CUK, FFH, FDR, MWH, SBP, FCW, WPK, WMK, TTM | H58: 000A26FE
A59: =HYPERLINK("https://en.uesp.net/wiki/Skyrim:Lightning_Bolt", "Lightning Bolt") -> Lightning Bolt | B59: N | C59: Destruction | D59: (2) - Apprentice | E59: 95 | F59: Create a bolt of lightning that does 25 points of shock damage to health and half that to magicka | G59: Purchase from CUK, FFH, FDR, MWH, SBP, FCW, WPK, WMK, TTM | H59: 000A26FF
A60: =HYPERLINK("https://en.uesp.net/wiki/Skyrim:Lightning_Rune", "Lightning Rune") -> Lightning Rune | B60: N | C60: Destruction | D60: (2) - Apprentice | E60: 93 | F60: Cast on a nearby surface, explodes for 50 points of shock damage when enemies come near | G60: Purchase from CUK, FFH, FDR, MWH, SBP, FCW, WPK, WMK, TTM | H60: 000A2702
A61: =HYPERLINK("https://en.uesp.net/wiki/Skyrim:Chain_Lightning", "Chain Lightning") -> Chain Lightning | B61: N | C61: Destruction | D61: (3) - Adept | E61: 390 | F61: Lightning bolt that shock damages health magicka, then leaps to another target | G61: Purchase from FDR, MWH, ECW, FCW, WPK, TTM (level 40 Destruction) | H61: 000A2708
A62: =HYPERLINK("https://en.uesp.net/wiki/Skyrim:Fireball", "Fireball") -> Fireball | B62: N | C62: Destruction | D62: (3) - Adept | E62: 345 | F62: A fiery explosion for 50 points of damage in 15 foot radius; targets on fire take extra damage | G62: Purchase from FDR, MWH, ECW, FCW, WPK, TTM (level 40 Destruction) | H62: 000A2706
A63: =HYPERLINK("https://en.uesp.net/wiki/Skyrim:Flame_Cloak", "Flame Cloak") -> Flame Cloak | B63: N | C63: Destruction | D63: (3) - Adept | E63: 325 | F63: For 60 seconds, opponents in melee range take 8/s fire damage; targets on fire take extra damage | G63: Purchase from FDR, MWH, ECW, FCW, WPK, TTM (level 40 Destruction) | H63: 000A2703
A64: =HYPERLINK("https://en.uesp.net/wiki/Skyrim:Frost_Cloak", "Frost Cloak") -> Frost Cloak | B64: N | C64: Destruction | D64: (3) - Adept | E64: 340 | F64: For 60 seconds, opponents in melee range take 8/s frost damage and stamina damage | G64: Purchase from FDR, MWH, ECW, FCW, WPK, TTM (level 40 Destruction) | H64: 000A2704
A65: =HYPERLINK("https://en.uesp.net/wiki/Skyrim:Ice_Storm", "Ice Storm") -> Ice Storm | B65: N | C65: Destruction | D65: (3) - Adept | E65: 360 | F65: Create a freezing whirlwind that does 40/s frost damage to health and stamina | G65: Purchase from FDR, MWH, ECW, FCW, WPK, TTM (level 40 Destruction) | H65: 000A2707
A66: =HYPERLINK("https://en.uesp.net/wiki/Skyrim:Lightning_Cloak", "Lightning Cloak") -> Lightning Cloak | B66: N | C66: Destruction | D66: (3) - Adept | E66: 355 | F66: For 60 seconds nearby opponents take 8 points shock damage and half magicka damage | G66: Purchase from FDR, MWH, ECW, FCW, WPK, TTM (level 40 Destruction) | H66: 000A2705
A67: =HYPERLINK("https://en.uesp.net/wiki/Skyrim:Whirlwind_Cloak", "Whirlwind Cloak (DB)") -> Whirlwind Cloak (DB) | B67: N | C67: Destruction | D67: (3) - Adept | E67: 395 | F67: (DB) For 60 seconds, opponents in melee range have a chance of being flung away | G67: Purchase from TTM after "Wind and Sand" quest | H67: XX0177AD
A68: =HYPERLINK("https://en.uesp.net/wiki/Skyrim:Icy_Spear", "Icy Spear") -> Icy Spear | B68: N | C68: Destruction | D68: (4) - Expert | E68: 725 | F68: Throw spear of ice that does 60 points of frost damage to health and stamina | G68: Purchase from ECW, FCW, TTM (level 65 Destruction) | H68: 0010F7F3
A69: =HYPERLINK("https://en.uesp.net/wiki/Skyrim:Incinerate", "Incinerate") -> Incinerate | B69: N | C69: Destruction | D69: (4) - Expert | E69: 710 | F69: Create blast of fire that does 60 points of damage; targets on fire take extra damage | G69: Purchase from ECW, FCW, TTM (level 65 Destruction) | H69: 0010F7F4
A70: =HYPERLINK("https://en.uesp.net/wiki/Skyrim:Thunderbolt", "Thunderbolt") -> Thunderbolt | B70: N | C70: Destruction | D70: (4) - Expert | E70: 750 | F70: Create a thunderbolt that does 60 points of shock damage to health and half that to magicka | G70: Purchase from ECW, FCW, TTM (level 65 Destruction) | H70: 0010F7F5
A71: =HYPERLINK("https://en.uesp.net/wiki/Skyrim:Wall_of_Flames", "Wall of Flames") -> Wall of Flames | B71: N | C71: Destruction | D71: (4) - Expert | E71: 680 | F71: Sprayed on the ground, creates wall of flames that does 50/s fire damage | G71: Purchase from ECW, FCW, TTM (level 65 Destruction) | H71: 000A2709
A72: =HYPERLINK("https://en.uesp.net/wiki/Skyrim:Wall_of_Frost", "Wall of Frost") -> Wall of Frost | B72: N | C72: Destruction | D72: (4) - Expert | E72: 700 | F72: Sprayed on the ground, creates wall of frost that does 50/s frost damage | G72: Purchase from ECW, FCW, TTM (level 65 Destruction) | H72: 000A270A
A73: =HYPERLINK("https://en.uesp.net/wiki/Skyrim:Wall_of_Storms", "Wall of Storms") -> Wall of Storms | B73: N | C73: Destruction | D73: (4) - Expert | E73: 725 | F73: Sprayed on the ground, creates wall of lightning that does 50/s shock damage | G73: Purchase from ECW, FCW, TTM (level 65 Destruction) | H73: 000A270B
A74: =HYPERLINK("https://en.uesp.net/wiki/Skyrim:Blizzard", "Blizzard") -> Blizzard | B74: N | C74: Destruction | D74: (5) - Master | E74: 1350 | F74: Targets take 20 frost damage + Stamina damage for 10 seconds | G74: Purchase from FCW after "Destruction Ritual Spell" quest (level 90 Destruction) | H74: 000A270D
A75: =HYPERLINK("https://en.uesp.net/wiki/Skyrim:Fire_Storm", "Fire Storm") -> Fire Storm | B75: N | C75: Destruction | D75: (5) - Master | E75: 1290 | F75: When cast it explodes for 150 points of fire damage to nearby enemies | G75: Reward for "Destruction Ritual Spell" quest (level 90 Destruction) | H75: 000A270C
A76: =HYPERLINK("https://en.uesp.net/wiki/Skyrim:Lightning_Storm", "Lightning Storm") -> Lightning Storm | B76: N | C76: Destruction | D76: (5) - Master | E76: 1400 | F76: Target takes 75/s shock damage to Health and 75/2s damage to Magicka | G76: Purchase from FCW after "Destruction Ritual Spell" quest (level 90 Destruction) | H76: 000A270E
A77: =HYPERLINK("https://en.uesp.net/wiki/Skyrim:Illusion_Spells#Clairvoyance", "Clairvoyance") -> Clairvoyance | B77: N | C77: Illusion | D77: (1) - Novice | E77: 50 | F77: Shows the path to the current goal | G77: Purchase from CUK, FFH, FDR, MWH, NFH, RT, SBP, DCW, WPK, WMK | H77: 000FF7D1
A78: =HYPERLINK("https://en.uesp.net/wiki/Skyrim:Courage", "Courage") -> Courage | B78: N | C78: Illusion | D78: (1) - Novice | E78: 46 | F78: Target won't flee for 60 seconds and gains some extra health and stamina | G78: Purchase from CUK, FFH, FDR, MWH, NFH, SBP, DCW, WPK, WMK | H78: 0009E2AD
A79: =HYPERLINK("https://en.uesp.net/wiki/Skyrim:Fury", "Fury") -> Fury | B79: N | C79: Illusion | D79: (1) - Novice | E79: 43 | F79: Creatures and people up to level 6 will attack anything nearby for 30 seconds | G79: Purchase from CUK, FFH, FDR, MWH, NFH, RT, SBP, DCW, WPK, WMK | H79: 0009E2AC
A80: =HYPERLINK("https://en.uesp.net/wiki/Skyrim:Vision_of_the_Tenth_Eye", "Vision of the Tenth Eye") -> Vision of the Tenth Eye | B80: N | C80: Illusion | D80: (1) - Novice | E80: 0 | F80: See what others cannot | G80: Learned during the quest "Illusion Ritual Spell" (level 90 Illusion) | H80: N/A
A81: =HYPERLINK("https://en.uesp.net/wiki/Skyrim:Calm", "Calm") -> Calm | B81: N | C81: Illusion | D81: (2) - Apprentice | E81: 91 | F81: Creatures and people up to level 9 won't fight for 30 seconds | G81: Purchase from CUK, FFH, FDR, MWH, SBP, DCW, WPK, WMK | H81: 000A2711
A82: =HYPERLINK("https://en.uesp.net/wiki/Skyrim:Fear_(spell)", "Fear") -> Fear | B82: N | C82: Illusion | D82: (2) - Apprentice | E82: 80 | F82: Creatures and people up to level 9 flee from combat for 30 seconds | G82: Purchase from CUK, FFH, FDR, MWH, SBP, DCW, WPK, WMK | H82: 000A2712
A83: =HYPERLINK("https://en.uesp.net/wiki/Skyrim:Illusion_Spells#Muffle", "Muffle") -> Muffle | B83: N | C83: Illusion | D83: (2) - Apprentice | E83: 88 | F83: Allows player to move more quietly for 180 seconds | G83: Purchase from CUK, FFH, FDR, MWH, SBP, DCW, WPK, WMK | H83: 000A270F
A84: =HYPERLINK("https://en.uesp.net/wiki/Skyrim:Frenzy_(spell)", "Frenzy") -> Frenzy | B84: N | C84: Illusion | D84: (3) - Adept | E84: 330 | F84: Creatures and people up to level 14 will attack anyone nearby | G84: Purchase from SBP, DCW (level 40 Illusion) | H84: 000A2714
A85: =HYPERLINK("https://en.uesp.net/wiki/Skyrim:Frenzy_Rune", "Frenzy Rune (DB)") -> Frenzy Rune (DB) | B85: N | C85: Illusion | D85: (3) - Adept | E85: 310 | F85: (DB) Targets up to level 20 that fail to resist are frenzied for 30 seconds | G85: Purchase from TTM after "From the Ashes" quest | H85: XX0177BD
A86: =HYPERLINK("https://en.uesp.net/wiki/Skyrim:Rally_(spell)", "Rally") -> Rally | B86: N | C86: Illusion | D86: (3) - Adept | E86: 300 | F86: Targets won't flee for 60 seconds and boosts player's health and stamina | G86: Purchase from SBP, DCW (level 40 Illusion) | H86: 000A2713
A87: =HYPERLINK("https://en.uesp.net/wiki/Skyrim:Invisibility_(spell)", "Invisibility") -> Invisibility | B87: N | C87: Illusion | D87: (4) - Expert | E87: 625 | F87: Caster is invisible (but can still be heard) for 30 seconds; activating an object or attacking will break the spell | G87: Purchase from DCW (level 65 Illusion) | H87: 000A2715
A88: =HYPERLINK("https://en.uesp.net/wiki/Skyrim:Pacify_(spell)", "Pacify") -> Pacify | B88: N | C88: Illusion | D88: (4) - Expert | E88: 610 | F88: Creatures and people up to level 20 won't fight for 60 seconds | G88: Purchase from DCW (level 65 Illusion) | H88: 000A2717
A89: =HYPERLINK("https://en.uesp.net/wiki/Skyrim:Rout", "Rout") -> Rout | B89: N | C89: Illusion | D89: (4) - Expert | E89: 653 | F89: Creatures and people up to level 20 flee from combat for 30 sec | G89: Purchase from DCW (level 65 Illusion) | H89: 000A2718
A90: =HYPERLINK("https://en.uesp.net/wiki/Skyrim:Call_to_Arms", "Call to Arms") -> Call to Arms | B90: N | C90: Illusion | D90: (5) - Master | E90: 1150 | F90: Improves target combat skills for 10 minutes | G90: Purchase from DCW after "Illusion Ritual Spell" quest (level 90 Illusion) | H90: 000A271B
A91: =HYPERLINK("https://en.uesp.net/wiki/Skyrim:Harmony", "Harmony") -> Harmony | B91: N | C91: Illusion | D91: (5) - Master | E91: 1220 | F91: Creatures and people up to level 25 nearby won't fight for 60 seconds | G91: Purchase from DCW after "Illusion Ritual Spell" quest (level 90 Illusion) | H91: 000A271A
A92: =HYPERLINK("https://en.uesp.net/wiki/Skyrim:Hysteria", "Hysteria") -> Hysteria | B92: N | C92: Illusion | D92: (5) - Master | E92: 1240 | F92: Creatures and people up to level 25 flee from combat for 60 seconds | G92: Reward for "Illusion Ritual Spell" quest (level 90 Illusion) | H92: 000A271C
A93: =HYPERLINK("https://en.uesp.net/wiki/Skyrim:Mayhem", "Mayhem") -> Mayhem | B93: N | C93: Illusion | D93: (5) - Master | E93: 1250 | F93: Creatures and people up to level 25 will attack anyone nearby for 60 seconds | G93: Purchase from DCW after "Illusion Ritual Spell" quest (level 90 Illusion) | H93: 000A2719
A94: =HYPERLINK("https://en.uesp.net/wiki/Skyrim:Healing", "Healing") -> Healing | B94: Y | C94: Restoration | D94: (1) - Novice | E94: 50 | F94: Heals caster 10/s | G94: All players start with this spell | H94: 0009E2AF
A95: =HYPERLINK("https://en.uesp.net/wiki/Skyrim:Lesser_Ward", "Lesser Ward") -> Lesser Ward | B95: N | C95: Restoration | D95: (1) - Novice | E95: 45 | F95: Increases armor rating by 40 points and negates up to 40 points of spell damage or effects | G95: Purchase from CUK, FFH, FDR, MWH, NFH, RT, SBP, CCW, WPK, WMK | H95: 0009E2AE
A96: =HYPERLINK("https://en.uesp.net/wiki/Skyrim:Fast_Healing", "Fast Healing") -> Fast Healing | B96: N | C96: Restoration | D96: (2) - Apprentice | E96: 94 | F96: Instantly heals caster 50 points | G96: Purchase from CUK, FFH, FDR, MWH, NFH, SBP, CCW, WPK, WMK | H96: 000A271D
A97: =HYPERLINK("https://en.uesp.net/wiki/Skyrim:Healing_Hands", "Healing Hands") -> Healing Hands | B97: N | C97: Restoration | D97: (2) - Apprentice | E97: 89 | F97: Heals target 10/s, but not undead, atronachs, or machines | G97: Purchase from CUK, FFH, FDR, MWH, NFH, SBP, CCW, WPK, WMK | H97: 000A271E
A98: =HYPERLINK("https://en.uesp.net/wiki/Skyrim:Necromantic_Healing", "Necromantic Healing (DG)") -> Necromantic Healing (DG) | B98: N | C98: Restoration | D98: (2) - Apprentice | E98: 115 | F98: (DG) Heals the undead target 10 points per second, but not the living, atronachs or machines | G98: Purchased from RVK, Found in Dimhollow Crypt | H98: XX00E8D5
A99: =HYPERLINK("https://en.uesp.net/wiki/Skyrim:Steadfast_Ward", "Steadfast Ward") -> Steadfast Ward | B99: N | C99: Restoration | D99: (2) - Apprentice | E99: 92 | F99: Increases armor rating 60 / negates up to 60 points spell damage or effects | G99: Purchase from CUK, FFH, FDR, MWH, NFH, SBP, CCW, WPK, WMK | H99: 000A2720
A100: =HYPERLINK("https://en.uesp.net/wiki/Skyrim:Sun_Fire", "Sun Fire (DG)") -> Sun Fire (DG) | B100: N | C100: Restoration | D100: (2) - Apprentice | E100: 80 | F100: (DG) Ball of sunlight that does 25 points of damage to undead | G100: Purchase from SFD | H100: XX003F51
...

Sheet Dragon Shouts
A1: Obtained? | B1: Word of Power | C1: Translation | D1: Word Wall Location
A2: =countif(A4:A110,"*Y*")/81 -> 0
B3: =HYPERLINK("https://en.uesp.net/wiki/Skyrim:Animal_Allegiance", "Animal Allegiance") -> Animal Allegiance
A4: N | B4: Raan | C4: Animal | D4: =HYPERLINK("https://en.uesp.net/wiki/Skyrim:Ancient%27s_Ascent","Ancient's Ascent") -> Ancient's Ascent
A5: N | B5: Mir | C5: Allegiance | D5: =HYPERLINK("https://en.uesp.net/wiki/Skyrim:Angarvunde","Angarvunde") -> Angarvunde
A6: N | B6: Tah | C6: Pack | D6: =HYPERLINK("https://en.uesp.net/wiki/Skyrim:Ysgramor%27s_Tomb","Ysgramor's Tomb") -> Ysgramor's Tomb
B7: =HYPERLINK("https://en.uesp.net/wiki/Skyrim:Aura_Whisper", "Aura Whisper") -> Aura Whisper
A8: N | B8: Laas | C8: Life | D8: =HYPERLINK("https://en.uesp.net/wiki/Skyrim:Northwind_Summit","Northwind Summit") -> Northwind Summit
A9: N | B9: Yah | C9: Seek | D9: =HYPERLINK("https://en.uesp.net/wiki/Skyrim:Valthume","Valthume") -> Valthume
A10: N | B10: Nir | C10: Hunt | D10: =HYPERLINK("https://en.uesp.net/wiki/Skyrim:Volunruud","Volunruud") -> Volunruud
B11: =HYPERLINK("https://en.uesp.net/wiki/Skyrim:Become_Ethereal", "Become Ethereal") -> Become Ethereal
A12: N | B12: Feim | C12: Fade | D12: =HYPERLINK("https://en.uesp.net/wiki/Skyrim:Ironbind_Barrow","Ironbind Barrow") -> Ironbind Barrow
A13: N | B13: Zii | C13: Spirit | D13: =HYPERLINK("https://en.uesp.net/wiki/Skyrim:Lost_Valley_Redoubt","Lost Valley Redoubt") -> Lost Valley Redoubt
A14: N | B14: Gron | C14: Bind | D14: =HYPERLINK("https://en.uesp.net/wiki/Skyrim:The_Horn_of_Jurgen_Windcaller","Ustengrav - During The Horn of Jurgen Windcaller") -> Ustengrav - During The Horn of Jurgen Windcaller
B15: =HYPERLINK("https://en.uesp.net/wiki/Skyrim:Call_Dragon", "Call Dragon") -> Call Dragon
A16: N | B16: Od | C16: Snow | D16: =HYPERLINK("https://en.uesp.net/wiki/Skyrim:The_Fallen","High Hrothgar - During The Fallen") -> High Hrothgar - During The Fallen
A17: N | B17: Ah | C17: Hunter
A18: N | B18: Viing | C18: Wing
B19: =HYPERLINK("https://en.uesp.net/wiki/Skyrim:Call_of_Valor", "Call of Valor") -> Call of Valor
A20: N | B20: Hun | C20: Hero | D20: =HYPERLINK("https://en.uesp.net/wiki/Skyrim:Dragonslayer","Sovngarde - During Dragonslayer") -> Sovngarde - During Dragonslayer
A21: N | B21: Kaal | C21: Champion
A22: N | B22: Zoor | C22: Legend
B23: =HYPERLINK("https://en.uesp.net/wiki/Skyrim:Clear_Skies", "Clear Skies") -> Clear Skies
A24: N | B24: Lok | C24: Sky | D24: =HYPERLINK("https://en.uesp.net/wiki/Skyrim:Throat_of_the_World","High Hrothgar - During The Throat of the World") -> High Hrothgar - During The Throat of the World
A25: N | B25: Vah | C25: Spring
A26: N | B26: Koor | C26: Summer
B27: =HYPERLINK("https://en.uesp.net/wiki/Skyrim:Disarm", "Disarm") -> Disarm
A28: N | B28: Zun | C28: Weapon | D28: =HYPERLINK("https://en.uesp.net/wiki/Skyrim:Eldersblood_Peak","Eldersblood Peak") -> Eldersblood Peak
A29: N | B29: Haal | C29: Hand | D29: =HYPERLINK("https://en.uesp.net/wiki/Skyrim:Silverdrift_Lair","Silverdrift Lair") -> Silverdrift Lair
A30: N | B30: Viik | C30: Defeat | D30: =HYPERLINK("https://en.uesp.net/wiki/Skyrim:Speaking_With_Silence","Snow Veil Sanctum (quest locked)") -> Snow Veil Sanctum (quest locked)
B31: =HYPERLINK("https://en.uesp.net/wiki/Skyrim:Dismay", "Dismay") -> Dismay
A32: N | B32: Faas | C32: Fear | D32: =HYPERLINK("https://en.uesp.net/wiki/Skyrim:Dead_Crone_Rock","Dead Crone Rock") -> Dead Crone Rock
A33: N | B33: Ru | C33: Run | D33: =HYPERLINK("https://en.uesp.net/wiki/Skyrim:Lost_Tongue_Overlook","Lost Tongue Overlook") -> Lost Tongue Overlook
A34: N | B34: Maar | C34: Terror | D34: =HYPERLINK("https://en.uesp.net/wiki/Skyrim:Shalidor%27s_Maze","Shalidor's Maze") -> Shalidor's Maze
B35: =HYPERLINK("https://en.uesp.net/wiki/Skyrim:Dragonrend", "Dragonrend") -> Dragonrend
A36: N | B36: Joor | C36: Mortal | D36: =HYPERLINK("https://en.uesp.net/wiki/Skyrim:Throat_of_the_World","Throat of the World - During Alduin's Bane") -> Throat of the World - During Alduin's Bane
A37: N | B37: Zah | C37: Finite
A38: N | B38: Frul | C38: Temporary
B39: =HYPERLINK("https://en.uesp.net/wiki/Skyrim:Elemental_Fury", "Elemental Fury") -> Elemental Fury
A40: N | B40: Su | C40: Air | D40: =HYPERLINK("https://en.uesp.net/wiki/Skyrim:Dragontooth_Crater","Dragontooth Crater") -> Dragontooth Crater
A41: N | B41: Grah | C41: Battle | D41: =HYPERLINK("https://en.uesp.net/wiki/Skyrim:Shriekwind_Bastion","Shriekwind Bastion") -> Shriekwind Bastion
A42: N | B42: Dun | C42: Grace | D42: =HYPERLINK("https://en.uesp.net/wiki/Skyrim:Statue_to_Meridia","Statue to Meridia") -> Statue to Meridia
B43: =HYPERLINK("https://en.uesp.net/wiki/Skyrim:Fire_Breath", "Fire Breath") -> Fire Breath
A44: N | B44: Yol | C44: Fire | D44: =HYPERLINK("https://en.uesp.net/wiki/Skyrim:Proving_Honor#Dustman.27s_Cairn","Dustman's Cairn - During Proving Honor") -> Dustman's Cairn - During Proving Honor
A45: N | B45: Toor | C45: Inferno | D45: =HYPERLINK("https://en.uesp.net/wiki/Skyrim:Sunderstone_Gorge","Sunderstone Gorge") -> Sunderstone Gorge
A46: N | B46: Shul | C46: Sun | D46: =HYPERLINK("https://en.uesp.net/wiki/Skyrim:Throat_of_the_World","Throat of the World - During Throat of the World") -> Throat of the World - During Throat of the World
B47: =HYPERLINK("https://en.uesp.net/wiki/Skyrim:Frost_Breath", "Frost Breath") -> Frost Breath
A48: N | B48: Fo | C48: Frost | D48: =HYPERLINK("https://en.uesp.net/wiki/Skyrim:Bonestrewn_Crest","Bonestrewn Crest") -> Bonestrewn Crest
A49: N | B49: Krah | C49: Cold | D49: =HYPERLINK("https://en.uesp.net/wiki/Skyrim:Folgunthur","Folgunthur") -> Folgunthur
A50: N | B50: Diin | C50: Freeze | D50: =HYPERLINK("https://en.uesp.net/wiki/Skyrim:Skyborn_Altar","Skyborn Altar") -> Skyborn Altar
B51: =HYPERLINK("https://en.uesp.net/wiki/Skyrim:Ice_Form", "Ice Form") -> Ice Form
A52: N | B52: Iiz | C52: Ice | D52: =HYPERLINK("https://en.uesp.net/wiki/Skyrim:Frostmere_Crypt","Frostmere Crypt") -> Frostmere Crypt
A53: N | B53: Slen | C53: Flesh | D53: =HYPERLINK("https://en.uesp.net/wiki/Skyrim:Mount_Anthor","Mount Anthor") -> Mount Anthor
A54: N | B54: Nus | C54: Statue | D54: =HYPERLINK("https://en.uesp.net/wiki/Skyrim:Saarthal","Saarthal (quest locked)") -> Saarthal (quest locked)
B55: =HYPERLINK("https://en.uesp.net/wiki/Skyrim:Kyne's_Peace", "Kyne's Peace") -> Kyne's Peace
A56: N | B56: Kaan | C56: Kyne | D56: =HYPERLINK("https://en.uesp.net/wiki/Skyrim:Ragnvald","Ragnvald") -> Ragnvald
A57: N | B57: Drem | C57: Peace | D57: =HYPERLINK("https://en.uesp.net/wiki/Skyrim:Rannveig%27s_Fast","Rannveig's Fast") -> Rannveig's Fast
A58: N | B58: Ov | C58: Trust | D58: =HYPERLINK("https://en.uesp.net/wiki/Skyrim:Shroud_Hearth_Barrow","Shroud Hearth Barrow") -> Shroud Hearth Barrow
B59: =HYPERLINK("https://en.uesp.net/wiki/Skyrim:Marked_for_Death", "Marked for Death") -> Marked for Death
A60: N | B60: Krii | C60: Kill | D60: =HYPERLINK("https://en.uesp.net/wiki/Skyrim:Autumnwatch_Tower","Autumnwatch Tower") -> Autumnwatch Tower
A61: N | B61: Lun | C61: Leech | D61: =HYPERLINK("https://en.uesp.net/wiki/Skyrim:Dark_Brotherhood_Sanctuary","Dark Brotherhood Sanctuary (quest locked)") -> Dark Brotherhood Sanctuary (quest locked)
A62: N | B62: Aus | C62: Suffer | D62: =HYPERLINK("https://en.uesp.net/wiki/Skyrim:Forsaken_Cave","Forsaken Cave") -> Forsaken Cave
B63: =HYPERLINK("https://en.uesp.net/wiki/Skyrim:Slow_Time", "Slow Time") -> Slow Time
A64: N | B64: Tiid | C64: Time | D64: =HYPERLINK("https://en.uesp.net/wiki/Skyrim:Hag%27s_End","Hag's End") -> Hag's End
A65: N | B65: Klo | C65: Sand | D65: =HYPERLINK("https://en.uesp.net/wiki/Skyrim:Korvanjund","Korvanjund (quest locked)") -> Korvanjund (quest locked)
A66: N | B66: Ul | C66: Eternity | D66: =HYPERLINK("https://en.uesp.net/wiki/Skyrim:Labyrinthian","Labyrinthian (quest locked)") -> Labyrinthian (quest locked)
B67: =HYPERLINK("https://en.uesp.net/wiki/Skyrim:Storm_Call", "Storm Call") -> Storm Call
A68: N | B68: Strun | C68: Storm | D68: =HYPERLINK("https://en.uesp.net/wiki/Skyrim:Forelhost","Forelhost") -> Forelhost
A69: N | B69: Bah | C69: Wrath | D69: =HYPERLINK("https://en.uesp.net/wiki/Skyrim:High_Gate_Ruins","High Gate Ruins") -> High Gate Ruins
A70: N | B70: Qo | C70: Lightning | D70: =HYPERLINK("https://en.uesp.net/wiki/Skyrim:Skuldafn#Skuldafn_Temple","Skuldafn Temple (quest locked)") -> Skuldafn Temple (quest locked)
B71: =HYPERLINK("https://en.uesp.net/wiki/Skyrim:Throw_Voice", "Throw Voice") -> Throw Voice
A72: N | B72: Zul | C72: Voice | D72: =HYPERLINK("https://en.uesp.net/wiki/Skyrim:Shearpoint","Shearpoint") -> Shearpoint
A73: N | B73: Mey | C73: Fool
A74: N | B74: Gut | C74: Far
B75: =HYPERLINK("https://en.uesp.net/wiki/Skyrim:Unrelenting_Force", "Unrelenting Force") -> Unrelenting Force
A76: N | B76: Fus | C76: Force | D76: =HYPERLINK("https://en.uesp.net/wiki/Skyrim:Bleak_Falls_Barrow","Bleak Falls Barrow") -> Bleak Falls Barrow
A77: N | B77: Ro | C77: Balance | D77: =HYPERLINK("https://en.uesp.net/wiki/Skyrim:High_Hrothgar","High Hrothgar - During The Way of the Voice") -> High Hrothgar - During The Way of the Voice
A78: N | B78: Dah | C78: Push | D78: =HYPERLINK("https://en.uesp.net/wiki/Skyrim:High_Hrothgar","High Hrothgar - During The Horn of Jurgen Windcaller") -> High Hrothgar - During The Horn of Jurgen Windcaller
B79: =HYPERLINK("https://en.uesp.net/wiki/Skyrim:Whirlwind_Sprint", "Whirlwind Sprint") -> Whirlwind Sprint
A80: N | B80: Wuld | C80: Whirlwind | D80: =HYPERLINK("https://en.uesp.net/wiki/Skyrim:Dead_Men%27s_Respite","Dead Men's Respite") -> Dead Men's Respite
A81: N | B81: Nah | C81: Fury | D81: =HYPERLINK("https://en.uesp.net/wiki/Skyrim:High_Hrothgar","High Hrothgar - During The Way of the Voice") -> High Hrothgar - During The Way of the Voice
A82: N | B82: Kest | C82: Tempest | D82: =HYPERLINK("https://en.uesp.net/wiki/Skyrim:Volskygge","Volskygge") -> Volskygge
B83: =HYPERLINK("https://en.uesp.net/wiki/Skyrim:Drain_Vitality", "Drain Vitality (Dawnguard)") -> Drain Vitality (Dawnguard)
A84: N | B84: Gaan | C84: Stamina | D84: =HYPERLINK("https://en.uesp.net/wiki/Skyrim:Dimhollow_Crypt","Dimhollow Crypt") -> Dimhollow Crypt
A85: N | B85: Lah | C85: Magicka | D85: =HYPERLINK("https://en.uesp.net/wiki/Skyrim:Forgotten_Vale","Forgotten Vale") -> Forgotten Vale
A86: N | B86: Haas | C86: Health | D86: =HYPERLINK("https://en.uesp.net/wiki/Skyrim:Arcwind_Point","Arcwind Point") -> Arcwind Point
B87: =HYPERLINK("https://en.uesp.net/wiki/Skyrim:Soul_Tear", "Soul Tear (Dawnguard)") -> Soul Tear (Dawnguard)
A88: N | B88: Rii | C88: Essence | D88: =HYPERLINK("https://en.uesp.net/wiki/Skyrim:Durnehviir","Durnehviir teaches you a word each time you summon him from the Soul Cairn.") -> Durnehviir teaches you a word each time you summon him from the Soul Cairn.
A89: N | B89: Vaaz | C89: Tear
A90: N | B90: Zol | C90: Zombie
B91: =HYPERLINK("https://en.uesp.net/wiki/Skyrim:Summon_Durnehviir", "Summon Durnehviir (Dawnguard)") -> Summon Durnehviir (Dawnguard)
A92: N | B92: Dur | C92: Curse | D92: =HYPERLINK("https://en.uesp.net/wiki/Skyrim:Soul_Cairn","Soul Cairn - During Beyond Death") -> Soul Cairn - During Beyond Death
A93: N | B93: Neh | C93: Never
A94: N | B94: Viir | C94: Dying
B95: =HYPERLINK("https://en.uesp.net/wiki/Skyrim:Battle_Fury", "Battle Fury (Dragonborn)") -> Battle Fury (Dragonborn)
A96: N | B96: Mid | C96: Loyal | D96: =HYPERLINK("https://en.uesp.net/wiki/Skyrim:Vahlok%27s_Tomb","Vahlok's Tomb") -> Vahlok's Tomb
A97: N | B97: Vur | C97: Valor
A98: N | B98: Shaan | C98: Inspire
B99: =HYPERLINK("https://en.uesp.net/wiki/Skyrim:Bend_Will", "Bend Will (Dragonborn)") -> Bend Will (Dragonborn)
A100: N | B100: Gol | C100: Earth | D100: =HYPERLINK("https://en.uesp.net/wiki/Skyrim:Saering%27s_Watch","Saering's Watch") -> Saering's Watch
...

Sheet Locations
A1: Location Name | B1: Location Category | C1: Region | D1: Discovered? | E1: Visited? | F1: Cleared?
A2: * indicates additional info. Refer to the wiki link under "bugs" or a note inside a cell | G2: HIDDEN
A3: Vanilla Locations | G3: Count total %
A4: Location Name | B4: Location Category | C4: Region | D4: Discovered? | E4: Visited? | F4: Cleared? | G4: =countif(D6:F478,"Y")/(countif(D6:F478,"Y") + countif(D6:F478,"N")) -> 0
A5: - | B5: - | C5: - | D5: =COUNTIF(D6:D365,"Y")/(COUNTIF(D6:D365,"Y") + COUNTIF(D6:D365,"N")) -> 0 | E5: =COUNTIF(E6:E365,"Y")/(COUNTIF(E6:E365,"Y") + COUNTIF(E6:E365,"N")) -> 0 | F5: =COUNTIF(F6:F365,"Y")/(COUNTIF(F6:F365,"Y") + COUNTIF(F6:F365,"N")) -> 0
A6: =HYPERLINK("https://en.uesp.net/wiki/Skyrim:Abandoned_Prison","Abandoned Prison") -> Abandoned Prison | B6: Imperial Tower | C6: Eastmarch | D6: N | E6: N | F6: N
A7: =HYPERLINK("https://en.uesp.net/wiki/Skyrim:Abandoned_Shack","Abandoned Shack") -> Abandoned Shack | B7: Shack | C7: Hjaalmarch | D7: N | E7: N | F7: -
A8: =HYPERLINK("https://en.uesp.net/wiki/Skyrim:Alchemist%27s_Shack","Alchemist's Shack") -> Alchemist's Shack | B8: Shack | C8: The Rift | D8: N | E8: N | F8: -
A9: =HYPERLINK("https://en.uesp.net/wiki/Skyrim:Alftand","Alftand") -> Alftand | B9: Dwarven Ruin | C9: Winterhold | D9: N | E9: N | F9: N
A10: =HYPERLINK("https://en.uesp.net/wiki/Skyrim:Ancient%27s_Ascent","Ancient's Ascent") -> Ancient's Ascent | B10: Dragon Lair | C10: Falkreath Hold | D10: N | E10: N | F10: N
A11: =HYPERLINK("https://en.uesp.net/wiki/Skyrim:Anga%27s_Mill","Anga's Mill") -> Anga's Mill | B11: Wood Mill | C11: The Pale | D11: N | E11: N | F11: -
A12: =HYPERLINK("https://en.uesp.net/wiki/Skyrim:Angarvunde","Angarvunde") -> Angarvunde | B12: Nordic Ruin | C12: Eastmarch | D12: N | E12: N | F12: N
A13: =HYPERLINK("https://en.uesp.net/wiki/Skyrim:Angi%27s_Camp","Angi's Camp") -> Angi's Camp | B13: Shack | C13: Falkreath Hold | D13: N | E13: N | F13: -
A14: =HYPERLINK("https://en.uesp.net/wiki/Skyrim:Anise%27s_Cabin","Anise's Cabin") -> Anise's Cabin | B14: Shack | C14: Falkreath Hold | D14: N | E14: N | F14: -
A15: =HYPERLINK("https://en.uesp.net/wiki/Skyrim:Ansilvund","Ansilvund") -> Ansilvund | B15: Nordic Ruin | C15: Eastmarch | D15: N | E15: N | F15: N
A16: =HYPERLINK("https://en.uesp.net/wiki/Skyrim:Arcwind_Point","Arcwind Point") -> Arcwind Point | B16: Nordic Ruin | C16: The Rift | D16: N | E16: N | F16: N
A17: =HYPERLINK("https://en.uesp.net/wiki/Skyrim:Autumnshade_Clearing","Autumnshade Clearing") -> Autumnshade Clearing | B17: Clearing | C17: The Rift | D17: N | E17: N | F17: N
A18: =HYPERLINK("https://en.uesp.net/wiki/Skyrim:Autumnwatch_Tower","Autumnwatch Tower") -> Autumnwatch Tower | B18: Dragon Lair | C18: The Rift | D18: N | E18: N | F18: N
A19: =HYPERLINK("https://en.uesp.net/wiki/Skyrim:Avanchnzel","Avanchnzel") -> Avanchnzel | B19: Dwarven Ruin | C19: The Rift | D19: N | E19: N | F19: N
A20: =HYPERLINK("https://en.uesp.net/wiki/Skyrim:Bannermist_Tower","Bannermist Tower") -> Bannermist Tower | B20: Nordic Tower | C20: Falkreath Hold | D20: N | E20: N | F20: N
A21: =HYPERLINK("https://en.uesp.net/wiki/Skyrim:Bard%27s_Leap_Summit","Bard's Leap Summit") -> Bard's Leap Summit | B21: Landmark | C21: The Reach | D21: N | E21: N | F21: -
A22: =HYPERLINK("https://en.uesp.net/wiki/Skyrim:Battle-Born_Farm","Battle-Born Farm") -> Battle-Born Farm | B22: Wheat Mill | C22: Whiterun Hold | D22: N | E22: N | F22: -
A23: =HYPERLINK("https://en.uesp.net/wiki/Skyrim:Bilegulch_Mine","Bilegulch Mine") -> Bilegulch Mine | B23: Mine | C23: Falkreath Hold | D23: N | E23: N | F23: N
A24: =HYPERLINK("https://en.uesp.net/wiki/Skyrim:Black-Briar_Lodge","Black-Briar Lodge") -> Black-Briar Lodge | B24: Settlement | C24: The Rift | D24: N | E24: N | F24: -
A25: =HYPERLINK("https://en.uesp.net/wiki/Skyrim:Bleak_Falls_Barrow_(place)","Bleak Falls Barrow") -> Bleak Falls Barrow | B25: Nordic Ruin | C25: Falkreath Hold | D25: N | E25: N | F25: N
A26: =HYPERLINK("https://en.uesp.net/wiki/Skyrim:Bleakcoast_Cave","Bleakcoast Cave") -> Bleakcoast Cave | B26: Cave | C26: Winterhold | D26: N | E26: N | F26: N
A27: =HYPERLINK("https://en.uesp.net/wiki/Skyrim:Bleakwind_Basin","Bleakwind Basin") -> Bleakwind Basin | B27: Giant Camp | C27: Whiterun Hold | D27: N | E27: N | F27: N
A28: =HYPERLINK("https://en.uesp.net/wiki/Skyrim:Bleakwind_Bluff","Bleakwind Bluff") -> Bleakwind Bluff | B28: Nordic Tower | C28: The Reach | D28: N | E28: N | F28: N
A29: =HYPERLINK("https://en.uesp.net/wiki/Skyrim:Blind_Cliff_Cave","Blind Cliff Cave") -> Blind Cliff Cave | B29: Cave | C29: The Reach | D29: N | E29: N | F29: N
A30: =HYPERLINK("https://en.uesp.net/wiki/Skyrim:Blizzard_Rest","Blizzard Rest") -> Blizzard Rest | B30: Giant Camp | C30: The Pale | D30: N | E30: N | F30: N
A31: =HYPERLINK("https://en.uesp.net/wiki/Skyrim:Bloated_Man%27s_Grotto","Bloated Man's Grotto") -> Bloated Man's Grotto | B31: Cave | C31: Falkreath Hold | D31: N | E31: N | F31: N
A32: =HYPERLINK("https://en.uesp.net/wiki/Skyrim:Bloodlet_Throne","Bloodlet Throne") -> Bloodlet Throne | B32: Military Fort | C32: Falkreath Hold | D32: N | E32: N | F32: N
A33: =HYPERLINK("https://en.uesp.net/wiki/Skyrim:Blue_Palace","Blue Palace") -> Blue Palace | B33: Castle | C33: Haafingar | D33: N | E33: N | F33: -
A34: =HYPERLINK("https://en.uesp.net/wiki/Skyrim:Bonechill_Passage","Bonechill Passage") -> Bonechill Passage | B34: Cave | C34: Falkreath Hold | D34: N | E34: N | F34: N
A35: =HYPERLINK("https://en.uesp.net/wiki/Skyrim:Bonestrewn_Crest","Bonestrewn Crest") -> Bonestrewn Crest | B35: Dragon Lair | C35: Eastmarch | D35: N | E35: N | F35: N
A36: =HYPERLINK("https://en.uesp.net/wiki/Skyrim:Boulderfall_Cave","Boulderfall Cave") -> Boulderfall Cave | B36: Cave | C36: The Rift | D36: N | E36: N | F36: N
A37: =HYPERLINK("https://en.uesp.net/wiki/Skyrim:Brandy-Mug_Farm","Brandy-Mug Farm") -> Brandy-Mug Farm | B37: Farm/Settlement | C37: Eastmarch | D37: N | E37: N | F37: -
A38: =HYPERLINK("https://en.uesp.net/wiki/Skyrim:Brinewater_Grotto","Brinewater Grotto") -> Brinewater Grotto | B38: Cave | C38: Haafingar | D38: N | E38: N | F38: -
A39: =HYPERLINK("https://en.uesp.net/wiki/Skyrim:Broken_Fang_Cave","Broken Fang Cave") -> Broken Fang Cave | B39: Cave | C39: Whiterun Hold | D39: N | E39: N | F39: N
A40: =HYPERLINK("https://en.uesp.net/wiki/Skyrim:Broken_Helm_Hollow","Broken Helm Hollow") -> Broken Helm Hollow | B40: Cave | C40: The Rift | D40: N | E40: N | F40: N
A41: =HYPERLINK("https://en.uesp.net/wiki/Skyrim:Broken_Limb_Camp","Broken Limb Camp") -> Broken Limb Camp | B41: Giant Camp | C41: Eastmarch | D41: N | E41: N | F41: N
A42: =HYPERLINK("https://en.uesp.net/wiki/Skyrim:Broken_Oar_Grotto","Broken Oar Grotto") -> Broken Oar Grotto | B42: Cave | C42: Haafingar | D42: N | E42: N | F42: N
A43: =HYPERLINK("https://en.uesp.net/wiki/Skyrim:Broken_Tower_Redoubt","Broken Tower Redoubt") -> Broken Tower Redoubt | B43: Military Fort | C43: The Reach | D43: N | E43: N | F43: N
A44: =HYPERLINK("https://en.uesp.net/wiki/Skyrim:Bronze_Water_Cave","Bronze Water Cave") -> Bronze Water Cave | B44: Cave | C44: The Pale | D44: N | E44: N | F44: N
A45: =HYPERLINK("https://en.uesp.net/wiki/Skyrim:Brood_Cavern","Brood Cavern") -> Brood Cavern | B45: Cave | C45: Hjaalmarch | D45: N | E45: N | F45: N
A46: =HYPERLINK("https://en.uesp.net/wiki/Skyrim:Bruca%27s_Leap_Redoubt","Bruca's Leap Redoubt") -> Bruca's Leap Redoubt | B46: Cave | C46: The Reach | D46: N | E46: N | F46: N
A47: =HYPERLINK("https://en.uesp.net/wiki/Skyrim:Bthardamz","Bthardamz") -> Bthardamz | B47: Dwarven Ruin | C47: The Reach | D47: N | E47: N | F47: N
A48: =HYPERLINK("https://en.uesp.net/wiki/Skyrim:Chillfurrow_Farm","Chillfurrow Farm") -> Chillfurrow Farm | B48: Wheat Mill | C48: Whiterun Hold | D48: N | E48: N | F48: -
A49: =HYPERLINK("https://en.uesp.net/wiki/Skyrim:Chillwind_Depths","Chillwind Depths") -> Chillwind Depths | B49: Cave | C49: Hjaalmarch | D49: N | E49: N | F49: N
A50: =HYPERLINK("https://en.uesp.net/wiki/Skyrim:Clearpine_Pond","Clearpine Pond") -> Clearpine Pond | B50: Clearing | C50: Haafingar | D50: N | E50: N | F50: N
A51: =HYPERLINK("https://en.uesp.net/wiki/Skyrim:Clearspring_Tarn","Clearspring Tarn") -> Clearspring Tarn | B51: Clearing | C51: The Rift | D51: N | E51: N | F51: N
A52: =HYPERLINK("https://en.uesp.net/wiki/Skyrim:Cliffside_Retreat","Cliffside Retreat") -> Cliffside Retreat | B52: Shack | C52: The Reach | D52: N | E52: N | F52: -
A53: =HYPERLINK("https://en.uesp.net/wiki/Skyrim:College_of_Winterhold_(place)","College of Winterhold") -> College of Winterhold | B53: Guild Hall | C53: Winterhold | D53: N | E53: N | F53: -
A54: =HYPERLINK("https://en.uesp.net/wiki/Skyrim:Crabber%27s_Shanty","Crabber's Shanty") -> Crabber's Shanty | B54: Shack | C54: Hjaalmarch | D54: N | E54: N | F54: -
A55: =HYPERLINK("https://en.uesp.net/wiki/Skyrim:Cracked_Tusk_Keep","Cracked Tusk Keep") -> Cracked Tusk Keep | B55: Military Fort | C55: Falkreath Hold | D55: N | E55: N | F55: N
A56: =HYPERLINK("https://en.uesp.net/wiki/Skyrim:Cradle_Stone_Tower","Cradle Stone Tower") -> Cradle Stone Tower | B56: Nordic Tower | C56: The Reach | D56: N | E56: N | F56: N
A57: =HYPERLINK("https://en.uesp.net/wiki/Skyrim:Cradlecrush_Rock","Cradlecrush Rock") -> Cradlecrush Rock | B57: Giant Camp | C57: Eastmarch | D57: N | E57: N | F57: N
A58: =HYPERLINK("https://en.uesp.net/wiki/Skyrim:Cragslane_Cavern","Cragslane Cavern") -> Cragslane Cavern | B58: Cave | C58: Eastmarch | D58: N | E58: N | F58: N
A59: =HYPERLINK("https://en.uesp.net/wiki/Skyrim:Cragwallow_Slope","Cragwallow Slope") -> Cragwallow Slope | B59: Cave | C59: Eastmarch | D59: N | E59: N | F59: N
A60: =HYPERLINK("https://en.uesp.net/wiki/Skyrim:Cronvangr_Cave","Cronvangr Cave") -> Cronvangr Cave | B60: Cave | C60: Eastmarch | D60: N | E60: N | F60: N
A61: =HYPERLINK("https://en.uesp.net/wiki/Skyrim:Crystaldrift_Cave","Crystaldrift Cave") -> Crystaldrift Cave | B61: Cave | C61: The Rift | D61: N | E61: N | F61: N
A62: =HYPERLINK("https://en.uesp.net/wiki/Skyrim:Dainty_Sload","Dainty Sload") -> Dainty Sload | B62: Shipwreck | C62: Haafingar | D62: N | E62: N | F62: N
A63: =HYPERLINK("https://en.uesp.net/wiki/Skyrim:Dark_Brotherhood_Sanctuary","Dark Brotherhood Sanctuary") -> Dark Brotherhood Sanctuary | B63: Guild Hall | C63: Falkreath Hold | D63: N | E63: N | F63: -
A64: =HYPERLINK("https://en.uesp.net/wiki/Skyrim:Darklight_Tower","Darklight Tower") -> Darklight Tower | B64: Military Fort | C64: The Rift | D64: N | E64: N | F64: N
A65: =HYPERLINK("https://en.uesp.net/wiki/Skyrim:Darkshade","Darkshade") -> Darkshade | B65: Cave | C65: Falkreath Hold | D65: N | E65: N | F65: N
A66: =HYPERLINK("https://en.uesp.net/wiki/Skyrim:Darkwater_Crossing","Darkwater Crossing") -> Darkwater Crossing | B66: Settlement/Mine | C66: Eastmarch | D66: N | E66: N | F66: -
A67: =HYPERLINK("https://en.uesp.net/wiki/Skyrim:Darkwater_Pass","Darkwater Pass") -> Darkwater Pass | B67: Cave | C67: The Rift | D67: N | E67: N | F67: N
A68: =HYPERLINK("https://en.uesp.net/wiki/Skyrim:Dawnstar","Dawnstar") -> Dawnstar | B68: City | C68: The Pale | D68: N | E68: N | F68: -
A69: =HYPERLINK("https://en.uesp.net/wiki/Skyrim:Dawnstar_Sanctuary","Dawnstar Sanctuary") -> Dawnstar Sanctuary | B69: Guild Hall | C69: The Pale | D69: N | E69: N | F69: -
A70: =HYPERLINK("https://en.uesp.net/wiki/Skyrim:Dead_Crone_Rock","Dead Crone Rock") -> Dead Crone Rock | B70: Nordic Tower | C70: The Reach | D70: N | E70: N | F70: N
A71: =HYPERLINK("https://en.uesp.net/wiki/Skyrim:Dead_Men%27s_Respite","Dead Men's Respite") -> Dead Men's Respite | B71: Nordic Ruin | C71: Hjaalmarch | D71: N | E71: N | F71: N
A72: =HYPERLINK("https://en.uesp.net/wiki/Skyrim:Deep_Folk_Crossing","Deep Folk Crossing") -> Deep Folk Crossing | B72: Landmark | C72: The Reach | D72: N | E72: N | F72: -
A73: =HYPERLINK("https://en.uesp.net/wiki/Skyrim:Deepwood_Redoubt","Deepwood Redoubt") -> Deepwood Redoubt | B73: Nordic Ruin | C73: The Reach | D73: N | E73: N | F73: N
A74: =HYPERLINK("https://en.uesp.net/wiki/Skyrim:Dragon_Bridge","Dragon Bridge") -> Dragon Bridge | B74: Town | C74: Haafingar | D74: N | E74: N | F74: -
A75: =HYPERLINK("https://en.uesp.net/wiki/Skyrim:Dragon_Bridge_Overlook","Dragon Bridge Overlook") -> Dragon Bridge Overlook | B75: Camp | C75: The Reach | D75: N | E75: N | F75: N
A76: =HYPERLINK("https://en.uesp.net/wiki/Skyrim:Dragonsreach","Dragonsreach") -> Dragonsreach | B76: Castle | C76: Whiterun Hold | D76: N | E76: N | F76: -
A77: =HYPERLINK("https://en.uesp.net/wiki/Skyrim:Dragontooth_Crater","Dragontooth Crater") -> Dragontooth Crater | B77: Dragon Lair | C77: The Reach | D77: N | E77: N | F77: N
A78: =HYPERLINK("https://en.uesp.net/wiki/Skyrim:Drelas%27_Cottage","Drelas' Cottage") -> Drelas' Cottage | B78: Shack | C78: Whiterun Hold | D78: N | E78: N | F78: N
A79: =HYPERLINK("https://en.uesp.net/wiki/Skyrim:Driftshade_Refuge","Driftshade Refuge") -> Driftshade Refuge | B79: Military Fort | C79: Winterhold | D79: N | E79: N | F79: N
A80: =HYPERLINK("https://en.uesp.net/wiki/Skyrim:Druadach_Redoubt","Druadach Redoubt") -> Druadach Redoubt | B80: Camp | C80: The Reach | D80: N | E80: N | F80: N
A81: =HYPERLINK("https://en.uesp.net/wiki/Skyrim:Dushnikh_Yal","Dushnikh Yal") -> Dushnikh Yal | B81: Orc Stronghold | C81: The Reach | D81: N | E81: N | F81: -
A82: =HYPERLINK("https://en.uesp.net/wiki/Skyrim:Duskglow_Crevice","Duskglow Crevice") -> Duskglow Crevice | B82: Cave | C82: The Pale | D82: N | E82: N | F82: N
A83: =HYPERLINK("https://en.uesp.net/wiki/Skyrim:Dustman%27s_Cairn","Dustman's Cairn") -> Dustman's Cairn | B83: Nordic Ruin | C83: The Reach | D83: N | E83: N | F83: N
A84: =HYPERLINK("https://en.uesp.net/wiki/Skyrim:East_Empire_Company_Warehouse", "East Empire Company Warehouse") -> East Empire Company Warehouse | B84: Dock | C84: Hjaalmarch | D84: N | E84: N | F84: -
A85: =HYPERLINK("https://en.uesp.net/wiki/Skyrim:Eldergleam_Sanctuary","Eldergleam Sanctuary") -> Eldergleam Sanctuary | B85: Cave | C85: Eastmarch | D85: N | E85: N | F85: -
A86: =HYPERLINK("https://en.uesp.net/wiki/Skyrim:Eldersblood_Peak","Eldersblood Peak") -> Eldersblood Peak | B86: Dragon Lair | C86: Hjaalmarch | D86: N | E86: N | F86: N
A87: =HYPERLINK("https://en.uesp.net/wiki/Skyrim:Embershard_Mine","Embershard Mine") -> Embershard Mine | B87: Mine | C87: Falkreath Hold | D87: N | E87: N | F87: N
A88: =HYPERLINK("https://en.uesp.net/wiki/Skyrim:Evergreen_Grove","Evergreen Grove") -> Evergreen Grove | B88: Grove | C88: Falkreath Hold | D88: N | E88: N | F88: N
A89: =HYPERLINK("https://en.uesp.net/wiki/Skyrim:Faldar%27s_Tooth","Faldar's Tooth") -> Faldar's Tooth | B89: Military Fort | C89: The Rift | D89: N | E89: N | F89: N
A90: =HYPERLINK("https://en.uesp.net/wiki/Skyrim:Falkreath","Falkreath") -> Falkreath | B90: City | C90: Falkreath Hold | D90: N | E90: N | F90: -
A91: =HYPERLINK("https://en.uesp.net/wiki/Skyrim:Falkreath_Watchtower","Falkreath Watchtower") -> Falkreath Watchtower | B91: Imperial Tower | C91: Falkreath Hold | D91: N | E91: N | F91: N
A92: =HYPERLINK("https://en.uesp.net/wiki/Skyrim:Fallowstone_Cave","Fallowstone Cave") -> Fallowstone Cave | B92: Cave | C92: The Rift | D92: N | E92: N | F92: N
A93: =HYPERLINK("https://en.uesp.net/wiki/Skyrim:Fellglow_Keep","Fellglow Keep") -> Fellglow Keep | B93: Military Fort | C93: Whiterun Hold | D93: N | E93: N | F93: N
A94: =HYPERLINK("https://en.uesp.net/wiki/Skyrim:Folgunthur","Folgunthur") -> Folgunthur | B94: Nordic Ruin | C94: Hjaalmarch | D94: N | E94: N | F94: N
A95: =HYPERLINK("https://en.uesp.net/wiki/Skyrim:Forelhost","Forelhost") -> Forelhost | B95: Nordic Ruin | C95: The Rift | D95: N | E95: N | F95: N
A96: =HYPERLINK("https://en.uesp.net/wiki/Skyrim:Forsaken_Cave","Forsaken Cave") -> Forsaken Cave | B96: Cave | C96: The Pale | D96: N | E96: N | F96: N
A97: =HYPERLINK("https://en.uesp.net/wiki/Skyrim:Fort_Amol","Fort Amol") -> Fort Amol | B97: Military Fort | C97: Eastmarch | D97: N | E97: N | F97: -
A98: =HYPERLINK("https://en.uesp.net/wiki/Skyrim:Fort_Dunstad","Fort Dunstad") -> Fort Dunstad | B98: Military Fort | C98: The Pale | D98: N | E98: N | F98: -
A99: =HYPERLINK("https://en.uesp.net/wiki/Skyrim:Fort_Fellhammer","Fort Fellhammer") -> Fort Fellhammer | B99: Military Fort/Mine | C99: Winterhold | D99: N | E99: N | F99: N
A100: =HYPERLINK("https://en.uesp.net/wiki/Skyrim:Fort_Greenwall","Fort Greenwall") -> Fort Greenwall | B100: Military Fort | C100: The Rift | D100: N | E100: N | F100: -
...

Sheet Merchants
A1: Merchant Name | B1: Partner or (Replacment) | C1: Invested? | D1: Alive? | E1: P/R Alive? | F1: Region | G1: Store/Location Name | H1: Merchandise | I1: Gold | J1: Investable | K1: Master Trader | L1: Notes
A2: A compiled list of all the merchants in skyrim * indicates there is additional info in the notes section.
A3: - | B3: - | C3: =countif(C4:C132,"Y")/(countif(C4:C132,"Y") + countif(C4:C132,"N")) -> 0 | D3: =countif(D4:D132,"Y")/(countif(D4:D132,"Y") + countif(D4:D132,"N")) -> 1 | E3: =countif(E4:E132,"Y")/(countif(E4:E132,"Y") + countif(E4:E132,"N")) -> 1 | F3: - | G3: - | H3: - | I3: - | J3: - | K3: - | L3: -
A4: =HYPERLINK("https://en.uesp.net/wiki/Skyrim:Rustleif", "Rustleif") -> Rustleif | B4: =HYPERLINK("https://en.uesp.net/wiki/Skyrim:Seren", "Seren") -> Seren | C4: N | D4: Y | E4: Y | F4: Dawnstar | G4: =HYPERLINK("https://en.uesp.net/wiki/Skyrim:Rustleif's_House", "Rustleif's House") -> Rustleif's House | H4: Blacksmith | I4: 1000 | J4: Yes | K4: Yes
A5: =HYPERLINK("https://en.uesp.net/wiki/Skyrim:Frida", "Frida") -> Frida | C5: N | D5: Y | E5: - | F5: Dawnstar | G5: =HYPERLINK("https://en.uesp.net/wiki/Skyrim:The_Mortar_and_Pestle", "The Mortar and Pestle") -> The Mortar and Pestle | H5: Apothecary | I5: 500 | J5: Yes | K5: Yes
A6: =HYPERLINK("https://en.uesp.net/wiki/Skyrim:Madena", "Madena") -> Madena | C6: - | D6: Y | E6: - | F6: Dawnstar | G6: =HYPERLINK("https://en.uesp.net/wiki/Skyrim:The_White_Hall", "The White Hall") -> The White Hall | H6: Spells | I6: 500 | J6: No | K6: Yes
A7: =HYPERLINK("https://en.uesp.net/wiki/Skyrim:Thoring", "Thoring") -> Thoring | B7: =HYPERLINK("https://en.uesp.net/wiki/Skyrim:Karita_(bard)", "(Karita)") -> (Karita) | C7: - | D7: Y | E7: Y | F7: Dawnstar | G7: =HYPERLINK("https://en.uesp.net/wiki/Skyrim:Windpeak_Inn", "Windpeak Inn") -> Windpeak Inn | H7: Innkeeper | I7: 100 | J7: No | K7: No
A8: =HYPERLINK("https://en.uesp.net/wiki/Skyrim:Hadring", "Hadring") -> Hadring | C8: - | D8: Y | E8: - | F8: Dawnstar - Nightgate Inn | G8: =HYPERLINK("https://en.uesp.net/wiki/Skyrim:Nightgate_Inn", "Nightgate Inn") -> Nightgate Inn | H8: Innkeeper | I8: 100 | J8: No | K8: No
A9: =HYPERLINK("https://en.uesp.net/wiki/Skyrim:Valga_Vinicia", "Valga Vinicia") -> Valga Vinicia | C9: - | D9: Y | E9: - | F9: Falkreath | G9: =HYPERLINK("https://en.uesp.net/wiki/Skyrim:Dead_Man's_Drink", "Dead Man's Drink") -> Dead Man's Drink | H9: Innkeeper | I9: 100 | J9: No | K9: No
A10: =HYPERLINK("https://en.uesp.net/wiki/Skyrim:Zaria", "Zaria") -> Zaria | C10: - | D10: Y | E10: - | F10: Falkreath | G10: =HYPERLINK("https://en.uesp.net/wiki/Skyrim:Grave_Concoctions", "Grave Concoctions") -> Grave Concoctions | H10: Apothecary | I10: 500 | J10: No | K10: Yes
A11: =HYPERLINK("https://en.uesp.net/wiki/Skyrim:Solaf", "Solaf") -> Solaf | C11: N | D11: Y | E11: - | F11: Falkreath | G11: =HYPERLINK("https://en.uesp.net/wiki/Skyrim:Gray_Pine_Goods", "Gray Pine Goods") -> Gray Pine Goods | H11: General; sells Blue Mage Robes | I11: 750 | J11: Yes | K11: Yes
A12: =HYPERLINK("https://en.uesp.net/wiki/Skyrim:Lod", "Lod") -> Lod | C12: - | D12: Y | E12: - | F12: Falkreath | G12: =HYPERLINK("https://en.uesp.net/wiki/Skyrim:Lod's_House", "Lod's House") -> Lod's House | H12: Blacksmith | I12: 1000 | J12: No | K12: Yes
A13: =HYPERLINK("https://en.uesp.net/wiki/Skyrim:Babette", "Babette") -> Babette | C13: - | D13: Y | E13: - | F13: Falkreath | G13: =HYPERLINK("https://en.uesp.net/wiki/Skyrim:Dark_Brotherhood_Sanctuary", "The Dark Brotherhood Sanctuary") -> The Dark Brotherhood Sanctuary | H13: Apothecary (also buys Tools) | I13: 500 | J13: No | K13: Yes
A14: =HYPERLINK("https://en.uesp.net/wiki/Skyrim:Lisbet", "Lisbet") -> Lisbet | B14: =HYPERLINK("https://en.uesp.net/wiki/Skyrim:Imedhnain", "(Imedhnain)") -> (Imedhnain) | C14: N | D14: Y | E14: Y | F14: Markarth | G14: =HYPERLINK("https://en.uesp.net/wiki/Skyrim:Arnleif_and_Sons_Trading_Company", "Arnleif and Sons Trading Company") -> Arnleif and Sons Trading Company | H14: General | I14: 750 | J14: Yes | K14: Yes
A15: =HYPERLINK("https://en.uesp.net/wiki/Skyrim:Ghorza_gra-Bagol", "Ghorza gra-Bagol*") -> Ghorza gra-Bagol* | B15: =HYPERLINK("https://en.uesp.net/wiki/Skyrim:Tacitus_Sallustius", "(Tacitus Sallustius)") -> (Tacitus Sallustius) | C15: N | D15: Y | E15: Y | F15: Markarth | G15: At the forge near The Hag's Cure or in Understone Keep | H15: Blacksmith | I15: 1000 | J15: No* | K15: Yes | L15: Ghorza gra-Bagol will have the dialogue option to invest in her store, but the only option is to decline, due to a bug. However, the option works just fine with Tacitus Sallustius.
A16: =HYPERLINK("https://en.uesp.net/wiki/Skyrim:Endon", "Endon") -> Endon | C16: - | D16: Y | E16: - | F16: Markarth | G16: =HYPERLINK("https://en.uesp.net/wiki/Skyrim:Endon's_House", "Endon's House") -> Endon's House | H16: Fence | I16: 1000-4000 | J16: No | K16: Yes
A17: =HYPERLINK("https://en.uesp.net/wiki/Skyrim:Anton_Virane", "Anton Virane") -> Anton Virane | C17: - | D17: Y | E17: - | F17: Markarth | G17: =HYPERLINK("https://en.uesp.net/wiki/Skyrim:Understone_Keep", "In Understone Keep") -> In Understone Keep | H17: Innkeeper | I17: 100 | J17: No | K17: No
A18: =HYPERLINK("https://en.uesp.net/wiki/Skyrim:Calcelmo", "Calcelmo") -> Calcelmo | C18: N | D18: Y | E18: - | F18: Markarth | G18: =HYPERLINK("https://en.uesp.net/wiki/Skyrim:in_Understone_Keep", "in Understone Keep") -> in Understone Keep | H18: Spells | I18: 500 | J18: Yes | K18: Yes
A19: =HYPERLINK("https://en.uesp.net/wiki/Skyrim:Moth_gro-Bagol", "Moth gro-Bagol*") -> Moth gro-Bagol* | C19: N | D19: Y | E19: - | F19: Markarth | G19: =HYPERLINK("https://en.uesp.net/wiki/Skyrim:Understone_Keep", "in Understone Keep") -> in Understone Keep | H19: Blacksmith | I19: 500 | J19: Yes* | K19: Yes | L19: Investing in Ghorza gra-Bagol or Tacitus Sallustius also invests 500 gold in Moth gro-Bagol, due to another bug.
A20: =HYPERLINK("https://en.uesp.net/wiki/Skyrim:Hogni_Red-Arm", "Hogni Red-Arm") -> Hogni Red-Arm | C20: - | D20: Y | E20: - | F20: Markarth | G20: Marketplace Stall | H20: Innkeeper | I20: 50 | J20: No | K20: No
A21: =HYPERLINK("https://en.uesp.net/wiki/Skyrim:Kerah", "Kerah") -> Kerah | C21: - | D21: Y | E21: - | F21: Markarth | G21: Marketplace Stall | H21: Jeweler | I21: 50 | J21: No | K21: No
A22: =HYPERLINK("https://en.uesp.net/wiki/Skyrim:Kleppr", "Kleppr") -> Kleppr | B22: =HYPERLINK("https://en.uesp.net/wiki/Skyrim:Frabbi", "(Frabbi)") -> (Frabbi) | C22: - | D22: Y | E22: Y | F22: Markarth | G22: =HYPERLINK("https://en.uesp.net/wiki/Skyrim:Silver-Blood_Inn", "Silver-Blood Inn") -> Silver-Blood Inn | H22: Innkeeper | I22: 100 | J22: No | K22: No
A23: =HYPERLINK("https://en.uesp.net/wiki/Skyrim:Bothela", "Bothela") -> Bothela | B23: =HYPERLINK("https://en.uesp.net/wiki/Skyrim:Muiri", "(Muiri)") -> (Muiri) | C23: N | D23: Y | E23: Y | F23: Markarth | G23: =HYPERLINK("https://en.uesp.net/wiki/Skyrim:The_Hag's_Cure", "The Hag's Cure") -> The Hag's Cure | H23: Apothecary | I23: 500 | J23: Yes | K23: Yes
A24: =HYPERLINK("https://en.uesp.net/wiki/Skyrim:Gharol", "Gharol") -> Gharol | C24: - | D24: Y | E24: - | F24: Markarth - Dushnikh Yal | G24: =HYPERLINK("https://en.uesp.net/wiki/Skyrim:Burguk's_Longhouse", "at Burguk's Longhouse") -> at Burguk's Longhouse | H24: Blacksmith | I24: 400 | J24: No | K24: Yes
A25: =HYPERLINK("https://en.uesp.net/wiki/Skyrim:Murbul", "Murbul") -> Murbul | C25: - | D25: Y | E25: - | F25: Markarth - Dushnikh Yal | G25: =HYPERLINK("https://en.uesp.net/wiki/Skyrim:Burguk's_Longhouse", "at Burguk's Longhouse") -> at Burguk's Longhouse | H25: Apothecary | I25: 500 | J25: No | K25: Yes
A26: =HYPERLINK("https://en.uesp.net/wiki/Skyrim:Sharamph", "Sharamph") -> Sharamph | C26: - | D26: Y | E26: - | F26: Markarth - Mor Khazgur | G26: =HYPERLINK("https://en.uesp.net/wiki/Skyrim:Larak's_Longhouse", "at Larak's Longhouse") -> at Larak's Longhouse | H26: Apothecary | I26: 500 | J26: No | K26: Yes
A27: =HYPERLINK("https://en.uesp.net/wiki/Skyrim:Shuftharz", "Shuftharz") -> Shuftharz | C27: - | D27: Y | E27: - | F27: Markarth - Mor Khazgur | G27: =HYPERLINK("https://en.uesp.net/wiki/Skyrim:Larak's_Longhouse", "at Larak's Longhouse") -> at Larak's Longhouse | H27: Blacksmith | I27: 400 | J27: No | K27: Yes
A28: =HYPERLINK("https://en.uesp.net/wiki/Skyrim:Eydis", "Eydis") -> Eydis | B28: =HYPERLINK("https://en.uesp.net/wiki/Skyrim:Leontius_Salvius", "(Leontius Salvius)") -> (Leontius Salvius) | C28: - | D28: Y | E28: Y | F28: Markarth - Old Hroldan Inn | G28: =HYPERLINK("https://en.uesp.net/wiki/Skyrim:Old_Hroldan_Inn", "Old Hroldan Inn") -> Old Hroldan Inn | H28: Innkeeper | I28: 100 | J28: No | K28: No
A29: =HYPERLINK("https://en.uesp.net/wiki/Skyrim:Falion", "Falion") -> Falion | C29: - | D29: Y | E29: - | F29: Morthal | G29: =HYPERLINK("https://en.uesp.net/wiki/Skyrim:Falion's_House", "Falion's House") -> Falion's House | H29: Spells; sells 1 Black Soul Gem | I29: 500 | J29: No | K29: Yes
A30: =HYPERLINK("https://en.uesp.net/wiki/Skyrim:Jonna", "Jonna") -> Jonna | C30: - | D30: Y | E30: - | F30: Morthal | G30: =HYPERLINK("https://en.uesp.net/wiki/Skyrim:Moorside_Inn", "Moorside Inn") -> Moorside Inn | H30: Innkeeper | I30: 100 | J30: No | K30: No
A31: =HYPERLINK("https://en.uesp.net/wiki/Skyrim:Lami", "Lami") -> Lami | C31: N | D31: Y | E31: - | F31: Morthal | G31: =HYPERLINK("https://en.uesp.net/wiki/Skyrim:Thaumaturgist's_Hut", "Thaumaturgist's Hut") -> Thaumaturgist's Hut | H31: Apothecary | I31: 500 | J31: Yes | K31: Yes
A32: =HYPERLINK("https://en.uesp.net/wiki/Skyrim:Imperial_Quartermaster", "Imperial Quartermaster") -> Imperial Quartermaster | C32: - | D32: Y | E32: - | F32: Most Imperial camps | H32: Blacksmith | I32: 1000 | J32: No | K32: No
A33: =HYPERLINK("https://en.uesp.net/wiki/Skyrim:Stormcloak_Quartermaster", "Stormcloak Quartermaster") -> Stormcloak Quartermaster | C33: - | D33: Y | E33: - | F33: Most Stormcloak camps | H33: Blacksmith | I33: 1000 | J33: No | K33: No
A34: =HYPERLINK("https://en.uesp.net/wiki/Skyrim:Hunter", "Hunter") -> Hunter | C34: - | D34: Y | E34: - | F34: Randomly anywhere in the wilderness | H34: Meat, Hides | I34: 3-36* | J34: No | K34: No | L34: Hunters will not dissipate their wealth when you sell them things. They have theoretically unlimited wealth. It is just that they will only pay up to a certain amount of gold for a single item, or a single stack of items.
A35: =HYPERLINK("https://en.uesp.net/wiki/Skyrim:Skooma_Dealer_(NPC)", "Skooma Dealer") -> Skooma Dealer | C35: - | D35: Y | E35: - | F35: Randomly anywhere in the wilderness | H35: Moon Sugar, Skooma, Sleeping Tree Sap | I35: 20-56 | J35: No | K35: No
A36: =HYPERLINK("https://en.uesp.net/wiki/Skyrim:Peddler", "Peddler") -> Peddler | C36: - | D36: Y | E36: - | F36: Randomly anywhere in the wilderness (being attacked by bandits or Forsworn) | H36: General Goods | I36: 50-77 | J36: No | K36: No
A37: =HYPERLINK("https://en.uesp.net/wiki/Skyrim:Ungrien", "Ungrien") -> Ungrien | C37: - | D37: Y | E37: - | F37: Riften | G37: =HYPERLINK("https://en.uesp.net/wiki/Skyrim:Black-Briar_Meadery", "Black-Briar Meadery") -> Black-Briar Meadery | H37: Innkeeper | I37: 100 | J37: No | K37: No
A38: =HYPERLINK("https://en.uesp.net/wiki/Skyrim:Elgrim", "Elgrim") -> Elgrim | B38: =HYPERLINK("https://en.uesp.net/wiki/Skyrim:Hafjorg", "Hafjorg") -> Hafjorg | C38: N | D38: Y | E38: - | F38: Riften | G38: =HYPERLINK("https://en.uesp.net/wiki/Skyrim:Elgrim's_Elixirs", "Elgrim's Elixirs") -> Elgrim's Elixirs | H38: Apothecary | I38: 500 | J38: Yes | K38: Yes
A39: =HYPERLINK("https://en.uesp.net/wiki/Skyrim:Wylandriah", "Wylandriah") -> Wylandriah | C39: N | D39: Y | E39: - | F39: Riften | G39: =HYPERLINK("https://en.uesp.net/wiki/Skyrim:Mistveil_Keep", "in Mistveil Keep") -> in Mistveil Keep | H39: Spells | I39: 500 | J39: Yes | K39: Yes
A40: =HYPERLINK("https://en.uesp.net/wiki/Skyrim:Brand-Shei", "Brand-Shei") -> Brand-Shei | C40: - | D40: Y | E40: - | F40: Riften | G40: =HYPERLINK("https://en.uesp.net/wiki/Skyrim:Marketplace_Stall", "Marketplace Stall") -> Marketplace Stall | H40: General | I40: 750 | J40: No | K40: Yes
A41: =HYPERLINK("https://en.uesp.net/wiki/Skyrim:Grelka", "Grelka") -> Grelka | C41: - | D41: Y | E41: - | F41: Riften | G41: Marketplace Stall | H41: General | I41: 750 | J41: No | K41: Yes
A42: =HYPERLINK("https://en.uesp.net/wiki/Skyrim:Madesi", "Madesi") -> Madesi | C42: - | D42: Y | E42: - | F42: Riften | G42: Marketplace Stall | H42: Jeweler | I42: 750 | J42: No | K42: No
A43: =HYPERLINK("https://en.uesp.net/wiki/Skyrim:Marise_Aravel", "Marise Aravel") -> Marise Aravel | C43: - | D43: Y | E43: - | F43: Riften | G43: Marketplace Stall | H43: General | I43: 50 | J43: No | K43: No
A44: =HYPERLINK("https://en.uesp.net/wiki/Skyrim:Bersi_Honey-Hand", "Bersi Honey-Hand") -> Bersi Honey-Hand | B44: =HYPERLINK("https://en.uesp.net/wiki/Skyrim:Drifa", "(Drifa)") -> (Drifa) | C44: N | D44: Y | E44: Y | F44: Riften | G44: =HYPERLINK("https://en.uesp.net/wiki/Skyrim:Pawned_Prawn", "Pawned Prawn") -> Pawned Prawn | H44: General | I44: 750 | J44: Yes | K44: Yes
A45: =HYPERLINK("https://en.uesp.net/wiki/Skyrim:Keerava", "Keerava") -> Keerava | B45: =HYPERLINK("https://en.uesp.net/wiki/Skyrim:Talen-Jei", "Talen-Jei") -> Talen-Jei | C45: - | D45: Y | E45: - | F45: Riften | G45: =HYPERLINK("https://en.uesp.net/wiki/Skyrim:The_Bee_and_Barb", "The Bee and Barb") -> The Bee and Barb | H45: Innkeeper | I45: 100 | J45: No | K45: No
A46: =HYPERLINK("https://en.uesp.net/wiki/Skyrim:Arnskar_Ember-Master", "Arnskar Ember-Master") -> Arnskar Ember-Master | C46: - | D46: Y | E46: - | F46: Riften | G46: =HYPERLINK("https://en.uesp.net/wiki/Skyrim:The_Ragged_Flagon", "The Ragged Flagon") -> The Ragged Flagon | H46: Blacksmith | I46: 1000 | J46: No | K46: Yes
A47: =HYPERLINK("https://en.uesp.net/wiki/Skyrim:Herluin_Lothaire", "Herluin Lothaire") -> Herluin Lothaire | C47: - | D47: Y | E47: - | F47: Riften | G47: =HYPERLINK("https://en.uesp.net/wiki/Skyrim:The_Ragged_Flagon", "The Ragged Flagon") -> The Ragged Flagon | H47: Apothecary | I47: 500 | J47: No | K47: Yes
A48: =HYPERLINK("https://en.uesp.net/wiki/Skyrim:Syndus", "Syndus") -> Syndus | C48: - | D48: Y | E48: - | F48: Riften | G48: =HYPERLINK("https://en.uesp.net/wiki/Skyrim:The_Ragged_Flagon", "The Ragged Flagon") -> The Ragged Flagon | H48: Blacksmith | I48: 1000 | J48: No | K48: Yes
A49: =HYPERLINK("https://en.uesp.net/wiki/Skyrim:Tonilia", "Tonilia") -> Tonilia | C49: - | D49: Y | E49: - | F49: Riften | G49: =HYPERLINK("https://en.uesp.net/wiki/Skyrim:The_Ragged_Flagon", "The Ragged Flagon") -> The Ragged Flagon | H49: Fence | I49: 1000-4000 | J49: No | K49: Yes
A50: =HYPERLINK("https://en.uesp.net/wiki/Skyrim:Vanryth_Gatharian", "Vanryth Gatharian") -> Vanryth Gatharian | C50: - | D50: Y | E50: - | F50: Riften | G50: =HYPERLINK("https://en.uesp.net/wiki/Skyrim:The_Ragged_Flagon", "The Ragged Flagon") -> The Ragged Flagon | H50: Blacksmith | I50: 1000 | J50: No | K50: Yes
A51: =HYPERLINK("https://en.uesp.net/wiki/Skyrim:Vekel_the_Man", "Vekel the Man") -> Vekel the Man | B51: =HYPERLINK("https://en.uesp.net/wiki/Skyrim:Dirge", "(Dirge)") -> (Dirge) | C51: - | D51: Y | E51: Y | F51: Riften | G51: =HYPERLINK("https://en.uesp.net/wiki/Skyrim:The_Ragged_Flagon", "The Ragged Flagon") -> The Ragged Flagon | H51: Innkeeper | I51: 100 | J51: No | K51: No
A52: =HYPERLINK("https://en.uesp.net/wiki/Skyrim:Balimund", "Balimund") -> Balimund | B52: =HYPERLINK("https://en.uesp.net/wiki/Skyrim:Asbjorn_Fire-Tamer", "(Asbjorn Fire-Tamer)") -> (Asbjorn Fire-Tamer) | C52: N | D52: Y | E52: Y | F52: Riften | G52: =HYPERLINK("https://en.uesp.net/wiki/Skyrim:The_Scorched_Hammer", "The Scorched Hammer") -> The Scorched Hammer | H52: Blacksmith | I52: 1000 | J52: Yes | K52: Yes
A53: =HYPERLINK("https://en.uesp.net/wiki/Skyrim:Florentius_Baenius", "Florentius Baenius") -> Florentius Baenius | C53: - | D53: Y | E53: - | F53: Riften - Fort Dawnguard | H53: Apothecary, Spells | I53: 500 | J53: No | K53: No | L53: Hostile to vampires
A54: =HYPERLINK("https://en.uesp.net/wiki/Skyrim:Gunmar", "Gunmar") -> Gunmar | C54: - | D54: Y | E54: - | F54: Riften - Fort Dawnguard | H54: Blacksmith | I54: 1000 | J54: No | K54: No | L54: Hostile to vampires
A55: =HYPERLINK("https://en.uesp.net/wiki/Skyrim:Sorine_Jurard", "Sorine Jurard") -> Sorine Jurard | C55: - | D55: Y | E55: - | F55: Riften - Fort Dawnguard | H55: General | I55: 750 | J55: No | K55: No | L55: Hostile to vampires
A56: =HYPERLINK("https://en.uesp.net/wiki/Skyrim:Wilhelm", "Wilhelm") -> Wilhelm | C56: - | D56: Y | E56: - | F56: Riften - Ivarstead | G56: =HYPERLINK("https://en.uesp.net/wiki/Skyrim:Vilemyr_Inn", "Vilemyr Inn") -> Vilemyr Inn | H56: Innkeeper | I56: 100 | J56: No | K56: No
A57: =HYPERLINK("https://en.uesp.net/wiki/Skyrim:Filnjar", "Filnjar") -> Filnjar | C57: - | D57: Y | E57: - | F57: Riften - Shor's Stone | G57: =HYPERLINK("https://en.uesp.net/wiki/Skyrim:Filnjar's_House", "Filnjar's House") -> Filnjar's House | H57: Blacksmith | I57: 500 | J57: No | K57: Yes
A58: =HYPERLINK("https://en.uesp.net/wiki/Skyrim:Angeline_Morrard", "Angeline Morrard*") -> Angeline Morrard* | B58: =HYPERLINK("https://en.uesp.net/wiki/Skyrim:Vivienne_Onis", "(Vivienne Onis)") -> (Vivienne Onis) | C58: N | D58: Y | E58: Y | F58: Solitude | G58: =HYPERLINK("https://en.uesp.net/wiki/Skyrim:Angeline's_Aromatics", "Angeline's Aromatics") -> Angeline's Aromatics | H58: Apothecary | I58: 500 | J58: No* | K58: Yes | L58: It is possible to invest endlessly with Angeline. She never loses the dialogue option to invest, but her permanent base gold cannot increase, due to a bug.
A59: =HYPERLINK("https://en.uesp.net/wiki/Skyrim:Sayma", "Sayma") -> Sayma | C59: N | D59: Y | E59: - | F59: Solitude | G59: =HYPERLINK("https://en.uesp.net/wiki/Skyrim:Bits_and_Pieces", "Bits and Pieces") -> Bits and Pieces | H59: General | I59: 750 | J59: Yes | K59: Yes
A60: =HYPERLINK("https://en.uesp.net/wiki/Skyrim:Sybille_Stentor", "Sybille Stentor") -> Sybille Stentor | B60: =HYPERLINK("https://en.uesp.net/wiki/Skyrim:Melaran", "(Melaran)") -> (Melaran) | C60: N | D60: Y | E60: - | F60: Solitude | G60: =HYPERLINK("https://en.uesp.net/wiki/Skyrim:Blue_Palace", "Blue Palace") -> Blue Palace | H60: Spells | I60: 500 | J60: Yes | K60: Yes
A61: =HYPERLINK("https://en.uesp.net/wiki/Skyrim:Fihada", "Fihada*") -> Fihada* | B61: =HYPERLINK("https://en.uesp.net/wiki/Skyrim:Jawanan", "(Jawanan)") -> (Jawanan) | C61: N | D61: Y | E61: Y | F61: Solitude | G61: =HYPERLINK("https://en.uesp.net/wiki/Skyrim:Fletcher_(place)", "Fletcher") -> Fletcher | H61: Armor, Arrows, Tools, Weapons | I61: 750 | J61: No* | K61: Yes | L61: Fihada has the investment dialogue, allowing you to pay him 500 gold to invest in his store. However, investing in him has no actual effect—his gold is not permanently increased—because his merchant chest does not contain the PerkInvestorStoreUpgrade bonus gold.
A62: =HYPERLINK("https://en.uesp.net/wiki/Skyrim:Addvar", "Addvar") -> Addvar | B62: =HYPERLINK("https://en.uesp.net/wiki/Skyrim:Greta", "(Greta)") -> (Greta) | C62: - | D62: Y | E62: Y | F62: Solitude | G62: Marketplace Stall | H62: Innkeeper | I62: 50 | J62: No | K62: Yes
A63: =HYPERLINK("https://en.uesp.net/wiki/Skyrim:Evette_San", "Evette San") -> Evette San | C63: - | D63: Y | E63: - | F63: Solitude | G63: Marketplace Stall | H63: Innkeeper | I63: 50 | J63: No | K63: Yes
A64: =HYPERLINK("https://en.uesp.net/wiki/Skyrim:Jala", "Jala") -> Jala | C64: - | D64: Y | E64: - | F64: Solitude | G64: Marketplace Stall | H64: Innkeeper | I64: 50 | J64: No | K64: Yes
A65: =HYPERLINK("https://en.uesp.net/wiki/Skyrim:Endarie", "Endarie") -> Endarie | B65: =HYPERLINK("https://en.uesp.net/wiki/Skyrim:Taarie", "Taarie") -> Taarie | C65: N | D65: Y | E65: Y | F65: Solitude | G65: =HYPERLINK("https://en.uesp.net/wiki/Skyrim:Radiant_Raiment", "Radiant Raiment") -> Radiant Raiment | H65: Clothing, Jewelry | I65: 750 | J65: Yes | K65: Yes
A66: =HYPERLINK("https://en.uesp.net/wiki/Skyrim:Beirand", "Beirand") -> Beirand | C66: N | D66: Y | E66: - | F66: Solitude | G66: =HYPERLINK("https://en.uesp.net/wiki/Skyrim:Solitude_Blacksmith", "Solitude Blacksmith") -> Solitude Blacksmith | H66: Blacksmith | I66: 1000 | J66: Yes | K66: Yes
A67: =HYPERLINK("https://en.uesp.net/wiki/Skyrim:Corpulus_Vinius", "Corpulus Vinius") -> Corpulus Vinius | C67: - | D67: Y | E67: - | F67: Solitude | G67: =HYPERLINK("https://en.uesp.net/wiki/Skyrim:The_Winking_Skeever", "The Winking Skeever") -> The Winking Skeever | H67: Innkeeper | I67: 100 | J67: No | K67: Yes
A68: =HYPERLINK("https://en.uesp.net/wiki/Skyrim:Gulum-Ei", "Gulum-Ei") -> Gulum-Ei | C68: - | D68: Y | E68: - | F68: Solitude | G68: =HYPERLINK("https://en.uesp.net/wiki/Skyrim:The_Winking_Skeever", "The Winking Skeever") -> The Winking Skeever | H68: Fence | J68: No | K68: Yes
A69: =HYPERLINK("https://en.uesp.net/wiki/Skyrim:Faida", "Faida") -> Faida | C69: - | D69: Y | E69: - | F69: Solitude - Dragon Bridge | G69: =HYPERLINK("https://en.uesp.net/wiki/Skyrim:Four_Shields_Tavern", "Four Shields Tavern") -> Four Shields Tavern | H69: Innkeeper | I69: 100 | J69: No | K69: No
A70: =HYPERLINK("https://en.uesp.net/wiki/Skyrim:Feran_Sadri", "Feran Sadri") -> Feran Sadri | C70: - | D70: Y | E70: - | F70: Solitude - Volkihar Keep | H70: Apothecary | I70: 500 | J70: No | K70: No | L70: Hostile to non-vampires
A71: =HYPERLINK("https://en.uesp.net/wiki/Skyrim:Hestla", "Hestla") -> Hestla | C71: - | D71: Y | E71: - | F71: Solitude - Volkihar Keep | H71: Blacksmith | I71: 1000 | J71: No | K71: No | L71: Hostile to non-vampires
A72: =HYPERLINK("https://en.uesp.net/wiki/Skyrim:Ronthil", "Ronthil") -> Ronthil | C72: - | D72: Y | E72: - | F72: Solitude - Volkihar Keep | H72: General | I72: 750 | J72: No | K72: No | L72: Hostile to non-vampires
A73: =HYPERLINK("https://en.uesp.net/wiki/Skyrim:Halbarn_Iron-Fur", "Halbarn Iron-Fur") -> Halbarn Iron-Fur | C73: - | D73: Y | E73: - | F73: Solstheim - Bujold's Retreat | G73: Bujold's Retreat / Thirsk Mead Hall | H73: Blacksmith | I73: 1000 | J73: No | K73: Yes
A74: =HYPERLINK("https://en.uesp.net/wiki/Skyrim:Falas_Selvayn", "Falas Selvayn") -> Falas Selvayn | C74: - | D74: Y | E74: - | F74: Solstheim - Ramshackle Trading Post | G74: =HYPERLINK("https://en.uesp.net/wiki/Skyrim:Ramshackle_Trading_Post", "Ramshackle Trading Post") -> Ramshackle Trading Post | H74: General | I74: 750 | J74: No | K74: Yes
A75: =HYPERLINK("https://en.uesp.net/wiki/Skyrim:Fethis_Alor", "Fethis Alor") -> Fethis Alor | C75: - | D75: Y | E75: - | F75: Solstheim - Raven Rock | G75: =HYPERLINK("https://en.uesp.net/wiki/Skyrim:Alor_House", "Alor House") -> Alor House | H75: General | I75: 1500 | J75: No | K75: Yes
A76: =HYPERLINK("https://en.uesp.net/wiki/Skyrim:Glover_Mallory", "Glover Mallory") -> Glover Mallory | C76: - | D76: Y | E76: - | F76: Solstheim - Raven Rock | G76: =HYPERLINK("https://en.uesp.net/wiki/Skyrim:Glover_Mallory's_House", "Glover Mallory's House") -> Glover Mallory's House | H76: Blacksmith | I76: 2000 | J76: No | K76: Yes
A77: =HYPERLINK("https://en.uesp.net/wiki/Skyrim:Garyn_Ienth", "Garyn Ienth") -> Garyn Ienth | C77: - | D77: Y | E77: - | F77: Solstheim - Raven Rock | G77: =HYPERLINK("https://en.uesp.net/wiki/Skyrim:Ienth_Farm", "Ienth Farm") -> Ienth Farm | H77: Innkeeper | I77: 50 | J77: No | K77: No
A78: =HYPERLINK("https://en.uesp.net/wiki/Skyrim:Milore_Ienth", "Milore Ienth") -> Milore Ienth | C78: - | D78: Y | E78: - | F78: Solstheim - Raven Rock | G78: =HYPERLINK("https://en.uesp.net/wiki/Skyrim:Ienth_Farm", "Ienth Farm") -> Ienth Farm | H78: Apothecary | I78: 1000 | J78: No | K78: Yes
A79: =HYPERLINK("https://en.uesp.net/wiki/Skyrim:Geldis_Sadri", "Geldis Sadri") -> Geldis Sadri | C79: - | D79: Y | E79: - | F79: Solstheim - Raven Rock | G79: =HYPERLINK("https://en.uesp.net/wiki/Skyrim:The_Retching_Netch", "The Retching Netch") -> The Retching Netch | H79: Innkeeper | I79: 100 | J79: No | K79: No
A80: =HYPERLINK("https://en.uesp.net/wiki/Skyrim:Baldor_Iron-Shaper", "Baldor Iron-Shaper") -> Baldor Iron-Shaper | C80: - | D80: Y | E80: - | F80: Solstheim - Skaal Village | G80: =HYPERLINK("https://en.uesp.net/wiki/Skyrim:Baldor_Iron-Shaper's_House", "Baldor Iron-Shaper's House") -> Baldor Iron-Shaper's House | H80: Blacksmith | I80: 1000 | J80: No | K80: * | L80: Wiki does not include info on Master Trader perk for this merchant
A81: =HYPERLINK("https://en.uesp.net/wiki/Skyrim:Edla", "Edla") -> Edla | C81: - | D81: Y | E81: - | F81: Solstheim - Skaal Village | G81: =HYPERLINK("https://en.uesp.net/wiki/Skyrim:Edla's_House", "Edla's House") -> Edla's House | H81: Apothecary | I81: 50 | J81: No | K81: No
A82: =HYPERLINK("https://en.uesp.net/wiki/Skyrim:Neloth", "Neloth") -> Neloth | C82: - | D82: Y | E82: - | F82: Solstheim - Tel Mithryn | G82: =HYPERLINK("https://en.uesp.net/wiki/Skyrim:Tel_Mithryn", "Tel Mithryn") -> Tel Mithryn | H82: Staves & Spells | I82: 1000 | J82: No | K82: Yes
A83: =HYPERLINK("https://en.uesp.net/wiki/Skyrim:Revus_Sarvani", "Revus Sarvani") -> Revus Sarvani | C83: - | D83: Y | E83: - | F83: Solstheim - Tel Mithryn | G83: =HYPERLINK("https://en.uesp.net/wiki/Skyrim:Tel_Mithryn", "Tel Mithryn") -> Tel Mithryn | H83: General | I83: 500 | J83: No | K83: No | L83: Found on outskirts of the town with his silt strider
A84: =HYPERLINK("https://en.uesp.net/wiki/Skyrim:Talvas_Fathryon", "Talvas Fathryon") -> Talvas Fathryon | C84: - | D84: Y | E84: - | F84: Solstheim - Tel Mithryn | G84: =HYPERLINK("https://en.uesp.net/wiki/Skyrim:Tel_Mithryn", "Tel Mithryn") -> Tel Mithryn | H84: Spells | I84: 500 | J84: No | K84: Yes
A85: =HYPERLINK("https://en.uesp.net/wiki/Skyrim:Elynea_Mothren", "Elynea Mothren") -> Elynea Mothren | C85: - | D85: Y | E85: - | F85: Solstheim - Tel Mithryn | G85: =HYPERLINK("https://en.uesp.net/wiki/Skyrim:Tel_Mithryn_Apothecary", "Tel Mithryn Apothecary") -> Tel Mithryn Apothecary | H85: Apothecary | I85: 1000 | J85: No | K85: Yes
A86: =HYPERLINK("https://en.uesp.net/wiki/Skyrim:Ahkari", "Ahkari") -> Ahkari | C86: N | D86: Y | E86: - | F86: Traveling - Dawnstar or Riften | G86: =HYPERLINK("https://en.uesp.net/wiki/Skyrim:khajiit_Traders", "Khajiit Traders") -> Khajiit Traders | H86: General; Sells Moon Sugar and Skooma | I86: 750 | J86: Yes | K86: Yes
A87: =HYPERLINK("https://en.uesp.net/wiki/Skyrim:Zaynabi", "Zaynabi") -> Zaynabi | C87: - | D87: Y | E87: - | F87: Traveling - Dawnstar or Riften | G87: =HYPERLINK("https://en.uesp.net/wiki/Skyrim:khajiit_Traders", "khajiit Traders") -> khajiit Traders | H87: Fence | I87: 1000-4000 | J87: No | K87: Yes
A88: =HYPERLINK("https://en.uesp.net/wiki/Skyrim:Atahbah", "Atahbah") -> Atahbah | C88: - | D88: Y | E88: - | F88: Traveling - Markarth or Whiterun | G88: =HYPERLINK("https://en.uesp.net/wiki/Skyrim:khajiit_Traders", "khajiit Traders") -> khajiit Traders | H88: Fence | I88: 1000-4000 | J88: No | K88: Yes
A89: =HYPERLINK("https://en.uesp.net/wiki/Skyrim:Ri'saad", "Ri'saad") -> Ri'saad | C89: N | D89: Y | E89: - | F89: Traveling - Markarth or Whiterun | G89: =HYPERLINK("https://en.uesp.net/wiki/Skyrim:khajiit_Traders", "khajiit Traders") -> khajiit Traders | H89: General; Sells Moon Sugar and Skooma | I89: 750 | J89: Yes | K89: Yes
A90: =HYPERLINK("https://en.uesp.net/wiki/Skyrim:Ma'dran", "Ma'dran") -> Ma'dran | C90: N | D90: Y | E90: - | F90: Traveling - Solitude or Windhelm | G90: =HYPERLINK("https://en.uesp.net/wiki/Skyrim:khajiit_Traders", "khajiit Traders") -> khajiit Traders | H90: General; Sells Moon Sugar and Skooma | I90: 750 | J90: Yes | K90: Yes
A91: =HYPERLINK("https://en.uesp.net/wiki/Skyrim:Ma'jhad", "Ma'jhad") -> Ma'jhad | C91: - | D91: Y | E91: - | F91: Traveling - Solitude or Windhelm | G91: =HYPERLINK("https://en.uesp.net/wiki/Skyrim:khajiit_Traders", "khajiit Traders") -> khajiit Traders | H91: Fence | I91: 1000-4000 | J91: No | K91: Yes
A92: =HYPERLINK("https://en.uesp.net/wiki/Skyrim:Arcadia", "Arcadia") -> Arcadia | C92: N | D92: Y | E92: - | F92: Whiterun | G92: =HYPERLINK("https://en.uesp.net/wiki/Skyrim:Arcadia's_Cauldron", "Arcadia's Cauldron") -> Arcadia's Cauldron | H92: Apothecary | I92: 500 | J92: Yes | K92: Yes
A93: =HYPERLINK("https://en.uesp.net/wiki/Skyrim:Belethor", "Belethor") -> Belethor | C93: N | D93: Y | E93: - | F93: Whiterun | G93: =HYPERLINK("https://en.uesp.net/wiki/Skyrim:Belethor's_General_Goods", "Belethor's General Goods") -> Belethor's General Goods | H93: General | I93: 750 | J93: Yes | K93: Yes
A94: =HYPERLINK("https://en.uesp.net/wiki/Skyrim:Farengar_Secret-Fire", "Farengar Secret-Fire") -> Farengar Secret-Fire | C94: N | D94: Y | E94: - | F94: Whiterun | G94: =HYPERLINK("https://en.uesp.net/wiki/Skyrim:Dragonsreach", "Dragonsreach") -> Dragonsreach | H94: Spells | I94: 500 | J94: Yes | K94: Yes
A95: =HYPERLINK("https://en.uesp.net/wiki/Skyrim:Mallus_Maccius", "Mallus Maccius") -> Mallus Maccius | C95: - | D95: Y | E95: - | F95: Whiterun | G95: =HYPERLINK("https://en.uesp.net/wiki/Skyrim:Honningbrew_Meadery", "Honningbrew Meadery") -> Honningbrew Meadery | H95: Fence | I95: 1000-4000 | J95: No | K95: Yes
A96: =HYPERLINK("https://en.uesp.net/wiki/Skyrim:Sabjorn", "Sabjorn") -> Sabjorn | C96: - | D96: Y | E96: - | F96: Whiterun | G96: =HYPERLINK("https://en.uesp.net/wiki/Skyrim:Honningbrew_Meadery", "Honningbrew Meadery") -> Honningbrew Meadery | H96: Innkeeper | I96: 100 | J96: No | K96: No
A97: =HYPERLINK("https://en.uesp.net/wiki/Skyrim:Anoriath", "Anoriath*") -> Anoriath* | C97: N | D97: Y | E97: - | F97: Whiterun | G97: Marketplace Stall | H97: Innkeeper | I97: 50 | J97: No* | K97: Yes | L97: Anoriath will allow you to invest in his store, but his available gold will not increase due to a bug.
A98: =HYPERLINK("https://en.uesp.net/wiki/Skyrim:Carlotta_Valentia", "Carlotta Valentia") -> Carlotta Valentia | C98: - | D98: Y | E98: - | F98: Whiterun | G98: Marketplace Stall | H98: Innkeeper | I98: 50 | J98: No | K98: Yes
A99: =HYPERLINK("https://en.uesp.net/wiki/Skyrim:Fralia_Gray-Mane", "Fralia Gray-Mane") -> Fralia Gray-Mane | C99: - | D99: Y | E99: - | F99: Whiterun | G99: Marketplace Stall | H99: Jeweler | I99: 50 | J99: No | K99: No
A100: =HYPERLINK("https://en.uesp.net/wiki/Skyrim:Eorlund_Gray-Mane", "Eorlund Gray-Mane") -> Eorlund Gray-Mane | C100: - | D100: Y | E100: - | F100: Whiterun | G100: =HYPERLINK("https://en.uesp.net/wiki/Skyrim:Skyforge", "Skyforge") -> Skyforge | H100: Blacksmith | I100: 1000 | J100: No | K100: Yes
...

Sheet Unique Gear
A1: Gear Name | C1: Gear Type | D1: Obtained? | E1: Notes
A2: Items marked with the same color are mutually exclusive (with each other or by two groups)
A3: Vanilla Skyrim Unique Gear
A5: Gear Name | C5: Gear Type | D5: Obtained? | E5: Notes
A6: - | C6: - | D6: =(countif(D7:D173,"Y")/Rows(D7:D173)) -> 0 | E6: -
A7: =HYPERLINK("https://en.uesp.net/wiki/Skyrim:Aegisbane","Aegisbane") -> Aegisbane | C7: Warhammer | D7: N
A8: =HYPERLINK("https://en.uesp.net/wiki/Skyrim:Dungeon_Delving_(Bandits)#Amren.27s_Family_Sword","Amren's Family Sword") -> Amren's Family Sword | C8: One-handed Sword | D8: N | E8: Quest item, but it can be pickpocketed back after completion.
A9: =HYPERLINK("https://en.uesp.net/wiki/Skyrim:Amulet_of_Articulation", "Amulet of Articulation") -> Amulet of Articulation | C9: Necklace | D9: N
A10: =HYPERLINK("https://en.uesp.net/wiki/Skyrim:Ancient_Helmet_of_the_Unburned","Ancient Helmet of the Unburned") -> Ancient Helmet of the Unburned | C10: Helmet | D10: N
A11: =HYPERLINK("https://en.uesp.net/wiki/Skyrim:Ancient_Shrouded_Armor","Ancient Shrouded Armor") -> Ancient Shrouded Armor | C11: Light Armor | D11: N
A12: =HYPERLINK("https://en.uesp.net/wiki/Skyrim:Ancient_Shrouded_Boots","Ancient Shrouded Boots") -> Ancient Shrouded Boots | C12: Light Boots | D12: N
A13: =HYPERLINK("https://en.uesp.net/wiki/Skyrim:Ancient_Shrouded_Cowl","Ancient Shrouded Cowl") -> Ancient Shrouded Cowl | C13: Light Helmet | D13: N
A14: =HYPERLINK("https://en.uesp.net/wiki/Skyrim:Ancient_Shrouded_Gloves","Ancient Shrouded Gloves") -> Ancient Shrouded Gloves | C14: Light Gauntlets | D14: N
A15: =HYPERLINK("https://en.uesp.net/wiki/Skyrim:Angi%27s_Bow","Angi's Bow") -> Angi's Bow | C15: Bow | D15: N
A16: =HYPERLINK("https://en.uesp.net/wiki/Skyrim:Boots_(Arch-Mage)","Archmage's Boots") -> Archmage's Boots | C16: Clothing | D16: N
A17: =HYPERLINK("https://en.uesp.net/wiki/Skyrim:Archmage%27s_Robes","Archmage's Robes") -> Archmage's Robes | C17: Clothing | D17: N
A18: =HYPERLINK("https://en.uesp.net/wiki/Skyrim:Armor_of_the_Old_Gods","Armor of the Old Gods") -> Armor of the Old Gods | C18: Light Armor | D18: N | E18: You can get this set along with Silver-blood ring. Free Madanach and then after getting the set kill everyone.
A19: =HYPERLINK("https://en.uesp.net/wiki/Skyrim:Quest_Items#Asgeir.27s_Wedding_Band","Asgeir's Wedding Band") -> Asgeir's Wedding Band | C19: Ring | D19: N | E19: During quest "Bound Until Death" can be stolen or took from Asgeir.
A20: =HYPERLINK("https://en.uesp.net/wiki/Skyrim:Azura%27s_Star","Azura's Star") -> Azura's Star | C20: Soul Gem | D20: N
A21: =HYPERLINK("https://en.uesp.net/wiki/Skyrim:The_Black_Star_(item)","Black Star") -> Black Star | C21: Soul Gem | D21: N
A22: =HYPERLINK("https://en.uesp.net/wiki/Skyrim:Blade_of_Sacrifice","Blade of Sacrifice") -> Blade of Sacrifice | C22: Dagger | D22: N | E22: Multiple may be aquired from pickpocketing the cultists during Boethiath's Proving
A23: =HYPERLINK("https://en.uesp.net/wiki/Skyrim:Blade_of_Woe","Blade of Woe") -> Blade of Woe | C23: Dagger | D23: N | E23: Two can be aquired if one is pickpocked from Astrid whe you first meet her
A24: =HYPERLINK("https://en.uesp.net/wiki/Skyrim:Specialty_Gear#Blades_Armor","Blades Armor") -> Blades Armor | C24: Heavy Armor | D24: N
A25: =HYPERLINK("https://en.uesp.net/wiki/Skyrim:Specialty_Gear#Blades_Boots","Blades Boots") -> Blades Boots | C25: Heavy Boots | D25: N
A26: =HYPERLINK("https://en.uesp.net/wiki/Skyrim:Specialty_Gear#Blades_Gauntlets","Blades Gauntlets") -> Blades Gauntlets | C26: Heavy Gauntlets | D26: N
A27: =HYPERLINK("https://en.uesp.net/wiki/Skyrim:Specialty_Gear#Blades_Helmet","Blades Helmet") -> Blades Helmet | C27: Heavy Helmet | D27: N
A28: =HYPERLINK("https://en.uesp.net/wiki/Skyrim:Specialty_Gear#Blades_Shield","Blades Shield") -> Blades Shield | C28: Heavy Shield | D28: N
A29: =HYPERLINK("https://en.uesp.net/wiki/Skyrim:Specialty_Gear#Blades_Sword","Blades Sword") -> Blades Sword | C29: One-Handed Sword | D29: N
A30: =HYPERLINK("https://en.uesp.net/wiki/Skyrim:Bloodthorn","Bloodthorn") -> Bloodthorn | C30: Dagger | D30: N
A31: =HYPERLINK("https://en.uesp.net/wiki/Skyrim:Bolar%27s_Oathblade","Bolar's Oathblade") -> Bolar's Oathblade | C31: One-handed Sword | D31: N
A32: =HYPERLINK("https://en.uesp.net/wiki/Skyrim:Boots_of_the_Old_Gods","Boots of the Old Gods") -> Boots of the Old Gods | C32: Light Boots | D32: N
A33: =HYPERLINK("https://en.uesp.net/wiki/Skyrim:Borvir%27s_Dagger","Borvir's Dagger") -> Borvir's Dagger | C33: Dagger | D33: N
A34: =HYPERLINK("https://en.uesp.net/wiki/Skyrim:Bow_of_the_Hunt","Bow of the Hunt") -> Bow of the Hunt | C34: Bow | D34: N
A35: =HYPERLINK("https://en.uesp.net/wiki/Skyrim:Charmed_Necklace","Charmed Necklace") -> Charmed Necklace | C35: Necklace | D35: N | E35: Carry a bottle of Honningbrew mead with you to get it during the random encounter.
A36: =HYPERLINK("https://en.uesp.net/wiki/Skyrim:Chillrend","Chillrend") -> Chillrend | C36: One-handed Sword | D36: N
A37: =HYPERLINK("https://en.uesp.net/wiki/Skyrim:Cicero%27s_Boots","Cicero's Boots") -> Cicero's Boots | C37: Clothing | D37: N | E37: Weaker version "Jester's Hat" available at Dawnstar sanctuary.
A38: =HYPERLINK("https://en.uesp.net/wiki/Skyrim:Cicero%27s_Clothes","Cicero's Clothes") -> Cicero's Clothes | C38: Clothing | D38: N | E38: Weaker version "Jester's Clothes" available at Dawnstar sanctuary.
A39: =HYPERLINK("https://en.uesp.net/wiki/Skyrim:Cicero%27s_Gloves","Cicero's Gloves") -> Cicero's Gloves | C39: Clothing | D39: N | E39: Weaker version "Jester's Gloves" available at Dawnstar sanctuary.
A40: =HYPERLINK("https://en.uesp.net/wiki/Skyrim:Cicero%27s_Hat","Cicero's Hat") -> Cicero's Hat | C40: Clothing | D40: N | E40: Weaker version "Jester's Hat" available at Dawnstar sanctuary.
A41: =HYPERLINK("https://en.uesp.net/wiki/Skyrim:Dawnbreaker","Dawnbreaker") -> Dawnbreaker | C41: One-handed Sword | D41: N
A42: =HYPERLINK("https://en.uesp.net/wiki/Skyrim:Diadem_of_the_Savant","Diadem of the Savant") -> Diadem of the Savant | C42: Light Helmet | D42: N
A43: =HYPERLINK("https://en.uesp.net/wiki/Skyrim:Dragon_Priest_Dagger","Dragon Priest Dagger") -> Dragon Priest Dagger | C43: Dagger | D43: N
A44: =HYPERLINK("https://en.uesp.net/wiki/Skyrim:Staves#Dragon_Priest_Staff","Dragon Priest Staff (Rahgot)") -> Dragon Priest Staff (Rahgot) | C44: Staff | D44: N
A45: =HYPERLINK("https://en.uesp.net/wiki/Skyrim:Dragonbane","Dragonbane") -> Dragonbane | C45: One-handed Sword | D45: N
A46: =HYPERLINK("https://en.uesp.net/wiki/Skyrim:Drainblood_Battleaxe","Drainblood Battleaxe") -> Drainblood Battleaxe | C46: Battleaxe | D46: N
A47: =HYPERLINK("https://en.uesp.net/wiki/Skyrim:Drainheart_Sword","Drainheart Sword") -> Drainheart Sword | C47: One-handed Sword | D47: N
A48: =HYPERLINK("https://en.uesp.net/wiki/Skyrim:Drainspell_Bow","Drainspell Bow") -> Drainspell Bow | C48: Bow | D48: N
A49: =HYPERLINK("https://en.uesp.net/wiki/Skyrim:Ebony_Blade","Ebony Blade") -> Ebony Blade | C49: Greatsword | D49: N
A50: =HYPERLINK("https://en.uesp.net/wiki/Skyrim:Ebony_Mail","Ebony Mail") -> Ebony Mail | C50: Heavy Armor | D50: N
A51: =HYPERLINK("https://en.uesp.net/wiki/Skyrim:Eduj","Eduj") -> Eduj | C51: One-handed Sword | D51: N
A52: =HYPERLINK("https://en.uesp.net/wiki/Skyrim:Clothing#00015516","Emperor's Robes") -> Emperor's Robes | C52: Clothing | D52: N | E52: Can get up to 3 during Dark Brotherhood questline.
A53: =HYPERLINK("https://en.uesp.net/wiki/Skyrim:Enchanted_Ring","Enchanted Ring") -> Enchanted Ring | C53: Ring | D53: N | E53: 3 rings during the quest "Under Saarthal". Can optionally be turned in or kept.
A54: =HYPERLINK("https://en.uesp.net/wiki/Skyrim:Execution_Hood","Execution Hood") -> Execution Hood | C54: Clothing | D54: N | E54: x3 during first DB quest
A55: =HYPERLINK("https://en.uesp.net/wiki/Skyrim:Staves#Eye_of_Melka","Eye of Melka") -> Eye of Melka | C55: Staff | D55: N
A56: =HYPERLINK("https://en.uesp.net/wiki/Skyrim:Firiniel%27s_End","Firiniel's End") -> Firiniel's End | C56: Bow | D56: N
A57: =HYPERLINK("https://en.uesp.net/wiki/Skyrim:Quest_Items#Fjola.27s_Wedding_Band","Fjola's Wedding Band") -> Fjola's Wedding Band | C57: Ring | D57: N | E57: Can optionally be turned in or kept during the quest "Mistwatch"
A58: =HYPERLINK("https://en.uesp.net/wiki/Skyrim:Froki%27s_Bow","Froki's Bow") -> Froki's Bow | C58: Bow | D58: N
A59: =HYPERLINK("https://en.uesp.net/wiki/Skyrim:Staves#Gadnor.27s_Staff_of_Charming","Gadnor's Staff of Charming") -> Gadnor's Staff of Charming | C59: Staff | D59: N
A60: =HYPERLINK("https://en.uesp.net/wiki/Skyrim:Gauldur_Blackblade","Gauldur Blackblade") -> Gauldur Blackblade | C60: One-handed Sword | D60: N
A61: =HYPERLINK("https://en.uesp.net/wiki/Skyrim:Gauldur_Blackbow","Gauldur Blackbow") -> Gauldur Blackbow | C61: Bow | D61: N
A62: =HYPERLINK("https://en.uesp.net/wiki/Skyrim:Gauntlets_of_the_Old_Gods","Gauntlets of the Old Gods") -> Gauntlets of the Old Gods | C62: Light Gauntlets | D62: N
A63: =HYPERLINK("https://en.uesp.net/wiki/Skyrim:General_Tullius%27_Armor","General Tullius' Armor") -> General Tullius' Armor | C63: Heavy Armor | D63: N
A64: =HYPERLINK("https://en.uesp.net/wiki/Skyrim:Ghostblade","Ghostblade") -> Ghostblade | C64: One-handed Sword | D64: N
A65: =HYPERLINK("https://en.uesp.net/wiki/Skyrim:Gilded_Wristguards","Gilded Wristguards") -> Gilded Wristguards | C65: Light Gauntlets | D65: N
A66: =HYPERLINK("https://en.uesp.net/wiki/Skyrim:Gloves_of_the_Pugilist","Gloves of the Pugilist") -> Gloves of the Pugilist | C66: Light Gauntlets | D66: N | E66: Disenchantable for a unique enchantment
A67: =HYPERLINK("https://en.uesp.net/wiki/Skyrim:Guild_Master%27s_Armor","Guild Master's Armor") -> Guild Master's Armor | C67: Light Armor | D67: N
A68: =HYPERLINK("https://en.uesp.net/wiki/Skyrim:Guild_Master%27s_Boots","Guild Master's Boots") -> Guild Master's Boots | C68: Light Boots | D68: N
A69: =HYPERLINK("https://en.uesp.net/wiki/Skyrim:Guild_Master%27s_Gloves","Guild Master's Gloves") -> Guild Master's Gloves | C69: Light Gauntlets | D69: N
A70: =HYPERLINK("https://en.uesp.net/wiki/Skyrim:Guild_Master%27s_Hood","Guild Master's Hood") -> Guild Master's Hood | C70: Light Helmet | D70: N
A71: =HYPERLINK("https://en.uesp.net/wiki/Skyrim:Halldir's_Staff", "Halldir's Staff") -> Halldir's Staff | C71: Staff | D71: N
A72: =HYPERLINK("https://en.uesp.net/wiki/Skyrim:Specialty_Gear#Headsman.27s_Axe","Headsman's Axe") -> Headsman's Axe | C72: Two-handed Battleaxe | D72: N | E72: Can be stolen or traded from Ahtar.
A73: =HYPERLINK("https://en.uesp.net/wiki/Skyrim:Quest_Items#Helm_of_Winterhold","Helm of Winterhold") -> Helm of Winterhold | C73: Heavy Helmet | D73: N | E73: Quest item, but it can be pickpocketed back after completion.
A74: =HYPERLINK("https://en.uesp.net/wiki/Skyrim:Helm_of_Yngol","Helm of Yngol") -> Helm of Yngol | C74: Heavy Helmet | D74: N
A75: =HYPERLINK("https://en.uesp.net/wiki/Skyrim:Helmet_of_the_Old_Gods","Helmet of the Old Gods") -> Helmet of the Old Gods | C75: Light Helmet | D75: N
A76: =HYPERLINK("https://en.uesp.net/wiki/Skyrim:Hevnoraak_(item)","Hevnoraak") -> Hevnoraak | C76: Heavy Helmet | D76: N
A77: =HYPERLINK("https://en.uesp.net/wiki/Skyrim:Hevnoraak's_Staff", "Hevnoraak's Staff") -> Hevnoraak's Staff | C77: Staff | D77: N
A78: =HYPERLINK("https://en.uesp.net/wiki/Skyrim:Quest_Items#Hrolfdir.27s_Shield","Hrolfdir's Shield") -> Hrolfdir's Shield | C78: Heavy Shield | D78: N | E78: Quest item, but it can be pickpocketed back after completion.
A79: =HYPERLINK("https://en.uesp.net/wiki/Skyrim:Ilas-Tei%27s_Ring","Ilas-Tei's Ring") -> Ilas-Tei's Ring | C79: Ring | D79: N
A80: =HYPERLINK("https://en.uesp.net/wiki/Skyrim:Ironhand_Gauntlets","Ironhand Gauntlets") -> Ironhand Gauntlets | C80: Heavy Gauntlets | D80: N
A81: =HYPERLINK("https://en.uesp.net/wiki/Skyrim:Quest_Items#Kahvozein.27s_Fang","Kahvozein's Fang") -> Kahvozein's Fang | C81: Dagger | D81: N
A82: =HYPERLINK("https://en.uesp.net/wiki/Skyrim:Keening","Keening") -> Keening | C82: Dagger | D82: N
A83: =HYPERLINK("https://en.uesp.net/wiki/Skyrim:Konahrik","Konahrik") -> Konahrik | C83: Heavy Helmet | D83: N
A84: =HYPERLINK("https://en.uesp.net/wiki/Skyrim:Krosis_(item)","Krosis") -> Krosis | C84: Light Helmet | D84: N
A85: =HYPERLINK("https://en.uesp.net/wiki/Skyrim:Kyne%27s_Token","Kyne's Token") -> Kyne's Token | C85: Necklace | D85: N
A86: =HYPERLINK("https://en.uesp.net/wiki/Skyrim:Linwe%27s_Armor","Linwe's Armor") -> Linwe's Armor | C86: Light Armor | D86: N
A87: =HYPERLINK("https://en.uesp.net/wiki/Skyrim:Linwe%27s_Boots","Linwe's Boots") -> Linwe's Boots | C87: Light Boots | D87: N
A88: =HYPERLINK("https://en.uesp.net/wiki/Skyrim:Linwe%27s_Gloves","Linwe's Gloves") -> Linwe's Gloves | C88: Light Gauntlets | D88: N
A89: =HYPERLINK("https://en.uesp.net/wiki/Skyrim:Linwe%27s_Hood","Linwe's Hood") -> Linwe's Hood | C89: Light Helmet | D89: N
A90: =HYPERLINK("https://en.uesp.net/wiki/Skyrim:Mace_of_Molag_Bal","Mace of Molag Bal") -> Mace of Molag Bal | C90: One-handed Mace | D90: N
A91: =HYPERLINK("https://en.uesp.net/wiki/Skyrim:Mage's_Circlet", "Mage's Circlet") -> Mage's Circlet | C91: Circlet | D91: N
A92: =HYPERLINK("https://en.uesp.net/wiki/Skyrim:Masque_of_Clavicus_Vile","Masque of Clavicus Vile") -> Masque of Clavicus Vile | C92: Heavy Helmet | D92: N
A93: =HYPERLINK("https://en.uesp.net/wiki/Skyrim:Mehrunes%27_Razor","Mehrunes' Razor") -> Mehrunes' Razor | C93: Dagger | D93: N
A94: =HYPERLINK("https://en.uesp.net/wiki/Skyrim:Morokei_(item)","Morokei") -> Morokei | C94: Light Helmet | D94: N
A95: =HYPERLINK("https://en.uesp.net/wiki/Skyrim:Movarth%27s_Boots","Movarth's Boots") -> Movarth's Boots | C95: Light Boots | D95: N
A96: =HYPERLINK("https://en.uesp.net/wiki/Skyrim:Muiri%27s_Ring","Muiri's Ring") -> Muiri's Ring | C96: Ring | D96: N
A97: =HYPERLINK("https://en.uesp.net/wiki/Skyrim:Clothing#000b1460","Mythic Dawn Boots") -> Mythic Dawn Boots | C97: Clothing | D97: N
A98: =HYPERLINK("https://en.uesp.net/wiki/Skyrim:Clothing#000b145b","Mythic Dawn Gloves") -> Mythic Dawn Gloves | C98: Clothing | D98: N
A99: =HYPERLINK("https://en.uesp.net/wiki/Skyrim:Mythic_Dawn_Robes","Mythic Dawn Robes") -> Mythic Dawn Robes | C99: Clothing | D99: N
A100: =HYPERLINK("https://en.uesp.net/wiki/Skyrim:Nahkriin_(item)","Nahkriin") -> Nahkriin | C100: Heavy Helmet | D100: N
A101: =HYPERLINK("https://en.uesp.net/wiki/Skyrim:Necromancer_Amulet","Necromancer Amulet") -> Necromancer Amulet | C101: Necklace | D101: N | E101: The mysterious amulet must be sold to Calicimo during Blood on the Ice
...

Sheet Books
A1: Book Title | B1: Collected? | C1: Read? | D1: On Shelf? | E1: Total Books | F1: Collected | G1: Collected % | H1: Remaining | I1: Remaining % | J1: Read | K1: Read % | L1: Hold | M1: Hold% | N1: List | O1: Author | P1: Description | Q1: Value | R1: Type
A2: Regular books, journals and spell tomes
A3: =concatenate("Total: ", E3, ", Remaining: ", H3, " (", I3, "%)") -> Total: 596, Remaining: 596 (100%) | B3: =concatenate(F3, " (", G3, "%)") -> 0 (0%) | C3: =concatenate(J3, " (", K3, "%)") -> 0 (0%) | D3: =concatenate(L3, " (", M3, "%)") -> 0 (0%) | E3: =rows(A4:A599) -> 596 | F3: =Countif(B4:B599, "Y") -> 0 | G3: =round(100 * (F3 / E3), 0) -> 0 | H3: =E3 - F3 -> 596 | I3: =round(100 * (H3 / E3), 0) -> 100 | J3: =Countif(C4:C599, "Y") -> 0 | K3: =round(100 * (J3 / E3), 0) -> 0 | L3: =countif(D4:D599, "Y") -> 0 | M3: =round(100 * (L3 / E3), 0) -> 0 | N3: - | O3: - | P3: -
A4: =HYPERLINK("http://en.uesp.net/wiki/Skyrim:16_Accords_of_Madness,_v._IX","16 Accords of Madness, v. IX") -> 16 Accords of Madness, v. IX | B4: N | C4: N | D4: N | N4: 4 | O4: Anonymous/Unknown | P4: Vaermina's Tale | Q4: 25 | R4: Book
A5: =HYPERLINK("http://en.uesp.net/wiki/Skyrim:16_Accords_of_Madness,_v._VI","16 Accords of Madness, v. VI") -> 16 Accords of Madness, v. VI | B5: N | C5: N | D5: N | N5: 4 | O5: Anonymous/Unknown | P5: Hircine's Tale | Q5: 25 | R5: Book
A6: =HYPERLINK("http://en.uesp.net/wiki/Skyrim:16_Accords_of_Madness,_v._XII","16 Accords of Madness, v. XII") -> 16 Accords of Madness, v. XII | B6: N | C6: N | D6: N | N6: 4 | O6: Anonymous/Unknown | P6: Malacath's Tale | Q6: 25 | R6: Book
A7: =HYPERLINK("http://en.uesp.net/wiki/Skyrim:2920,_Evening_Star,_v12","2920, Evening Star, v12") -> 2920, Evening Star, v12 | B7: N | C7: N | D7: N | N7: 3 | O7: Carlovac Townway | P7: Volume 12 of a historical series about Vivec and the Empire | Q7: 11 | R7: Book
A8: =HYPERLINK("http://en.uesp.net/wiki/Skyrim:2920,_First_Seed,_v3","2920, First Seed, v3") -> 2920, First Seed, v3 | B8: N | C8: N | D8: N | N8: 3 | O8: Carlovac Townway | P8: Volume 3 of a historical series about Vivec and the Empire | Q8: 11 | R8: Book
A9: =HYPERLINK("http://en.uesp.net/wiki/Skyrim:2920,_Frostfall,_v10","2920, Frostfall, v10") -> 2920, Frostfall, v10 | B9: N | C9: N | D9: N | N9: - | O9: Carlovac Townway | P9: Volume 10 of a historical series about Vivec and the Empire | Q9: 50 | R9: Skill Book - Conjuration
A10: =HYPERLINK("http://en.uesp.net/wiki/Skyrim:2920,_Hearth_Fire,_v9","2920, Hearth Fire, v9") -> 2920, Hearth Fire, v9 | B10: N | C10: N | D10: N | N10: - | O10: Carlovac Townway | P10: Volume 9 of a historical series about Vivec and the Empire | Q10: 50 | R10: Skill Book - Conjuration
A11: =HYPERLINK("http://en.uesp.net/wiki/Skyrim:2920,_Last_Seed,_v8","2920, Last Seed, v8") -> 2920, Last Seed, v8 | B11: N | C11: N | D11: N | N11: - | O11: Carlovac Townway | P11: Volume 8 of a historical series about Vivec and the Empire | Q11: 75 | R11: Skill Book - Sneak
A12: =HYPERLINK("http://en.uesp.net/wiki/Skyrim:2920,_MidYear,_v6","2920, MidYear, v6") -> 2920, MidYear, v6 | B12: N | C12: N | D12: N | N12: - | O12: Carlovac Townway | P12: Volume 6 of a historical series about Vivec and the Empire | Q12: 70 | R12: Skill Book - Heavy Armor
A13: =HYPERLINK("http://en.uesp.net/wiki/Skyrim:2920,_Morning_Star,_v1","2920, Morning Star, v1") -> 2920, Morning Star, v1 | B13: N | C13: N | D13: N | N13: - | O13: Carlovac Townway | P13: Volume 1 of a historical series about Vivec and the Empire | Q13: 50 | R13: Skill Book - One-handed
A14: =HYPERLINK("http://en.uesp.net/wiki/Skyrim:2920,_Rain%27s_Hand,_v4","2920, Rain's Hand, v4") -> 2920, Rain's Hand, v4 | B14: N | C14: N | D14: N | N14: - | O14: Carlovac Townway | P14: Volume 4 of a historical series about Vivec and the Empire | Q14: 55 | R14: Skill Book - Restoration
A15: =HYPERLINK("http://en.uesp.net/wiki/Skyrim:2920,_Second_Seed,_v5","2920, Second Seed, v5") -> 2920, Second Seed, v5 | B15: N | C15: N | D15: N | N15: - | O15: Carlovac Townway | P15: Volume 5 of a historical series about Vivec and the Empire | Q15: 60 | R15: Skill Book - Speech
A16: =HYPERLINK("http://en.uesp.net/wiki/Skyrim:2920,_Sun%27s_Dawn,_v2","2920, Sun's Dawn, v2") -> 2920, Sun's Dawn, v2 | B16: N | C16: N | D16: N | N16: - | O16: Carlovac Townway | P16: Volume 2 of a historical series about Vivec and the Empire | Q16: 60 | R16: Skill Book - Illusion
A17: =HYPERLINK("http://en.uesp.net/wiki/Skyrim:2920,_Sun%27s_Dusk,_v11","2920, Sun's Dusk, v11") -> 2920, Sun's Dusk, v11 | B17: N | C17: N | D17: N | N17: 3 | O17: Carlovac Townway | P17: Volume 11 of a historical series about Vivec and the Empire | Q17: 11 | R17: Book
A18: =HYPERLINK("http://en.uesp.net/wiki/Skyrim:2920,_Sun%27s_Height,_v7","2920, Sun's Height, v7") -> 2920, Sun's Height, v7 | B18: N | C18: N | D18: N | N18: 0 | O18: Carlovac Townway | P18: Volume 7 of a historical series about Vivec and the Empire | Q18: 3 | R18: Book
A19: =HYPERLINK("http://en.uesp.net/wiki/Skyrim:A_Children%27s_Anuad","A Children's Anuad") -> A Children's Anuad | B19: N | C19: N | D19: N | N19: 2 | O19: Anonymous/Unknown | P19: Early religious book providing a simplified version of The Anuad creation myth from the Mythic Era | Q19: 6 | R19: Book
A20: =HYPERLINK("http://en.uesp.net/wiki/Skyrim:A_Dance_in_Fire,_v1","A Dance in Fire, v1") -> A Dance in Fire, v1 | B20: N | C20: N | D20: N | N20: 0 | O20: Waughin Jarth | P20: Chapter 1 of a clerk's adventures in Valenwood | Q20: 3 | R20: Book
A21: =HYPERLINK("http://en.uesp.net/wiki/Skyrim:A_Dance_in_Fire,_v2","A Dance in Fire, v2") -> A Dance in Fire, v2 | B21: N | C21: N | D21: N | N21: - | O21: Waughin Jarth | P21: Chapter 2 of a clerk's adventures in Valenwood | Q21: 50 | R21: Skill Book - Block
A22: =HYPERLINK("http://en.uesp.net/wiki/Skyrim:A_Dance_in_Fire,_v3","A Dance in Fire, v3") -> A Dance in Fire, v3 | B22: N | C22: N | D22: N | N22: 0 | O22: Waughin Jarth | P22: Chapter 3 of a clerk's adventures in Valenwood | Q22: 3 | R22: Book
A23: =HYPERLINK("http://en.uesp.net/wiki/Skyrim:A_Dance_in_Fire,_v4","A Dance in Fire, v4") -> A Dance in Fire, v4 | B23: N | C23: N | D23: N | N23: 0 | O23: Waughin Jarth | P23: Chapter 4 of a clerk's adventures in Valenwood | Q23: 4 | R23: Book
A24: =HYPERLINK("http://en.uesp.net/wiki/Skyrim:A_Dance_in_Fire,_v5","A Dance in Fire, v5") -> A Dance in Fire, v5 | B24: N | C24: N | D24: N | N24: 4 | O24: Waughin Jarth | P24: Chapter 5 of a clerk's adventures in Valenwood | Q24: 30 | R24: Book
A25: =HYPERLINK("http://en.uesp.net/wiki/Skyrim:A_Dance_in_Fire,_v6","A Dance in Fire, v6") -> A Dance in Fire, v6 | B25: N | C25: N | D25: N | N25: - | O25: Waughin Jarth | P25: Chapter 6 of a clerk's adventures in Valenwood | Q25: 60 | R25: Skill Book - Speech
A26: =HYPERLINK("http://en.uesp.net/wiki/Skyrim:A_Dance_in_Fire,_v7","A Dance in Fire, v7") -> A Dance in Fire, v7 | B26: N | C26: N | D26: N | N26: - | O26: Waughin Jarth | P26: Chapter 7 of a clerk's adventures in Valenwood | Q26: 60 | R26: Skill Book - Speech
A27: =HYPERLINK("http://en.uesp.net/wiki/Skyrim:A_Dream_of_Sovngarde","A Dream of Sovngarde") -> A Dream of Sovngarde | B27: N | C27: N | D27: N | N27: 2 | O27: Skardan Free-Winter | P27: A soldier's tale of his dream before battle | Q27: 8 | R27: Book
A28: =HYPERLINK("http://en.uesp.net/wiki/Skyrim:A_Game_at_Dinner","A Game at Dinner") -> A Game at Dinner | B28: N | C28: N | D28: N | N28: - | O28: An Anonymous Spy | P28: A spy's observations upon poison making and a dinner party | Q28: 55 | R28: Skill Book - Alchemy
A29: =HYPERLINK("http://en.uesp.net/wiki/Skyrim:A_Gentleman%27s_Guide_to_Whiterun","A Gentleman's Guide to Whiterun") -> A Gentleman's Guide to Whiterun | B29: N | C29: N | D29: N | N29: 1 | O29: Mikael the Bard | P29: A guide to the Nordic city of Whiterun in the Fourth Era. | Q29: 3 | R29: Book
A30: =HYPERLINK("http://en.uesp.net/wiki/Skyrim:A_Hypothetical_Treachery","A Hypothetical Treachery") -> A Hypothetical Treachery | B30: N | C30: N | D30: N | N30: - | O30: Aicantar | P30: A short play about betrayal. | Q30: 55 | R30: Skill Book - Destruction
A31: =HYPERLINK("http://en.uesp.net/wiki/Skyrim:A_Kiss,_Sweet_Mother","A Kiss, Sweet Mother") -> A Kiss, Sweet Mother | B31: N | C31: N | D31: N | N31: 2 | O31: Anonymous/Unknown | P31: Guide to performing the Black Sacrament in order to summon the Dark Brotherhood. | Q31: 6 | R31: Book - Faction
A32: =HYPERLINK("http://en.uesp.net/wiki/Skyrim:A_Minor_Maze","A Minor Maze") -> A Minor Maze | B32: N | C32: N | D32: N | N32: 2 | O32: Anonymous/Unknown | P32: The history of Labyrinthian and its creator, Shalidor. | Q32: 8 | R32: Book
A33: =HYPERLINK("http://en.uesp.net/wiki/Skyrim:A_Tragedy_in_Black","A Tragedy in Black") -> A Tragedy in Black | B33: N | C33: N | D33: N | N33: - | O33: Anonymous/Unknown | P33: A folk tale about a young boy's encounter with a Dremora. | Q33: 50 | R33: Skill Book - Enchanting
A34: =HYPERLINK("http://en.uesp.net/wiki/Skyrim:Admonition_Against_Ebony","Admonition Against Ebony") -> Admonition Against Ebony | B34: N | C34: N | D34: N | N34: - | O34: Anonymous/Unknown | P34: A warning to any who might claim the Ebony Blade. | Q34: 5 | R34: Book
A35: =HYPERLINK("http://en.uesp.net/wiki/Skyrim:Advances_in_Lockpicking","Advances in Lockpicking") -> Advances in Lockpicking | B35: N | C35: N | D35: N | N35: - | O35: An Anonymous Thief | P35: A brief guidebook on lockpicking. | Q35: 75 | R35: Skill Book - Lockpicking
A36: =HYPERLINK("http://en.uesp.net/wiki/Skyrim:Adventurer%27s_Journal","Adventurer's Journal") -> Adventurer's Journal | B36: N | C36: N | D36: N | N36: - | O36: An Anonymous Adventurer | P36: About investigating attacks on caravans by the Falmer. | Q36: 5 | R36: Journal
A37: =HYPERLINK("http://en.uesp.net/wiki/Skyrim:Aedra_and_Daedra","Aedra and Daedra") -> Aedra and Daedra | B37: N | C37: N | D37: N | N37: 2 | O37: Anonymous/Unknown | P37: Overview of the basic differences between Gods, Demons, Aedra, and Daedra | Q37: 5 | R37: Book
A38: =HYPERLINK("http://en.uesp.net/wiki/Skyrim:Aevar_Stone-Singer","Aevar Stone-Singer") -> Aevar Stone-Singer | B38: N | C38: N | D38: N | N38: - | O38: Anonymous/Unknown | P38: Traditional Skaal myth about a young Skaal's journey to recover the Gifts of the All-Maker | Q38: 60 | R38: Skill Book - Pickpocket
A39: =HYPERLINK("http://en.uesp.net/wiki/Skyrim:Agrius%27s_Journal","Agrius's Journal") -> Agrius's Journal | B39: N | C39: N | D39: N | N39: - | O39: Agrius | P39: The last accounts of a bandit before being possessed and sacrificed by Halldir. | Q39: 5 | R39: Journal
A40: =HYPERLINK("https://en.uesp.net/wiki/Lore:Ahzidal%27s_Descent","Ahzidal's Descent") -> Ahzidal's Descent | B40: N | C40: N | D40: N | N40: 4 | O40: Halund Greycloak | P40: The tale of a powerful enchanter's descent into madness | Q40: 16 | R40: Book
A41: =HYPERLINK("http://en.uesp.net/wiki/Skyrim:Ahzirr_Traajijazeri","Ahzirr Traajijazeri") -> Ahzirr Traajijazeri | B41: N | C41: N | D41: N | N41: 0 | O41: Anonymous/Unknown | P41: The public manifesto of the Khajiit organization Renrijra Krin | Q41: 4 | R41: Book
A42: =HYPERLINK("http://en.uesp.net/wiki/Skyrim:Aicantar%27s_Lab_Journal","Aicantar's Lab Journal") -> Aicantar's Lab Journal | B42: N | C42: N | D42: N | N42: - | O42: Aicantar | P42: Research notes on Dwarven spider control | Q42: 5 | R42: Journal
A43: =HYPERLINK("http://en.uesp.net/wiki/Skyrim:Alchemist%27s_Journal_(camp)","Alchemist's Journal") -> Alchemist's Journal | B43: N | C43: N | D43: N | N43: - | O43: An Anonymous Alchemist | P43: A researcher investigating plant growth | Q43: 5 | R43: Journal
A44: =HYPERLINK("http://en.uesp.net/wiki/Skyrim:Alchemist%27s_Journal_(shack)","Alchemist's Journal") -> Alchemist's Journal | B44: N | C44: N | D44: N | N44: - | O44: An Anonymous Alchemist | P44: The idyllic journal of an alchemist | Q44: 5 | R44: Journal
A45: =HYPERLINK("http://en.uesp.net/wiki/Skyrim:Alduin_is_Real","Alduin is Real") -> Alduin is Real | B45: N | C45: N | D45: N | N45: 2 | O45: Thromgar Iron-Head | P45: A poorly spelled essay from a "prowd Nord" on the difference between Alduin and Akatosh | Q45: 8 | R45: Book
A46: =HYPERLINK("http://en.uesp.net/wiki/Skyrim:Alva%27s_Journal","Alva's Journal") -> Alva's Journal | B46: N | C46: N | D46: N | N46: - | O46: Alva | P46: A vampire's plot to take over all of Morthal | Q46: 5 | R46: Journal
A47: =HYPERLINK("http://en.uesp.net/wiki/Skyrim:Amongst_the_Draugr","Amongst the Draugr") -> Amongst the Draugr | B47: N | C47: N | D47: N | N47: 3 | O47: Bernadette Bantien, College of Winterhold | P47: Discoveries about the draugr and their link to the dragon cults | Q47: 14 | R47: Book
A48: =HYPERLINK("http://en.uesp.net/wiki/Skyrim:An_Accounting_of_the_Scrolls","An Accounting of the Scrolls") -> An Accounting of the Scrolls | B48: N | C48: N | D48: N | N48: 4 | O48: Quintus Nerevelus, Former Imperial Librarian | P48: An author's report on the Elder Scrolls and his subsequent entry into the Cult of the Ancestor Moth | Q48: 20 | R48: Book
A49: =HYPERLINK("http://en.uesp.net/wiki/Skyrim:An_Explorer%27s_Guide_to_Skyrim","An Explorer's Guide to Skyrim") -> An Explorer's Guide to Skyrim | B49: N | C49: N | D49: N | N49: 2 | O49: Marcius Carvain, Viscount Bruma | P49: A brief travel guide for adventuresome tourists in Skyrim | Q49: 8 | R49: Book
A50: =HYPERLINK("http://en.uesp.net/wiki/Skyrim:Ancestors_and_the_Dunmer","Ancestors and the Dunmer") -> Ancestors and the Dunmer | B50: N | C50: N | D50: N | N50: 2 | O50: Anonymous/Unknown | P50: An outdated guide for foreign visitors to Morrowind | Q50: 8 | R50: Book
A51: =HYPERLINK("http://en.uesp.net/wiki/Skyrim:Annals_of_the_Dragonguard","Annals of the Dragonguard") -> Annals of the Dragonguard | B51: N | C51: N | D51: N | N51: - | O51: Brother Annulus | P51: Chronicles of the Dragonguard in the late First Era | Q51: 200 | R51: Book
A52: =HYPERLINK("http://en.uesp.net/wiki/Skyrim:Antecedants_of_Dwemer_Law","Antecedants of Dwemer Law") -> Antecedants of Dwemer Law | B52: N | C52: N | D52: N | N52: 2 | O52: Anonymous/Unknown | P52: A historical account of the development of Dwemer law and custom from its roots in High Elven culture | Q52: 5 | R52: Book
A53: =HYPERLINK("http://en.uesp.net/wiki/Skyrim:Arcana_Restored","Arcana Restored") -> Arcana Restored | B53: N | C53: N | D53: N | N53: 4 | O53: Wapna Neustra Praeceptor Emeritus | P53: Cryptic instructions for the restoration of Arcana | Q53: 25 | R53: Book
A54: =HYPERLINK("http://en.uesp.net/wiki/Skyrim:Argonian_Account,_Book_1","Argonian Account, Book 1") -> Argonian Account, Book 1 | B54: N | C54: N | D54: N | N54: 0 | O54: Waughin Jarth | P54: Decumus Scotti's continued adventures in Black Marsh, Volume 1 | Q54: 2 | R54: Book
A55: =HYPERLINK("http://en.uesp.net/wiki/Skyrim:Argonian_Account,_Book_2","Argonian Account, Book 2") -> Argonian Account, Book 2 | B55: N | C55: N | D55: N | N55: 3 | O55: Waughin Jarth | P55: Decumus Scotti's continued adventures in Black Marsh, Volume 2 | Q55: 12 | R55: Book
A56: =HYPERLINK("http://en.uesp.net/wiki/Skyrim:Argonian_Account,_Book_3","Argonian Account, Book 3") -> Argonian Account, Book 3 | B56: N | C56: N | D56: N | N56: 0 | O56: Waughin Jarth | P56: Decumus Scotti's continued adventures in Black Marsh, Volume 3 | Q56: 12 | R56: Book
A57: =HYPERLINK("http://en.uesp.net/wiki/Skyrim:Argonian_Account,_Book_4","Argonian Account, Book 4") -> Argonian Account, Book 4 | B57: N | C57: N | D57: N | N57: 3 | O57: Waughin Jarth | P57: Decumus Scotti's continued adventures in Black Marsh, Volume 4 | Q57: 12 | R57: Book
A58: =HYPERLINK("http://en.uesp.net/wiki/Skyrim:Arvel%27s_Journal","Arvel's Journal") -> Arvel's Journal | B58: N | C58: N | D58: N | N58: - | O58: Arvel the Swift | P58: A journal describing how Arvel came into possession of the Golden Claw and a hint of its true purpose | Q58: 5 | R58: Journal
A59: =HYPERLINK("http://en.uesp.net/wiki/Skyrim:Atlas_of_Dragons","Atlas of Dragons") -> Atlas of Dragons | B59: N | C59: N | D59: N | N59: - | O59: Brother Mathnan | P59: A glossary of Skyrim's dragons | Q59: 50 | R59: Book
A60: =HYPERLINK("http://en.uesp.net/wiki/Skyrim:Atronach_Forge_Manual","Atronach Forge Manual") -> Atronach Forge Manual | B60: N | C60: N | D60: N | N60: - | O60: Anonymous/Unknown | P60: A guide on how to use the Atronach Forge | Q60: 5 | R60: Book
A61: =HYPERLINK("http://en.uesp.net/wiki/Skyrim:Azura_and_the_Box","Azura and the Box") -> Azura and the Box | B61: N | C61: N | D61: N | N61: 3 | O61: Marobar Sul | P61: Book 11 of a series of fictional stories about the Dwemer | Q61: 10 | R61: Book
A62: =HYPERLINK("http://en.uesp.net/wiki/Skyrim:Bandit_Leader%27s_Journal","Bandit Leader's Journal") -> Bandit Leader's Journal | B62: N | C62: N | D62: N | N62: - | O62: An Anonymous Bandit | P62: Journal entries indicating the location of a hidden stash | Q62: 5 | R62: Journal
A63: =HYPERLINK("http://en.uesp.net/wiki/Skyrim:Bandit%27s_Journal_(Fort_Neugrad)","Bandit's Journal") -> Bandit's Journal | B63: N | C63: N | D63: N | N63: - | O63: An Anonymous Bandit | P63: A Bandit's account of taking over Fort Neugrad | Q63: 5 | R63: Journal
A64: =HYPERLINK("http://en.uesp.net/wiki/Skyrim:Bandit%27s_Journal_(Orotheim)","Bandit's Journal") -> Bandit's Journal | B64: N | C64: N | D64: N | N64: - | O64: An Anonymous Bandit | P64: A bandit's complaints about their inability to kill a mammoth | Q64: 5 | R64: Journal
A65: =HYPERLINK("http://en.uesp.net/wiki/Skyrim:Battle_of_Red_Mountain","Battle of Red Mountain") -> Battle of Red Mountain | B65: N | C65: N | D65: N | N65: - | O65: Vivec | P65: The story of the Battle of Red Mountain and the Nerevarine Prophecies from Vivec's perspective | Q65: 50 | R65: Skill Book - Block
A66: =HYPERLINK("http://en.uesp.net/wiki/Skyrim:Battle_of_Sancre_Tor","Battle of Sancre Tor") -> Battle of Sancre Tor | B66: N | C66: N | D66: N | N66: - | O66: Anonymous/Unknown | P66: The story of how General Talos defeated the stronghold of Sancre Tor | Q66: 50 | R66: Skill Book - Two-handed
A67: =HYPERLINK("http://en.uesp.net/wiki/Skyrim:Before_the_Ages_of_Man","Before the Ages of Man") -> Before the Ages of Man | B67: N | C67: N | D67: N | N67: - | O67: Aicantar of Shimerene | P67: Chronicles the major events of the Dawn and Merethic Eras | Q67: 60 | R67: Skill Book - Illusion
A68: =HYPERLINK("http://en.uesp.net/wiki/Skyrim:Beggar_(book)","Beggar") -> Beggar | B68: N | C68: N | D68: N | N68: - | O68: Reven | P68: The first chapter in the adventures of Eslaf Erol | Q68: 60 | R68: Skill Book - Pickpocket
A69: =HYPERLINK("http://en.uesp.net/wiki/Skyrim:Beggar_Prince","Beggar Prince") -> Beggar Prince | B69: N | C69: N | D69: N | N69: 2 | O69: Anonymous/Unknown | P69: The story of Wheedle and his gifts from the Daedric Lord Namira | Q69: 5 | R69: Book
A70: =HYPERLINK("http://en.uesp.net/wiki/Skyrim:Biography_of_Barenziah,_v1","Biography of Barenziah, v1") -> Biography of Barenziah, v1 | B70: N | C70: N | D70: N | N70: 1 | O70: Stern Gamboge, Imperial Scribe | P70: Volume one in the official biography of Queen Barenziah. | Q70: 3 | R70: Book
A71: =HYPERLINK("http://en.uesp.net/wiki/Skyrim:Biography_of_Barenziah,_v2","Biography of Barenziah, v2") -> Biography of Barenziah, v2 | B71: N | C71: N | D71: N | N71: 1 | O71: Stern Gamboge, Imperial Scribe | P71: Volume two in the official biography of Queen Barenziah. | Q71: 3 | R71: Book
A72: =HYPERLINK("http://en.uesp.net/wiki/Skyrim:Biography_of_Barenziah,_v3","Biography of Barenziah, v3") -> Biography of Barenziah, v3 | B72: N | C72: N | D72: N | N72: 1 | O72: Stern Gamboge, Imperial Scribe | P72: Volume three in the official biography of Queen Barenziah. | Q72: 3 | R72: Book
A73: =HYPERLINK("http://en.uesp.net/wiki/Skyrim:Biography_of_the_Wolf_Queen","Biography of the Wolf Queen") -> Biography of the Wolf Queen | B73: N | C73: N | D73: N | N73: - | O73: Katar Eriphanes | P73: The history of Potema, The Wolf Queen of Solitude. | Q73: 60 | R73: Skill Book - Speech
A74: =HYPERLINK("http://en.uesp.net/wiki/Skyrim:Boethiah%27s_Glory","Boethiah's Glory") -> Boethiah's Glory | B74: N | C74: N | D74: N | N74: 4 | O74: Anonymous/Unknown | P74: A short prayer to Boethiah. | Q74: 25 | R74: Book
A75: =HYPERLINK("http://en.uesp.net/wiki/Skyrim:Boethiah%27s_Proving","Boethiah's Proving") -> Boethiah's Proving | B75: N | C75: N | D75: N | N75: 44231 | O75: Anonymous/Unknown | P75: A cultist's account of summoning Boethiah. | Q75: 25 | R75: Book
A76: =HYPERLINK("http://en.uesp.net/wiki/Skyrim:Bone,_Part_I","Bone, Part I (DB)") -> Bone, Part I (DB) | B76: N | C76: N | D76: N | N76: 2 | O76: Tavi Dromio | P76: Part one in a tale surrounding the creation of Bonemold armor. | Q76: 6 | R76: Book
A77: =HYPERLINK("http://en.uesp.net/wiki/Skyrim:Bone,_Part_II","Bone, Part II (DB)") -> Bone, Part II (DB) | B77: N | C77: N | D77: N | N77: 2 | O77: Tavi Dromio | P77: Part two in a tale surrounding the creation of Bonemold armor. | Q77: 6 | R77: Book
A78: =HYPERLINK("http://en.uesp.net/wiki/Skyrim:Breathing_Water","Breathing Water") -> Breathing Water | B78: N | C78: N | D78: N | N78: - | O78: Haliel Myrm | P78: A fictional tale where Tharien Winloth seeks to master water breathing. | Q78: 60 | R78: Skill Book - Alteration
A79: =HYPERLINK("http://en.uesp.net/wiki/Skyrim:Brief_History_of_the_Empire,_v1","Brief History of the Empire, v1") -> Brief History of the Empire, v1 | B79: N | C79: N | D79: N | N79: 1 | O79: Stronach k'Thojj III | P79: The succession of the first eight Emperors of the Septim Dynasty, from Tiber Septim to Kintyra II. | Q79: 2 | R79: Book
A80: =HYPERLINK("http://en.uesp.net/wiki/Skyrim:Brief_History_of_the_Empire,_v2","Brief History of the Empire, v2") -> Brief History of the Empire, v2 | B80: N | C80: N | D80: N | N80: 1 | O80: Stronach k'Thojj III | P80: The second volume described the War of the Red Diamond and the six Emperors who followed. | Q80: 2 | R80: Book
A81: =HYPERLINK("http://en.uesp.net/wiki/Skyrim:Brief_History_of_the_Empire,_v3","Brief History of the Empire, v3") -> Brief History of the Empire, v3 | B81: N | C81: N | D81: N | N81: 1 | O81: Stronach k'Thojj III | P81: The third volume described the troubles of the next three Emperors - the frustrated Uriel IV, the ineffectual Cephorus II, and the heroic Uriel V. | Q81: 2 | R81: Book
A82: =HYPERLINK("http://en.uesp.net/wiki/Skyrim:Brief_History_of_the_Empire,_v4","Brief History of the Empire, v4") -> Brief History of the Empire, v4 | B82: N | C82: N | D82: N | N82: 1 | O82: Stronach k'Thojj III | P82: The final volume describes the rest of the Empire's history leading up to Jagar Tharn. | Q82: 2 | R82: Book
A83: =HYPERLINK("http://en.uesp.net/wiki/Skyrim:Brothers_of_Darkness","Brothers of Darkness") -> Brothers of Darkness | B83: N | C83: N | D83: N | N83: 4 | O83: Pellarne Assi | P83: A brief history of the Dark Brotherhood | Q83: 30 | R83: Book
A84: =HYPERLINK("http://en.uesp.net/wiki/Skyrim:Butcher_Journal","Butcher Journal") -> Butcher Journal | B84: N | C84: N | D84: N | N84: - | O84: The Butcher/Calixto Corrium | P84: A journal revealing the ghoulish motivation behind killings in Windhelm | Q84: 5 | R84: Journal
A85: =HYPERLINK("http://en.uesp.net/wiki/Skyrim:Butcher_Journal_1","Butcher Journal #1") -> Butcher Journal #1 | B85: N | C85: N | D85: N | N85: - | O85: The Butcher/Calixto Corrium | P85: A serial killer's journal entries on stalking a victim | Q85: 5 | R85: Journal
A86: =HYPERLINK("http://en.uesp.net/wiki/Skyrim:Butcher_Journal_2","Butcher Journal #2") -> Butcher Journal #2 | B86: N | C86: N | D86: N | N86: - | O86: The Butcher/Calixto Corrium | P86: A serial killer's translation on "flesh" magic | Q86: 5 | R86: Journal
A87: =HYPERLINK("http://en.uesp.net/wiki/Skyrim:Catalogue_of_Armor_Enchantments","Catalogue of Armor Enchantments") -> Catalogue of Armor Enchantments | B87: N | C87: N | D87: N | N87: - | O87: Yvonne Bienne, Synod researcher | P87: A guide to various enchantments that can be bound to apparel. | Q87: 50 | R87: Skill Book - Enchanting
A88: =HYPERLINK("http://en.uesp.net/wiki/Skyrim:Catalogue_of_Weapon_Enchantments","Catalogue of Weapon Enchantments") -> Catalogue of Weapon Enchantments | B88: N | C88: N | D88: N | N88: - | O88: Yvonne Bienne, Synod researcher | P88: A guide to various enchantments that can be bound to weapons. | Q88: 50 | R88: Skill Book - Enchanting
A89: =HYPERLINK("http://en.uesp.net/wiki/Skyrim:Cats_of_Skyrim","Cats of Skyrim") -> Cats of Skyrim | B89: N | C89: N | D89: N | N89: 2 | O89: Aldetuile | P89: A brief treatise on the few felines that can be found in Skyrim | Q89: 7 | R89: Book
A90: =HYPERLINK("http://en.uesp.net/wiki/Skyrim:Chance%27s_Folly","Chance's Folly") -> Chance's Folly | B90: N | C90: N | D90: N | N90: 2 | O90: Zylmoc Golge | P90: The folly of a double-crosser | Q90: 6 | R90: Book
A91: =HYPERLINK("https://en.uesp.net/wiki/Skyrim:Changed_Ones", "Changed Ones (DB)") -> Changed Ones (DB) | B91: N | C91: N | D91: N | N91: 3 | O91: Anonymous/Unknown | P91: Story of how Boethiah refuted Trinimac | Q91: 11 | R91: Book
A92: =HYPERLINK("http://en.uesp.net/wiki/Skyrim:Charwich-Koniinge_Letters,_v1","Charwich-Koniinge Letters, v1") -> Charwich-Koniinge Letters, v1 | B92: N | C92: N | D92: N | N92: 3 | O92: Charwich | P92: A series of letters between Charwich and his friend Koniinge written during their search for Azura's Star. | Q92: 13 | R92: Book
A93: =HYPERLINK("http://en.uesp.net/wiki/Skyrim:Charwich-Koniinge_Letters,_v3","Charwich-Koniinge Letters, v3") -> Charwich-Koniinge Letters, v3 | B93: N | C93: N | D93: N | N93: 3 | O93: Charwich | P93: Letters between Charwich and Koniinge about their search for Azura's Star. | Q93: 13 | R93: Book
A94: =HYPERLINK("http://en.uesp.net/wiki/Skyrim:Charwich-Koniinge_Letters,_v4","Charwich-Koniinge Letters, v4") -> Charwich-Koniinge Letters, v4 | B94: N | C94: N | D94: N | N94: 4 | O94: Syrix Goinithi | P94: Letters between Charwich and Koniinge about their search for Azura's Star. | Q94: 13 | R94: Book
A95: =HYPERLINK("http://en.uesp.net/wiki/Skyrim:Charwich-Koniinge,_v2","Charwich-Koniinge, v2") -> Charwich-Koniinge, v2 | B95: N | C95: N | D95: N | N95: 3 | O95: Koniinge | P95: Letters between Charwich and Koniinge about their search for Azura's Star. | Q95: 13 | R95: Book
A96: =HYPERLINK("http://en.uesp.net/wiki/Skyrim:Chaurus_Pie:_A_Recipe","Chaurus Pie: A Recipe") -> Chaurus Pie: A Recipe | B96: N | C96: N | D96: N | N96: 3 | O96: Nils | P96: A recipe for a pie from chaurus meat | Q96: 11 | R96: Book
A97: =HYPERLINK("http://en.uesp.net/wiki/Skyrim:Cherim%27s_Heart","Cherim's Heart") -> Cherim's Heart | B97: N | C97: N | D97: N | N97: - | O97: Livillus Perus, Professor at the Imperial University | P97: Interview with Cherim, a master tapestry weaver | Q97: 70 | R97: Skill Book - Smithing
A98: =HYPERLINK("https://en.uesp.net/wiki/Skyrim:Children_of_the_All-Maker","Children of the all-maker (DB)") -> Children of the all-maker (DB) | B98: N | C98: N | D98: N | N98: 3 | O98: Tharstan of Solitude | P98: An outsider's accounting of the Skaal | Q98: 11 | R98: Book
A99: =HYPERLINK("http://en.uesp.net/wiki/Skyrim:Children_of_the_Sky","Children of the Sky") -> Children of the Sky | B99: N | C99: N | D99: N | N99: 4 | O99: Anonymous/Unknown | P99: A description of the Nords and the Thu'um | Q99: 25 | R99: Book
A100: =HYPERLINK("http://en.uesp.net/wiki/Skyrim:Chimarvamidium","Chimarvamidium") -> Chimarvamidium | B100: N | C100: N | D100: N | N100: 4 | O100: Marobar Sul | P100: Book 6 of a series of fictional stories about the Dwemer | Q100: 70/20 | R100: Skill Book - Heavy Armor
...

Sheet Collectible Items
A1: Bugs in a Jar | D1: Dragon Claws | G1: Treasure Maps (Map Only) | J1: Miscellaneous | M1: Paragons (DG)
A2: Collected? | B2: Item Name | C2: Location | D2: Collected? | E2: Item Name | F2: Related Quest | G2: Collected? | H2: Item Name | I2: Location | J2: Collected? | K2: Item Name | L2: Location | M2: Collected? | N2: Item Name | O2: Location
A3: =((countif(A4:A8,"Y")/5)) -> 0 | B3: - | C3: - | D3: =((countif(D4:D13,"Y")/10)) -> 0 | E3: - | F3: - | G3: =((countif(G4:G15,"Y")/12)) -> 0 | H3: - | I3: - | J3: =((countif(J4:J31,"Y")/ROWS(J4:J31))) -> 0 | K3: - | L3: - | M3: =((countif(M4:M8,"Y")/5)) -> 0 | N3: - | O3: -
A4: N | B4: =HYPERLINK("https://en.uesp.net/wiki/Skyrim:Miscellaneous_Items#Bee_in_a_Jar","Bee in a Jar") -> Bee in a Jar | C4: =HYPERLINK("https://en.uesp.net/wiki/Skyrim:Goldenglow_Estate","Goldenglow Estate") -> Goldenglow Estate | D4: N | E4: =HYPERLINK("https://en.uesp.net/wiki/Skyrim:Quest_Items#Coral_Dragon_Claw","Coral Dragon Claw") -> Coral Dragon Claw | F4: =HYPERLINK("https://en.uesp.net/wiki/Skyrim:Yngol%27s_Barrow","Yngol's Barrow ") -> Yngol's Barrow | G4: N | H4: =HYPERLINK("https://en.uesp.net/wiki/Skyrim:Treasure_Map_I","Treasure Map I") -> Treasure Map I | I4: Found at unmarked bandit camp just south of the Guardian Stones. | J4: N | K4: =HYPERLINK("https://en.uesp.net/wiki/Skyrim:Quest_Items#Amethyst_Claw.2C_Left_Half","Amethyst Claw, Left Half (DB)") -> Amethyst Claw, Left Half (DB) | L4: =HYPERLINK("https://en.uesp.net/wiki/Skyrim:Lost_Legacy","""Lost Legacy"" quest") -> "Lost Legacy" quest | M4: N | N4: =HYPERLINK("https://en.uesp.net/wiki/Skyrim:Amethyst_Paragon","Amethyst Paragon") -> Amethyst Paragon | O4: =HYPERLINK("https://en.uesp.net/wiki/Skyrim:Forgotten_Vale","Forgotten Vale") -> Forgotten Vale
A5: N | B5: =HYPERLINK("https://en.uesp.net/wiki/Skyrim:Miscellaneous_Items#Butterfly_in_a_Jar","Butterfly in a Jar") -> Butterfly in a Jar | C5: =HYPERLINK("https://en.uesp.net/wiki/Skyrim:Alchemist%27s_Shack","Alchemist's Shack") -> Alchemist's Shack | D5: N | E5: =HYPERLINK("https://en.uesp.net/wiki/Skyrim:Quest_Items#Diamond_Claw","Diamond Claw") -> Diamond Claw | F5: =HYPERLINK("https://en.uesp.net/wiki/Skyrim:The_World-Eater%27s_Eyrie","The World-Eater's Eyrie") -> The World-Eater's Eyrie | G5: N | H5: =HYPERLINK("https://en.uesp.net/wiki/Skyrim:Treasure_Map_II","Treasure Map II") -> Treasure Map II | I5: Found at Journeyman's Nook southeast of Winterhold. | J5: N | K5: =HYPERLINK("https://en.uesp.net/wiki/Skyrim:Quest_Items#Amethyst_Claw.2C_Right_Half","Amethyst Claw, Right Half (DB)") -> Amethyst Claw, Right Half (DB) | L5: =HYPERLINK("https://en.uesp.net/wiki/Skyrim:Lost_Legacy","""Lost Legacy"" quest") -> "Lost Legacy" quest | M5: N | N5: =HYPERLINK("https://en.uesp.net/wiki/Skyrim:Diamond_Paragon","Diamond Paragon") -> Diamond Paragon | O5: =HYPERLINK("https://en.uesp.net/wiki/Skyrim:Forgotten_Vale","Forgotten Vale") -> Forgotten Vale
A6: N | B6: =HYPERLINK("https://en.uesp.net/wiki/Skyrim:Miscellaneous_Items#Dragonfly_in_a_Jar","Dragonfly in a Jar") -> Dragonfly in a Jar | C6: =HYPERLINK("https://en.uesp.net/wiki/Skyrim:Burguk%27s_Longhouse","Burguk's Longhouse") -> Burguk's Longhouse | D6: N | E6: =HYPERLINK("https://en.uesp.net/wiki/Skyrim:Quest_Items#Ebony_Claw","Ebony Claw") -> Ebony Claw | F6: =HYPERLINK("https://en.uesp.net/wiki/Skyrim:The_Jagged_Crown_(Imperial)","The Jagged Crown") -> The Jagged Crown | G6: N | H6: =HYPERLINK("https://en.uesp.net/wiki/Skyrim:Treasure_Map_III","Treasure Map III") -> Treasure Map III | I6: Found at Riverside Shack west of Kynesgrove. | J6: N | K6: =HYPERLINK("https://en.uesp.net/wiki/Skyrim:Ancient_Traveler%27s_Skull","Ancient Traveler's Skull") -> Ancient Traveler's Skull | L6: =HYPERLINK("https://en.uesp.net/wiki/Skyrim:Wayward_Pass","Wayward Pass") -> Wayward Pass | M6: N | N6: =HYPERLINK("https://en.uesp.net/wiki/Skyrim:Emerald_Paragon","Emerald Paragon") -> Emerald Paragon | O6: =HYPERLINK("https://en.uesp.net/wiki/Skyrim:Forgotten_Vale","Forgotten Vale") -> Forgotten Vale
A7: N | B7: =HYPERLINK("https://en.uesp.net/wiki/Skyrim:Miscellaneous_Items#Moth_in_a_Jar","Moth in a Jar") -> Moth in a Jar | C7: =HYPERLINK("https://en.uesp.net/wiki/Skyrim:Duskglow_Crevice","Duskglow Crevice") -> Duskglow Crevice | D7: N | E7: =HYPERLINK("https://en.uesp.net/wiki/Skyrim:Quest_Items#Emerald_Dragon_Claw","Emerald Dragon Claw") -> Emerald Dragon Claw | F7: =HYPERLINK("https://en.uesp.net/wiki/Skyrim:Forbidden_Legend","Forbidden Legend") -> Forbidden Legend | G7: N | H7: =HYPERLINK("https://en.uesp.net/wiki/Skyrim:Treasure_Map_IV","Treasure Map IV") -> Treasure Map IV | I7: Found inside Redoran's Retreat northwest of Whiterun. | J7: N | K7: =HYPERLINK("https://en.uesp.net/wiki/Skyrim:Aretino_Family_Heirloom","Aretino Family Heirloom") -> Aretino Family Heirloom | L7: =HYPERLINK("https://en.uesp.net/wiki/Skyrim:Innocence_Lost", """Innocence Lost"" quest") -> "Innocence Lost" quest | M7: N | N7: =HYPERLINK("https://en.uesp.net/wiki/Skyrim:Ruby_Paragon","Ruby Paragon") -> Ruby Paragon | O7: =HYPERLINK("https://en.uesp.net/wiki/Skyrim:Forgotten_Vale","Forgotten Vale") -> Forgotten Vale
A8: N | B8: =HYPERLINK("https://en.uesp.net/wiki/Skyrim:Miscellaneous_Items#Torchbug_in_a_Jar","Torchbug in a Jar") -> Torchbug in a Jar | C8: =HYPERLINK("https://en.uesp.net/wiki/Skyrim:Frostflow_Lighthouse","Frostflow Lighthouse") -> Frostflow Lighthouse | D8: N | E8: =HYPERLINK("https://en.uesp.net/wiki/Skyrim:Quest_Items#Glass_Claw","Glass Claw") -> Glass Claw | F8: =HYPERLINK("https://en.uesp.net/wiki/Skyrim:Siege_on_the_Dragon_Cult","Siege on the Dragon Cult") -> Siege on the Dragon Cult | G8: N | H8: =HYPERLINK("https://en.uesp.net/wiki/Skyrim:Treasure_Map_V","Treasure Map V") -> Treasure Map V | I8: Found at Angi's Camp south of Falkreath. | J8: N | K8: =HYPERLINK("https://en.uesp.net/wiki/Skyrim:Quest_Items#Attunement_Sphere","Attunement Sphere") -> Attunement Sphere | L8: =HYPERLINK("https://en.uesp.net/wiki/Skyrim:Discerning_the_Transmundane","""Discerning the Transmundane"" quest") -> "Discerning the Transmundane" quest | M8: N | N8: =HYPERLINK("https://en.uesp.net/wiki/Skyrim:Sapphire_Paragon","Sapphire Paragon") -> Sapphire Paragon | O8: =HYPERLINK("https://en.uesp.net/wiki/Skyrim:Forgotten_Vale","Forgotten Vale") -> Forgotten Vale
D9: N | E9: =HYPERLINK("https://en.uesp.net/wiki/Skyrim:Quest_Items#Golden_Claw","Golden Claw") -> Golden Claw | F9: =HYPERLINK("https://en.uesp.net/wiki/Skyrim:The_Golden_Claw","The Golden Claw") -> The Golden Claw | G9: N | H9: =HYPERLINK("https://en.uesp.net/wiki/Skyrim:Treasure_Map_VI","Treasure Map VI") -> Treasure Map VI | I9: Found on corpse on top of a mountain SE of Shrine of Mehrunes Dagon and west of Stonehill Bluff. | J9: N | K9: =HYPERLINK("https://en.uesp.net/wiki/Skyrim:Balbus%27s_Fork", "Balbus's Fork") -> Balbus's Fork | L9: Given to you by Balbus if you have Gourmet's Writ of Passage. Can be stolen from him.
D10: N | E10: =HYPERLINK("https://en.uesp.net/wiki/Skyrim:Quest_Items#Iron_Claw","Iron Claw") -> Iron Claw | F10: =HYPERLINK("https://en.uesp.net/wiki/Skyrim:Evil_in_Waiting","Evil in Waiting") -> Evil in Waiting | G10: N | H10: =HYPERLINK("https://en.uesp.net/wiki/Skyrim:Treasure_Map_VII","Treasure Map VII") -> Treasure Map VII | I10: Found at Traitor's Post east of Windhelm. | J10: N | K10: =HYPERLINK("https://en.uesp.net/wiki/Skyrim:Quest_Items#Canticle_Bark","Canticle Bark (DG)") -> Canticle Bark (DG) | L10: =HYPERLINK("https://en.uesp.net/wiki/Skyrim:Unseen_Visions","""Unseen Visions"" quest") -> "Unseen Visions" quest
D11: N | E11: =HYPERLINK("https://en.uesp.net/wiki/Skyrim:Quest_Items#Ivory_Dragon_Claw","Ivory Dragon Claw") -> Ivory Dragon Claw | F11: =HYPERLINK("https://en.uesp.net/wiki/Skyrim:Forbidden_Legend","Forbidden Legend") -> Forbidden Legend | G11: N | H11: =HYPERLINK("https://en.uesp.net/wiki/Skyrim:Treasure_Map_VIII","Treasure Map VIII") -> Treasure Map VIII | I11: Found on Dead Hunter southeast of Bleakcoast Cave east of Winterhold. | J11: N | K11: =HYPERLINK("https://en.uesp.net/wiki/Skyrim:Quest_Items#Control_Cube","Control Cube (DB)") -> Control Cube (DB) | L11: =HYPERLINK("https://en.uesp.net/wiki/Skyrim:The_Path_of_Knowledge","""The Path of Knowledge"" quest. 5 copies.") -> "The Path of Knowledge" quest. 5 copies.
